Workbook

Sheet 2013-14
C1: octobre | D1: novembre | E1: décembre | F1: janvier | G1: février | H1: mars | I1: avril | J1: mai | K1: juin | L1: juillet | M1: août | N1: septembre
A2: toutain | B2: 47000 | D2: 25000 | E2: 22000
D3: 31686 | E3: 15141
A4: maurice | B4: 31462 | D4: 20000 | F4: 20700
D5: 10751 | F5: 24190
A6: landron | B6: 21110 | D6: 12000 | E6: 9110 | F6: 4000 | G6: 4000
D7: 6428 | E7: 10450 | G7: 4217
A8: leloup | B8: 34990 | D8: 15000 | F8: 19990
D9: 12264 | F9: 22276
A10: mary etienne | B10: 7013 | E10: 7013
E11: 7013
A12: lefebvre letourneur | B12: 2277 | D12: 2277
D13: 2277
A14: delacotte | B14: 4736 | E14: 1551 | G14: 3407
E15: 1551 | G15: 3407
A16: fablet | B16: 1209 | D16: 1209
D17: 1209
A18: foulquier leveziel | B18: 9448 | D18: 9448
D19: 9448
A20: marie toit mondeville | B20: 12155 | H20: 12155
H21: 16461
A22: dechauffour | B22: 60000 | F22: 20000 | G22: 20000 | I22: 20000
F23: 15114 | G23: 20145 | I23: 17593
A24: moulinet | B24: 42000 | G24: 20000 | I24: 11000 | K24: 12627
G25: 18475 | I25: 18026 | K25: 12172
A26: lycée malherbe | B26: 1500 | D26: 1500
D27: 1500
A28: feve damien | B28: 7000 | D28: 3000 | E28: 4000
D29: 4325 | E29: 2604
A30: mme etienne martine | B30: 7958 | D30: 4500 | E30: 3500
D31: 4772 | E31: 3186
A32: urban | B32: 55060 | E32: 15000 | I32: 17000 | J32: 10000 | L32: 10000
E33: 18362 | I33: 14190 | J33: 12702 | L33: 11624
A34: rf girard-marais | B34: 4911 | D34: 4911
D35: 4911
A36: pasquet menuiseries | B36: 2995 | D36: 2995 | I36: 314 | J36: 1214
D37: 2995 | I37: 314 | J37: 1214
A38: dauvergne | B38: 15084 | E38: 4000 | G38: 4752 | H38: 6300
E39: 5295 | G39: 4752 | H39: 8430
A40: carre | B40: 797 | G40: 797
G41: 797
A42: mariepierre(ancerne | B42: 10800 | E42: 3474 | H42: 10800
E43: 3474 | H43: 3500
C45: 92000
A46: hervieu | B46: 15362 | H46: 10000 | J46: 5362
H47: 10855 | J47: 4507
A48: sarl sosson depot repar | B48: 28691 | E48: 28691
E49: 28691
A50: sarl sosson sci galou | B50: 9415 | E50: 9415
E51: 9415
A52: suard 32000 | B52: 32000
A54: memet kilick | B54: 4180 | F54: 4180
F55: 4180
A56: josse | B56: 485 | F56: 485
F57: 485
A58: benoist yohann | B58: 56902 | I58: 15000 | K58: 15000 | L58: 20000
I59: 17025 | K59: 8986 | L59: 18335
A60: guilbert thales | B60: 27031 | J60: 7000
J61: 7628
A62: bicard-burlot | B62: 2503 | I62: 2503
I63: 2503
A64: eoles aventures | B64: 3049 | H64: 3049
H65: 3049
A66: chaventre | B66: 54201 | J66: 15000 | L66: 20000
J67: 16717 | L67: 14755
A68: cfab cotonnière | B68: 3249 | I68: 3249
I69: 3249
A70: viglieri | B70: 15000 | I70: 5000 | J70: 5000 | K70: 4700
I71: 5883 | J71: 6573 | K71: 3854
A72: bisson | B72: 54277 | K72: 15000 | N72: 9056
K73: 14793 | N73: 9056
A74: foulon firma | B74: 11100 | K74: 3000 | L74: 6000 | N74: 2000
K75: 2934 | L75: 4235 | N75: 3159
A76: mairie bretteville | B76: 5734 | K76: 5734
K77: 5734
A78: bouyguesifs | B78: 56000 | K78: 20000 | M78: 28696 | N78: 10184
K79: 17120 | M79: 28696 | N79: 3313
A80: talmar | B80: 10000 | J80: 10000
J81: 10000
A82: isoplaf | B82: 9000 | J82: 9000
J83: 9000
A84: selle iso ite | B84: 19150 | M84: 6500 | N84: 12600
M85: 6366 | N85: 12784
A86: viquesnel mob | B86: 56000 | L86: 15000 | N86: 17500
L87: 16078 | N87: 18689
A88: freire daniel | B88: 14000 | K88: 5000 | L88: 5000
K89: 4163 | L89: 6956
A90: legarrec terrasse | B90: 3281 | L90: 3281
L91: 3281
A92: res fam rabout | B92: 5200 | K92: 5200
K93: 5201
A94: HERVIEU report oct14
A96: bonneau | B96: 5980 | N96: 3981
N97: 3981
A98: rf guillot | B98: 12100 | N98: 12100
N99: 12100
A100: perin | B100: 18450 | M100: 6115 | N100: 6000
M101: 6115 | N101: 7125
A114: Total mensuel prévisionnel | C114: =C2+C4+C6+C8+C10+C12+C14+C16+C18+C20+C22+C24+C26+C28+C30+C32+C34+C36+C38+C40+C42+C44+C46+C48+C50+C52+C54+C56+C58+C60+C62+C64+C66+C68+C70+C72+C74+C76+C78+C80+C82+C84+C86+C88+C90+C92+C94+C96+C98+C100+C102+C104+C106+C108+C110+C112 -> 0 | D114: =D2+D4+D6+D8+D10+D12+D14+D16+D18+D20+D22+D24+D26+D28+D30+D32+D34+D36+D38+D40+D42+D44+D46+D48+D50+D52+D54+D56+D58+D60+D62+D64+D66+D68+D70+D72+D74+D76+D78+D80+D82+D84+D86+D88+D90+D92+D94+D96+D98+D100+D102+D104+D106+D108+D110+D112 -> 101840 | E114: =E2+E4+E6+E8+E10+E12+E14+E16+E18+E20+E22+E24+E26+E28+E30+E32+E34+E36+E38+E40+E42+E44+E46+E48+E50+E52+E54+E56+E58+E60+E62+E64+E66+E68+E70+E72+E74+E76+E78+E80+E82+E84+E86+E88+E90+E92+E94+E96+E98+E100+E102+E104+E106+E108+E110+E112 -> 107754 | F114: =F2+F4+F6+F8+F10+F12+F14+F16+F18+F20+F22+F24+F26+F28+F30+F32+F34+F36+F38+F40+F42+F44+F46+F48+F50+F52+F54+F56+F58+F60+F62+F64+F66+F68+F70+F72+F74+F76+F78+F80+F82+F84+F86+F88+F90+F92+F94+F96+F98+F100+F102+F104+F106+F108+F110+F112 -> 69355 | G114: =G2+G4+G6+G8+G10+G12+G14+G16+G18+G20+G22+G24+G26+G28+G30+G32+G34+G36+G38+G40+G42+G44+G46+G48+G50+G52+G54+G56+G58+G60+G62+G64+G66+G68+G70+G72+G74+G76+G78+G80+G82+G84+G86+G88+G90+G92+G94+G96+G98+G100+G102+G104+G106+G108+G110+G112 -> 52956 | H114: =H2+H4+H6+H8+H10+H12+H14+H16+H18+H20+H22+H24+H26+H28+H30+H32+H34+H36+H38+H40+H42+H44+H46+H48+H50+H52+H54+H56+H58+H60+H62+H64+H66+H68+H70+H72+H74+H76+H78+H80+H82+H84+H86+H88+H90+H92+H94+H96+H98+H100+H102+H104+H106+H108+H110+H112 -> 42304 | I114: =I2+I4+I6+I8+I10+I12+I14+I16+I18+I20+I22+I24+I26+I28+I30+I32+I34+I36+I38+I40+I42+I44+I46+I48+I50+I52+I54+I56+I58+I60+I62+I64+I66+I68+I70+I72+I74+I76+I78+I80+I82+I84+I86+I88+I90+I92+I94+I96+I98+I100+I102+I104+I106+I108+I110+I112 -> 74066 | J114: =J2+J4+J6+J8+J10+J12+J14+J16+J18+J20+J22+J24+J26+J28+J30+J32+J34+J36+J38+J40+J42+J44+J46+J48+J50+J52+J54+J56+J58+J60+J62+J64+J66+J68+J70+J72+J74+J76+J78+J80+J82+J84+J86+J88+J90+J92+J94+J96+J98+J100+J102+J104+J106+J108+J110+J112 -> 62576 | ... N114: =N2+N4+N6+N8+N10+N12+N14+N16+N18+N20+N22+N24+N26+N28+N30+N32+N34+N36+N38+N40+N42+N44+N46+N48+N50+N52+N54+N56+N58+N60+N62+N64+N66+N68+N70+N72+N74+N76+N78+N80+N82+N84+N86+N88+N90+N92+N94+N96+N98+N100+N102+N104+N106+N108+N110+N112 -> 73421
A115: Total mensuel | C115: =C3+C5+C7+C9+C11+C13+C15+C17+C19+C21+C23+C25+C27+C29+C31+C33+C35+C37+C39+C41+C43+C45+C47+C49+C51+C53+C55+C57+C59+C61+C63+C65+C67+C69+C71+C73+C75+C77+C79+C81+C83+C85+C87+C89+C91+C93+C95+C97+C99+C101+C103+C105+C107+C109+C111+C113 -> 92000 | D115: =D3+D5+D7+D9+D11+D13+D15+D17+D19+D21+D23+D25+D27+D29+D31+D33+D35+D37+D39+D41+D43+D45+D47+D49+D51+D53+D55+D57+D59+D61+D63+D65+D67+D69+D71+D73+D75+D77+D79+D81+D83+D85+D87+D89+D91+D93+D95+D97+D99+D101+D103+D105+D107+D109+D111+D113 -> 92566 | E115: =E3+E5+E7+E9+E11+E13+E15+E17+E19+E21+E23+E25+E27+E29+E31+E33+E35+E37+E39+E41+E43+E45+E47+E49+E51+E53+E55+E57+E59+E61+E63+E65+E67+E69+E71+E73+E75+E77+E79+E81+E83+E85+E87+E89+E91+E93+E95+E97+E99+E101+E103+E105+E107+E109+E111+E113 -> 105182 | F115: =F3+F5+F7+F9+F11+F13+F15+F17+F19+F21+F23+F25+F27+F29+F31+F33+F35+F37+F39+F41+F43+F45+F47+F49+F51+F53+F55+F57+F59+F61+F63+F65+F67+F69+F71+F73+F75+F77+F79+F81+F83+F85+F87+F89+F91+F93+F95+F97+F99+F101+F103+F105+F107+F109+F111+F113 -> 66245 | G115: =G3+G5+G7+G9+G11+G13+G15+G17+G19+G21+G23+G25+G27+G29+G31+G33+G35+G37+G39+G41+G43+G45+G47+G49+G51+G53+G55+G57+G59+G61+G63+G65+G67+G69+G71+G73+G75+G77+G79+G81+G83+G85+G87+G89+G91+G93+G95+G97+G99+G101+G103+G105+G107+G109+G111+G113 -> 51793 | H115: =H3+H5+H7+H9+H11+H13+H15+H17+H19+H21+H23+H25+H27+H29+H31+H33+H35+H37+H39+H41+H43+H45+H47+H49+H51+H53+H55+H57+H59+H61+H63+H65+H67+H69+H71+H73+H75+H77+H79+H81+H83+H85+H87+H89+H91+H93+H95+H97+H99+H101+H103+H105+H107+H109+H111+H113 -> 42295 | I115: =I3+I5+I7+I9+I11+I13+I15+I17+I19+I21+I23+I25+I27+I29+I31+I33+I35+I37+I39+I41+I43+I45+I47+I49+I51+I53+I55+I57+I59+I61+I63+I65+I67+I69+I71+I73+I75+I77+I79+I81+I83+I85+I87+I89+I91+I93+I95+I97+I99+I101+I103+I105+I107+I109+I111+I113 -> 78783 | J115: =J3+J5+J7+J9+J11+J13+J15+J17+J19+J21+J23+J25+J27+J29+J31+J33+J35+J37+J39+J41+J43+J45+J47+J49+J51+J53+J55+J57+J59+J61+J63+J65+J67+J69+J71+J73+J75+J77+J79+J81+J83+J85+J87+J89+J91+J93+J95+J97+J99+J101+J103+J105+J107+J109+J111+J113 -> 68341 | ... N115: =N3+N5+N7+N9+N11+N13+N15+N17+N19+N21+N23+N25+N27+N29+N31+N33+N35+N37+N39+N41+N43+N45+N47+N49+N51+N53+N55+N57+N59+N61+N63+N65+N67+N69+N71+N73+N75+N77+N79+N81+N83+N85+N87+N89+N91+N93+N95+N97+N99+N101+N103+N105+N107+N109+N111+N113 -> 70207
...

Sheet 2014-15
A1: Noms | B1: CA prévu | C1: octobre | D1: novembre | E1: décembre | F1: janvier | G1: février | H1: mars | I1: avril | J1: mai | K1: juin | L1: juillet | M1: août | N1: septembre
A2: guilbert thales | B2: 20031 | D2: 17446 | E2: 2585
D3: 17446 | E3: 2776
A4: chaventre | D4: 19000
D5: 25862
A6: bisson | D6: 16000 | G6: 15000
D7: 13076 | G7: 14668
A8: mazonni | B8: 11095 | D8: 3680 | F8: 7415 | H8: 2321
D9: 3680 | F9: 7415 | H9: 2321
A10: chaignet -dubois | B10: 65149 | C10: 11357 | D10: 11241 | E10: 21387 | F10: 5195 | G10: 10000 | H10: 5969
C11: 11357 | D11: 11241 | E11: 21387 | F11: 5195 | G11: 7088 | H11: 3880
A12: saillard | B12: 56109 | C12: 10476 | F12: 15428 | G12: 5312 | H12: 14720 | I12: 7230 | K12: 1122
C13: 10476 | F13: 15428 | G13: 5312 | H13: 14720 | I13: 7230 | K13: 1122
A14: dumont cocain | B14: 3838
A16: dumont lelong | B16: 11645 | E16: 5000 | F16: 6645
C17: 2387 | E17: 3464 | F17: 5794
A18: freire olivier | B18: 36354 | E18: 8507 | F18: 9682 | I18: 18000 | N18: 285
E19: 8507 | F19: 9682 | I19: 17389 | J19: 2310 | N19: 285
A20: freire bozec | B20: 27221 | C20: 6306 | D20: 2090 | G20: 9541 | H20: 9284
C21: 6306 | D21: 2090 | G21: 9541 | H21: 9284
A22: lemauf | B22: 2674 | D22: 2674
D23: 2674
A24: lemasle reno | B24: 33800 | D24: 10796 | G24: 21595
D25: 10796 | G25: 21595
A26: jeanne françoise | B26: 2000
A28: isoplaf devaux charp | B28: 11186 | C28: 3806 | E28: 7380
C29: 3806 | E29: 7379
A30: breteau mob | B30: 52000 | I30: 10750 | K30: 22144 | L30: 6926 | N30: 12180
I31: 10750 | K31: 22144 | L31: 6926 | N31: 13167
A32: scournec jean max | B32: 4806 | H32: 521 | J32: 4285
H33: 521 | J33: 4400
A34: rocton mob | B34: 16335 | C34: 7130 | E34: 4873 | G34: 4332
C35: 7130 | E35: 4873 | G35: 5071
A36: michel vinc mob | B36: 17702 | C36: 5000 | D36: 5000 | F36: 7702
C37: 4964 | D37: 4860 | F37: 11703
A38: perin | B38: 6800 | C38: 6800
C39: 3206
A40: viquesnel | B40: 23500 | C40: 23500
C41: 16329
A42: freire daniel | B42: 4000 | D42: 4000
D43: 3037
A44: deigneuret parquet | B44: 1895 | D44: 1895
D45: 1895 | U45: 1
A46: hervieu st sylvain | B46: 2370 | D46: 2370 | U46: 2
D47: 2370 | U47: 2
A48: bellenger mob | B48: 18288 | G48: 4194 | H48: 8094 | I48: 6000 | U48: 2
G49: 4194 | H49: 6509 | I49: 7187 | U49: 2
A50: comm pasquet | D50: 1148 | E50: 1005 | G50: 1590 | H50: 294 | K50: 256 | L50: 2387 | N50: 449 | U50: 2
D51: 1148 | E51: 1005 | G51: 1590 | H51: 294 | K51: 256 | L51: 2387 | N51: 449
A52: BENOIST YO | B52: 11254 | C52: 11254
C53: 10067 | U53: =SUM(U45:U52) -> 11
A54: cointo charpente | B54: 11475 | I54: 4300 | L54: 7175
I55: 4300 | L55: 7175
A56: scp michel | B56: 6936 | C56: 4000 | D56: 2936
C57: 4720 | D57: 2936
A58: desfeux reno | B58: 14437 | F58: 6485 | G58: 7952
F59: 6485 | G59: 7952
A60: besnier mob | B60: 14690 | D60: 2557 | E60: 4300 | F60: 7833
D61: 2557 | E61: 3589 | F61: 4196 | H61: 4348
A62: cauvin | B62: 7000 | G62: 2333 | H62: 4667
G63: 2333 | H63: 4667
A64: magny renov | B64: 49000 | J64: 14696 | K64: 17676 | L64: 16628
J65: 14696 | K65: 17676 | L65: 16631
A66: bondurand | B66: 14380 | I66: 10000 | J66: 5255 | K66: 4380
I67: 4745 | J67: 8203 | K67: 1586
A68: renouard | B68: 11453 | J68: 10000 | K68: 1453
J69: 3803 | K69: 8311
A70: RF rault renouf | B70: 6507 | H70: 6507
H71: 6507
A72: aec ref heckel | B72: 14665 | H72: 5123 | I72: 9542
H73: 5123 | I73: 9147
A74: ricateau | B74: 1221
A76: la taverne andre | B76: 4008 | N76: 2858
N77: 1805
A78: carre olivier | B78: 14194 | K78: 14194
A80: rf croteau | B80: 5245 | N80: 5245
N81: 5245
A82: rf letourneur | B82: 2496 | I82: 2496
I83: 2496
A84: daigremont | B84: 4707 | M84: 4707
M85: 4707
A86: antoine ferreira | B86: 15000 | N86: 6000
N87: 6563
A88: pinçon | B88: 68041
A90: regnauld | B90: 37806 | N90: 10000
N91: 10800
A92: foulon firma | B92: 1163 | I92: 1163
I93: 1163
A94: gardie david | B94: 3289 | I94: 3289
I95: 3289
A96: le mistral | B96: 1700 | I96: 1700
I97: 1700
A98: moblefevre manuel | B98: 30920 | M98: 9154 | N98: 21000
M99: 9154 | N99: 21766
A100: mob auber | B100: 10810 | M100: 10810
M101: 10810
A102: chebout mousset | B102: 9622 | J102: 2860 | K102: 4872 | N102: 1890
J103: 2860 | K103: 4872 | N103: 1890
A104: garnier | B104: 8044 | J104: 3030 | K104: 5014
J105: 3030 | K105: 5014
...

Sheet 2015-16
C1: OCTOBRE | E1: NOVEMBRE | G1: DECEMBRE | I1: JANVIER | K1: FEVRIER | M1: MARS | O1: AVRIL | Q1: MAI | S1: JUIN | U1: JUILLET | W1: AOUT | Y1: SEPTEMBRE
A2: NOM | B2: CA/contrat | C2: prévu | D2: réalisé | E2: prévu | F2: réalisé | G2: prévu | H2: réalisé | I2: prévu | J2: réalisé | K2: prévu | L2: réalisé | M2: prévu | N2: réalisé | O2: prévu | P2: réalisé | Q2: prévu | R2: réalisé | S2: prévu | T2: réalisé | U2: prévu | V2: réalisé | W2: prévu | X2: réalisé | Y2: prévu | Z2: réalisé
A3: PASQUET commission | B3: 5199 | C3: 1848 | D3: 1848 | E3: 148 | F3: 148 | G3: 1642 | H3: 1287 | I3: 619 | J3: 1297 | K3: 619 | L3: 619 | M3: 1329 | N3: 1329 | S3: 378 | T3: 378 | Y3: 1218 | Z3: 1218
A4: SARL ferme du parc | B4: 1150
A5: Antoine Ferrera POPUP | B5: 8434 | G5: 5980 | H5: 5980 | K5: 4780 | L5: 4780
A6: Lefevre | B6: 56714 | C6: 20000 | D6: 19302 | E6: 15000 | F6: 30798 | G6: 3643 | H6: 2080 | K6: 2608 | L6: 2608
A7: Auber | B7: 39190 | G7: 14257 | H7: 14257 | I7: 15661 | J7: 15661 | K7: 1920 | L7: 1920 | Q7: 9272 | R7: 8693
A8: Poret Caval | B8: 1400 | C8: 1400 | D8: 1481
A9: Bouet | B9: 25254 | E9: 25254 | F9: 25254
A10: Hebert | B10: 20556 | G10: 7488 | H10: 7488 | K10: 6050 | L10: 6050 | M10: 7018 | N10: 6062
A11: Chérance | B11: 15550 | C11: 5000 | D11: 5296 | G11: 5000 | H11: 9024 | I11: 5550 | J11: 1178
A12: Regnault | B12: 27006 | G12: 8246 | H12: 8246 | I12: 6693 | J12: 6693 | K12: 9566 | L12: 9566
A13: PINCON | B13: 68041 | E13: 9261 | F13: 9261 | K13: 22548 | L13: 22548 | M13: 20466 | N13: 20466 | O13: 15766 | P13: 15766
A14: ROUILLE | B14: 21439 | E14: 5221 | F14: 5221 | I14: 1755 | J14: 1755 | K14: 11478 | L14: 11478 | M14: 2985 | N14: 3120
A15: ESNAULT | B15: 12722 | E15: 3885 | F15: 3885 | G15: 8837 | H15: 8837
A16: MALECOT | B16: 11800 | C16: 5000 | D16: 3540 | G16: 6800 | H16: 6800
A17: CARRE | B17: 14194 | S17: 4864 | T17: 4864 | Y17: 9330 | Z17: 9330
A18: LA TAVERNE | B18: 1050 | C18: 1050 | D18: 1053
A19: RAVENEL | B19: 31153 | S19: 10000 | T19: 10012 | U19: 15949 | V19: 15949 | Y19: 11533 | Z19: 11728
A20: APAEI | B20: 1550 | C20: 1550 | D20: 1550
A21: MARAIS
A22: RF JACQUELIN | B22: 7038 | C22: 7038 | D22: 7038
A23: RF JARDIN | B23: 20133 | K23: 2440 | L23: 2440 | O23: 17693 | P23: 17693
A24: DENIS Archiviolette | B24: 65528 | K24: 17967 | L24: 17967 | M24: 27033 | N24: 21802 | Q24: 20528 | R24: 22487
A25: CHAPRON | B25: 44827 | Q25: 8097 | R25: 8097 | U25: 23395 | V25: 23395 | Y25: 13335
A26: RF MELENNE | B26: 5170 | E26: 5170 | F26: 5170
A27: AASSGARD | B27: 400 | C27: 400 | D27: 400
A28: SCI LA JALOUSIE | B28: 6445 | C28: 2600 | D28: 2600 | K28: 3495 | L28: 3495
A29: SBTP BIHEL | B29: 7503 | S29: 7503 | T29: 7503
A30: VALDENAIRE | B30: 10588 | E30: 3940 | F30: 3940 | G30: 6648 | H30: 6648
A31: GRUAU | B31: 950 | G31: 950 | H31: 950
A32: RF LEMETTEIL | B32: 6400 | G32: 6400 | H32: 6400
A33: RF VICQUELIN | B33: 5523 | I33: 5523 | J33: 5523
A34: SCI GALOU | B34: 2177 | E34: 2177 | F34: 2177
A35: PRIGENT | B35: 275 | E35: 275 | F35: 275
A36: RF SEYMOUR | B36: 12000 | I36: 12000 | J36: 12293
A37: EARL FERME DU PARC | B37: 11798 | K37: 4379 | L37: 4379 | M37: 7419 | N37: 7419
A38: RF LESENECHAL | B38: 6835 | I38: 6835 | J38: 6835
A39: RF HGP | B39: 4375 | M39: 4375 | N39: 4375
A40: SARL ESNAULT LES MARINAS | B40: 47975 | O40: 16312 | P40: 16312 | Q40: 22782 | R40: 22782 | S40: 8880 | T40: 8880
A41: DAUMESNIL | B41: 23622 | O41: 5122 | P41: 5122 | S41: 18500 | T41: 18500
A42: CORTEQUISSE ext | B42: 25230 | Y42: 25230 | Z42: 5664
A43: JORIS GIRARD | B43: 5360 | M43: 5360 | N43: 5360
A44: SAITER | B44: 4524 | M44: 4524 | N44: 4524
A45: BUNEL terrasse | B45: 2570 | Q45: 2570 | R45: 2570
A46: REANULT 2B peinture | B46: 2900 | O46: 1300 | P46: 1300 | S46: 1600 | T46: 1600
A47: DUVAL à moult | B47: 25000 | Y47: 25000
A48: RF CORNILLE | B48: 8871 | O48: 8246 | P48: 8246 | Q48: 625 | R48: 625
A49: DUBOIS CHAIGNET | B49: 2625 | S49: 2625 | T49: 2625
A50: RF LOHARD | B50: 6717 | Q50: 6717 | R50: 6717
A51: RF MANGION | B51: 6830 | Q51: 6830 | R51: 6830
A52: RF RICHARD | B52: 5146 | Q52: 5146 | R52: 5146
A53: LEBOUCHER ext | B53: 10976 | Q53: 3246 | R53: 3243 | U53: 7733 | V53: 7733
A54: ROSELIER | B54: 14259 | Q54: 2567 | R54: 2567 | S54: 5112 | T54: 5112 | Y54: 6600 | Z54: 2231
A55: BILLE francois | B55: 5756 | O55: 2700 | P55: 2700 | S55: 3056 | T55: 3056
A56: BOUILLARD | B56: 13155 | S56: 4249 | T56: 4249 | W56: 6809 | X56: 6809
A57: DE SOUSA | B57: 9005 | W57: 2253 | X57: 2253
A58: TANGUY | B58: 3015 | O58: 1050 | P58: 1050 | S58: 1965 | T58: 1965
A59: L'audacieuse | B59: 2467 | Q59: 2467 | R59: 2467
A60: corbion | B60: 4518 | Y60: 4518 | Z60: 4518
A61: BACON | B61: 19636 | W61: 5000 | X61: 5000
A62: lotton | B62: 4509 | Y62: 4509 | Z62: 4509
A63: SAMSON | B63: 9596
A64: GASTON samuel | B64: 7288 | S64: 1394 | T64: 1394 | U64: 3069 | V64: 3069 | Y64: 2824 | Z64: 2824
A65: SOCHON | B65: 12340 | U65: 3409 | V65: 3409 | W65: 3581 | X65: 3581 | Y65: 5349 | Z65: 5349
A66: CHAUVEL | B66: 28500 | U66: 16786 | V66: 16786 | W66: 5000 | X66: 4250 | Y66: 6712 | Z66: 7406
A67: LEMANISSIER | B67: 10874 | Y67: 2278 | Z67: 2278
A68: LEYEUCH | B68: 2878 | U68: 2878 | V68: 2878
A69: GOUESLARD | B69: 7492
A70: rf SORTON | B70: 8334 | U70: 8000 | V70: 8000
A71: rf tardif | B71: 7347
A72: jouannot | B72: 7331 | U72: 1126.8 | V72: 1127 | Y72: 2676 | Z72: 2676
A73: stab | B73: 2950 | Y73: 2950 | Z73: 2250
A74: guilloux | B74: 2980 | U74: 2980 | V74: 2980 | Y74: 850 | Z74: 850
A75: rf sabatier | B75: 9882 | Y75: 9882 | Z75: 9967
A76: rf russ | B76: 7987 | Y76: 7987 | Z76: 7987 | AA76: TOTAL
A77: sarl ecs bretteville | B77: 15500 | W77: 7540 | X77: 7540 | Y77: 7960
A78: GODIN | B78: 1521 | U78: 1521 | V78: 1521
A79: fossey | B79: 550 | Y79: 550 | Z79: 550
A80: jegou | B80: 510 | W80: 510 | X80: 510 | AA80: TOTAL
A81: TOTAL CA mensuel prévu | B81: =SUM(B3:B80) -> 978893 | C81: =SUM(C3:C80) -> 45886 | E81: =SUM(E3:E80) -> 70331 | G81: =SUM(G3:G80) -> 75891 | I81: =SUM(I3:I80) -> 54636 | K81: =SUM(K3:K80) -> 87850 | M81: =SUM(M3:M80) -> 80509 | O81: =SUM(O3:O80) -> 68189 | Q81: =SUM(Q3:Q80) -> 90847 | S81: =SUM(S3:S80) -> 70126 | U81: =SUM(U3:U80) -> 86846.8 | W81: =SUM(W3:W80) -> 30693 | Y81: =SUM(Y3:Y80) -> 151291 | AA81: =SUM(C81:Z81) -> 913095.8 | AB81: prévu
A82: TOTAL CA mensuel réalisé | D82: =SUM(D3:D81) -> 44108 | F82: =SUM(F3:F81) -> 86129 | H82: =SUM(H3:H81) -> 77997 | J82: =SUM(J3:J81) -> 51235 | L82: =SUM(L3:L81) -> 87850 | N82: =SUM(N3:N81) -> 74457 | P82: =SUM(P3:P81) -> 68189 | R82: =SUM(R3:R81) -> 92224 | T82: =SUM(T3:T81) -> 70138 | V82: =SUM(V3:V81) -> 86847 | X82: =SUM(X3:X81) -> 29943 | Z82: =SUM(Z3:Z81) -> 81335 | AA82: =SUM(C82:Z82) -> 850452 | AB82: réalisé
A83: TOTAL CA prévu cumulé | C83: =C81 -> 45886 | E83: =E81+C83 -> 116217 | G83: =G81+E83 -> 192108 | I83: =I81+G83 -> 246744 | K83: =K81+I83 -> 334594 | M83: =M81+K83 -> 415103 | O83: =O81+M83 -> 483292 | Q83: =Q81+O83 -> 574139 | S83: =S81+Q83 -> 644265 | U83: =U81+S83 -> 731111.8 | W83: =W81+U83 -> 761804.8 | Y83: =Y81+W83 -> 913095.8
A84: TOTAL CA réalisé cumulé | D84: =D82 -> 44108 | F84: =F82+D84 -> 130237 | H84: =H82+F84 -> 208234 | J84: =J82+H84 -> 259469 | L84: =L82+J84 -> 347319 | N84: =N82+L84 -> 421776 | P84: =P82+N84 -> 489965 | R84: =R82+P84 -> 582189 | T84: =T82+R84 -> 652327 | V84: =V82+T84 -> 739174 | X84: =X82+V84 -> 769117 | Z84: =Z82+X84 -> 850452
A88: Cumul CA réalisé 2014-15 | C88: ='2014-15'!C156 -> 80748 | E88: ='2014-15'!D156 -> 186416 | G88: ='2014-15'!E156 -> 239396 | I88: ='2014-15'!F156 -> 305294 | K88: ='2014-15'!G156 -> 384638 | M88: ='2014-15'!H156 -> 442812 | O88: ='2014-15'!I156 -> 512208 | Q88: ='2014-15'!J156 -> 553811 | S88: ='2014-15'!K156 -> 631730 | U88: ='2014-15'!L156 -> 727094 | W88: ='2014-15'!M156 -> 763646 | Y88: ='2014-15'!N156 -> 888339
A89: Cumul CA réalisé 2015-16 | D89: =D84 -> 44108 | F89: =F84 -> 130237 | H89: =H84 -> 208234 | J89: =J84 -> 259469 | L89: =L84 -> 347319 | N89: =N84 -> 421776 | P89: =P84 -> 489965 | R89: =R84 -> 582189 | T89: =T84 -> 652327 | V89: =V84 -> 739174 | X89: =X84 -> 769117 | Z89: =Z84 -> 850452
A90: % évolution année n-1

Sheet 2016-17
C1: OCTOBRE | E1: NOVEMBRE | G1: DECEMBRE | I1: JANVIER | K1: FEVRIER | M1: MARS | O1: AVRIL | Q1: MAI | S1: JUIN | U1: JUILLET | W1: AOUT | Y1: SEPTEMBRE
A2: NOM | B2: CA/contrat | C2: prévu | D2: réalisé | E2: prévu | F2: réalisé | G2: prévu | H2: réalisé | I2: prévu | J2: réalisé | K2: prévu | L2: réalisé | M2: prévu | N2: réalisé | O2: prévu | P2: réalisé | Q2: prévu | R2: réalisé | S2: prévu | T2: réalisé | U2: prévu | V2: réalisé | W2: prévu | X2: réalisé | Y2: prévu | Z2: réalisé
A3: PASQUET commission
C5: 45000 | D5: 45000 | E5: 55000 | F5: 55000 | G5: 68000 | H5: 68000 | I5: 22000 | J5: 22000 | K5: 82000 | L5: 82000 | M5: 92000 | N5: 92000 | O5: 90000 | P5: 90000 | Q5: 92000 | R5: 92000 | S5: =30000+9000+15000+5000+15000+9000+5000+2400+4800+4000 -> 99200 | T5: 90000
A6: pasquet menuiseries | U6: 498 | V6: 498 | Y6: 1313 | Z6: 1313
A7: letourneur | B7: =74015-17000 -> 57015 | U7: 20000 | V7: 25578 | Y7: 15000 | Z7: 14337
A8: college sacre cœur | B8: 76016 | U8: 10000 | V8: 15000 | W8: 28000 | X8: 21816 | Y8: 0
A9: suard | B9: =1048+15880 -> 16928 | U9: 16928 | V9: 16928
A10: marie nadine | B10: 19445 | U10: 10000 | V10: 10946 | W10: 4500 | X10: 5637 | Y10: 2860 | Z10: 2860
A11: delahayes | B11: 12193 | U11: 10179 | V11: 10179 | Y11: 2014 | Z11: 2014
A12: poulain | B12: 30680 | Y12: 30684 | Z12: 30684
A13: cointo | B13: 3893 | Y13: 3893 | Z13: 3893
A14: hamon | B14: 4864 | Y14: 0
A15: cardet | B15: 3999 | Y15: 3999 | Z15: 3999
A16: le de | B16: 14352 | W16: 3240 | X16: 3847 | Y16: 0
A17: marie stephanie | B17: 39384 | Y17: 24817 | Z17: 24817
A18: hamel extension | B18: 27017 | Y18: 18609 | Z18: 18609
A19: hamel reno | B19: =7089+5638+7097 -> 19824 | U19: 7097 | V19: 12015 | Y19: 0
A20: defibat | B20: 6400 | W20: 6400 | X20: 6400
A21: huard | B21: 47234 | Y21: 13278 | Z21: 13278
A22: queron | B22: 102917
A23: james | B23: 31500
A24: peltier | B24: 228880
A25: perret | B25: 26120
A26: guiboux | B26: 92161
A27: lefevre | B27: 150000
A28: duquenoy | B28: 32915
A29: leclerc charp | B29: 7775
A30: bugenne | B30: 10191
A31: skrzypeck | B31: 14934 | Y31: 4000 | Z31: 4070 | AA31: TOTAL
AA35: TOTAL
A36: TOTAL CA mensuel prévu | B36: =SUM(B3:B35) -> 1076637 | C36: =SUM(C3:C35) -> 45000 | E36: =SUM(E3:E35) -> 55000 | G36: =SUM(G3:G35) -> 68000 | I36: =SUM(I3:I35) -> 22000 | K36: =SUM(K3:K35) -> 82000 | M36: =SUM(M3:M35) -> 92000 | O36: =SUM(O3:O35) -> 90000 | Q36: =SUM(Q3:Q35) -> 92000 | S36: =SUM(S3:S35) -> 99200 | U36: =SUM(U3:U35) -> 74702 | W36: =SUM(W3:W35) -> 42140 | Y36: =SUM(Y3:Y35) -> 120467 | AA36: =SUM(C36:Z36) -> 882509 | AB36: prévu
A37: TOTAL CA mensuel réalisé | D37: =SUM(D3:D36) -> 45000 | F37: =SUM(F3:F36) -> 55000 | H37: =SUM(H3:H36) -> 68000 | J37: =SUM(J3:J36) -> 22000 | L37: =SUM(L3:L36) -> 82000 | N37: =SUM(N3:N36) -> 92000 | P37: =SUM(P3:P36) -> 90000 | R37: =SUM(R3:R36) -> 92000 | T37: =SUM(T3:T36) -> 90000 | V37: =SUM(V3:V36) -> 91144 | X37: =SUM(X3:X36) -> 37700 | Z37: =SUM(Z3:Z36) -> 119874 | AA37: =SUM(C37:Z37) -> 884718 | AB37: réalisé
A38: TOTAL CA prévu cumulé | C38: =C36 -> 45000 | E38: =E36+C38 -> 100000 | G38: =G36+E38 -> 168000 | I38: =I36+G38 -> 190000 | K38: =K36+I38 -> 272000 | M38: =M36+K38 -> 364000 | O38: =O36+M38 -> 454000 | Q38: =Q36+O38 -> 546000 | S38: =S36+Q38 -> 645200 | U38: =U36+S38 -> 719902 | W38: =W36+U38 -> 762042 | Y38: =Y36+W38 -> 882509
A39: TOTAL CA réalisé cumulé | D39: =D37 -> 45000 | F39: =F37+D39 -> 100000 | H39: =H37+F39 -> 168000 | J39: =J37+H39 -> 190000 | L39: =L37+J39 -> 272000 | N39: =N37+L39 -> 364000 | P39: =P37+N39 -> 454000 | R39: =R37+P39 -> 546000 | T39: =T37+R39 -> 636000 | V39: =V37+T39 -> 727144 | X39: =X37+V39 -> 764844 | Z39: =Z37+X39 -> 884718
A43: Cumul CA réalisé 2015-16 | D43: 45886 | F43: 116217 | H43: 192108 | J43: 246744 | L43: 334594 | N43: 415103 | P43: 483292 | R43: 574139 | T43: 644265 | V43: 731112 | X43: 761055 | Z43: 842390
A44: Cumul CA réalisé 2016-17 | D44: =D39 -> 45000 | F44: =F39 -> 100000 | H44: =H39 -> 168000 | J44: =J39 -> 190000 | L44: =L39 -> 272000 | N44: =N39 -> 364000 | P44: =P39 -> 454000 | R44: =R39 -> 546000 | T44: =T39 -> 636000 | V44: =V39 -> 727144 | X44: =X39 -> 764844 | Z44: =Z39 -> 884718
A45: % évolution année n-1

Sheet 2017-18
D1: OCTOBRE | F1: NOVEMBRE | H1: DECEMBRE | J1: JANVIER | L1: FEVRIER | N1: MARS | P1: AVRIL | R1: MAI | T1: JUIN | V1: JUILLET | X1: AOUT | Z1: SEPTEMBRE
A2: NOM | B2: CA/contrat | C2: CA/prevision | D2: prévu | E2: réalisé | F2: prévu | G2: réalisé | H2: prévu | I2: réalisé | J2: prévu | K2: réalisé | L2: prévu | M2: réalisé | N2: prévu | O2: réalisé | P2: prévu | Q2: réalisé | R2: prévu | S2: réalisé | T2: prévu | U2: réalisé | V2: prévu | W2: réalisé | X2: prévu | Y2: réalisé | Z2: prévu | AA2: réalisé
A3: PASQUET commission | T3: 149.55 | U3: 149.55
A5: pasquet menuiseries | B5: 3164 | C5: 3164 | D5: 608 | E5: 608 | F5: 2375.31 | G5: 2375 | H5: 575.01 | I5: 575 | L5: 333 | M5: 333 | N5: 685 | O5: 685 | V5: =368.1+447.52+335.7+484.41+479.54+363.41 -> 2478.68 | W5: 2479
A6: letourneur | B6: 28591.66 | C6: =21791.66+6800 -> 28591.66 | D6: 0 | F6: 8000 | G6: 8000 | H6: =3288+3767 -> 7055 | I6: 7055 | J6: 6736 | K6: 6736 | P6: 6828 | Q6: 6828
A7: college sacre cœur | B7: =39850.23 -> 39850.23 | C7: 39850.23 | D7: 31322 | E7: 31322 | F7: 8528.01 | G7: 9057.18
A8: hamon | C8: 4864 | D8: 0 | E8: 0 | T8: 0
A9: le de | B9: =11642.56-3847.2 -> 7795.36 | C9: =11642.56-3847.2 -> 7795.36 | D9: 7795 | E9: 7795
A10: marie stephanie | B10: =39384.42-24817.18 -> 14567.24 | C10: =39384.42-24817.18 -> 14567.24 | D10: 12567 | E10: 12567 | F10: 2000 | G10: 2000
A11: hamel extension | B11: 14170 | C11: 14170 | F11: 9833 | G11: 9833 | H11: 2850 | I11: 2850
A12: hamel reno | B12: 6770 | C12: 6770 | F12: 6770 | G12: 6770
A13: huard | B13: =47234.29-13278.17 -> 33956.12 | C13: =47234.29-13278.17 -> 33956.12 | F13: 33956.22 | G13: 33956
A14: queron | B14: 102917.19 | C14: 102917.19 | F14: 14971 | G14: 14971 | J14: 0 | N14: 31989 | O14: 31989 | P14: 30990.1 | Q14: 30990.1 | R14: 11863.1 | S14: 11863 | T14: 7054 | U14: 7054 | V14: 6048 | W14: 6048
A15: james | B15: 26240 | C15: 26640 | H15: 5072 | I15: 5072 | J15: 0 | L15: 6722 | M15: 6722 | N15: 4673 | O15: 4673 | P15: 8090 | Q15: 8090 | T15: 2082 | U15: 2082
A16: peltier | B16: 256701 | C16: 256701 | D16: 56000 | E16: 56000 | F16: 0 | H16: 45000 | I16: 45000 | J16: 0 | L16: 51027 | M16: 51027 | N16: 13901 | O16: 13901 | P16: 0 | Q16: 0 | R16: 26817.63 | S16: 26818 | T16: =26223+7269 -> 33492 | U16: 33492 | V16: 20069.23 | W16: 20069.23 | X16: 4048 | Z16: 10000
A17: perree | B17: 22450 | C17: 22450 | F17: 0 | H17: 6735 | I17: 6735 | J17: 0 | L17: 15715 | M17: 15715
A18: guiboux | C18: 92161.48
A19: lefevre | C19: 149882.03
A20: duquenoy | C20: =58285.49+10077.21 -> 68362.7
A21: De Souza | B21: 7392.42 | C21: =B21 -> 7392.42 | H21: 0 | L21: 7392 | M21: 7392
A22: bugenne | B22: 10191 | C22: 10191 | H22: 0 | J22: 0 | L22: 0 | T22: 10191 | U22: 10191
A23: skrzypeck | B23: =14189.06-4000 -> 10189.06 | C23: =14189.06-4000 -> 10189.06 | F23: 5390 | G23: 5390 | H23: 4614 | I23: 4614 | J23: 0
A24: henry ifs | B24: 27194.72 | C24: 27194.72 | F24: 0 | H24: 27194 | I24: 27194 | J24: 0
A25: desnos | B25: 9838 | C25: 9838 | H25: 9838 | I25: 9838
A26: mickaelis | B26: 31084 | C26: 31084 | F26: 5111 | G26: 5111 | H26: 25973 | I26: 25973
A27: bacon | B27: 36487 | C27: 36487 | N27: 0 | P27: 14404 | Q27: 14404 | R27: 15574 | S27: 15574 | T27: 0 | V27: =2900+3200 -> 6100 | W27: 6100
A28: hoste | B28: 55000 | C28: 55000 | F28: 0 | H28: 11238 | I28: 11238 | J28: 0 | L28: 30431 | M28: 30431 | N28: 13329 | O28: 13329
A29: louiche | B29: =C29 -> 14947 | C29: 14947 | P29: 3924 | Q29: 3924 | T29: 11023 | U29: 11023 | AB29: TOTAL
A30: rf goubin | B30: 1500 | C30: 1500 | J30: 0 | N30: 1500 | O30: 1500
A31: patrignani | B31: 3176 | C31: =B31 -> 3176 | D31: 3171 | E31: 3171
A32: FAUNY | B32: 20037.29 | C32: 20037.29 | N32: 11789 | O32: 11789 | P32: 8248 | Q32: 8248
A33: JARDIN via C. CABARET | C33: 122716.9
A34: crosfit | B34: 1000 | C34: 1000 | P34: 1000 | Q34: 1000
A35: rf ablin | B35: 10956 | C35: 10956 | P35: 10956 | Q35: 10956
A36: pezant | B36: 2484 | C36: 2484 | N36: 2484 | O36: 2484
A37: Rousseau | B37: 44277 | C37: 44277 | R37: 11580.24 | S37: 11580 | T37: 10812.39 | U37: 10812.39 | V37: 18998.89 | W37: 18998.89 | X37: 1938 | Z37: 947
A38: thomann | B38: 4085 | C38: 4085 | N38: 4085 | O38: 4085
A39: Gabriel | B39: 65791.68 | C39: =B39 -> 65791.68 | P39: 0 | R39: 20315.52 | S39: 20316 | T39: 0 | V39: 13168.94 | W39: 13168.94 | X39: 9897 | Z39: 10000
A40: ccs international | B40: 8232 | C40: 8232 | T40: 8232 | U40: 8232
A41: lequitte | B41: 790.4 | C41: 790.4 | L41: 790 | M41: 790
A42: pelloin | B42: 6038 | C42: 6038 | R42: 1811.6 | S42: 1812 | T42: 4227.06 | U42: 4227.06
A43: mealet | B43: 4299 | C43: 4299 | P43: 4299 | Q43: 4299
A44: camping | B44: 7135.16 | C44: 7135.16 | R44: 7135.16 | S44: 7135
A45: sci fill st sylvain | B45: 34606 | C45: 34606 | T45: 9697 | U45: 9697 | V45: 9104.27 | W45: 9104 | X45: 3000 | Z45: 12805
A46: euromatec | B46: 1266 | C46: 1266.4 | P46: 1266 | Q46: 1266
A47: ledorze | B47: 14681.81 | C47: 14681.81 | R47: 4404.54 | S47: 4405 | T47: 0 | V47: 3573.98 | W47: 3573.98
A48: lecomte | B48: 13725 | C48: 13725 | T48: 0 | V48: 13725 | W48: 13725
A49: bresson | B49: 17881 | C49: 17881 | R49: 6342 | S49: 6342 | T49: 11539 | U49: 11539
A50: MORLET blonville sur mer | B50: 79536 | C50: 79536.61 | X50: 17747 | Z50: 14931
A51: bihel sbtp | B51: 1285 | C51: 1285 | J51: 1285 | K51: 1285
A52: estorges | B52: 16070.35 | C52: 16070 | T52: 0 | V52: 12810 | W52: 12810 | X52: 0 | Z52: 3260
A53: rf plancher | B53: 1200 | C53: 1200 | L53: 1200 | M53: 1200
A54: josse | B54: 291 | C54: 291 | L54: 291 | M54: 291
A55: Germain | B55: 107313 | C55: 107313
A56: Morotti | B56: =C56 -> 12732.3 | C56: 12732.3 | X56: 4048 | Z56: 8684
A57: martin | B57: 3441 | C57: 3441 | P57: 3441 | Q57: 3441
A58: taillepied | B58: 8169 | C58: 8169 | R58: 8169 | S58: 8169
A59: naceur | B59: 2676 | C59: 2676 | P59: 2676 | Q59: 2676
A60: QUEMENER | B60: 44671 | C60: 44671 | T60: 5332 | U60: 5332 | Z60: 15060.238
A61: vandermersch | B61: 3191.95 | C61: 3191 | T61: 3192 | U61: 3192
A62: GOULAIN | B62: 10448 | C62: 10448 | Z62: 5000
A63: AMCM | B63: 480 | C63: 480 | V63: 480 | W63: 480
AB67: TOTAL
A68: TOTAL CA mensuel prévu | B68: =SUM(B3:B67) -> 1312961.9 | C68: =SUM(C3:C67) -> 1751348.8 | D68: =SUM(D3:D67) -> 111463 | F68: =SUM(F3:F67) -> 96934.54 | H68: =SUM(H3:H67) -> 146144.01 | J68: =SUM(J3:J67) -> 8021 | L68: =SUM(L3:L67) -> 113901 | N68: =SUM(N3:N67) -> 84435 | P68: =SUM(P3:P67) -> 96122.1 | R68: =SUM(R3:R67) -> 114012.79 | T68: =SUM(T3:T67) -> 117023 | V68: =SUM(V3:V67) -> 106556.99 | X68: =SUM(X3:X67) -> 40678 | Z68: =SUM(Z3:Z67) -> 80687.238 | AB68: =SUM(D68:AA68) -> 1115978.7 | AC68: prévu
A69: TOTAL CA mensuel réalisé | E69: =SUM(E3:E68) -> 111463 | G69: =SUM(G3:G68) -> 97463.18 | I69: =SUM(I3:I68) -> 146144 | K69: =SUM(K3:K68) -> 8021 | M69: =SUM(M3:M68) -> 113901 | O69: =SUM(O3:O68) -> 84435 | Q69: =SUM(Q3:Q68) -> 96122.1 | S69: =SUM(S3:S68) -> 114014 | U69: =SUM(U3:U68) -> 117023 | W69: =SUM(W3:W68) -> 106557.04 | Y69: =SUM(Y3:Y68) -> 0 | AA69: =SUM(AA3:AA68) -> 0 | AB69: =SUM(D69:AA69) -> 995143.32 | AC69: réalisé
A70: TOTAL CA prévu cumulé | D70: =D68 -> 111463 | F70: =F68+D70 -> 208397.54 | H70: =H68+F70 -> 354541.55 | J70: =J68+H70 -> 362562.55 | L70: =L68+J70 -> 476463.55 | N70: =N68+L70 -> 560898.55 | P70: =P68+N70 -> 657020.65 | R70: =R68+P70 -> 771033.44 | T70: =T68+R70 -> 888056.44 | V70: =V68+T70 -> 994613.43 | X70: =X68+V70 -> 1035291.4 | Z70: =Z68+X70 -> 1115978.7
A71: TOTAL CA réalisé cumulé | E71: =E69 -> 111463 | G71: =G69+E71 -> 208926.18 | I71: =I69+G71 -> 355070.18 | K71: =K69+I71 -> 363091.18 | M71: =M69+K71 -> 476992.18 | O71: =O69+M71 -> 561427.18 | Q71: =Q69+O71 -> 657549.28 | S71: =S69+Q71 -> 771563.28 | U71: =U69+S71 -> 888586.28 | W71: =W69+U71 -> 995143.32 | Y71: =Y69+W71 -> 995143.32 | AA71: =AA69+Y71 -> 995143.32
A75: Cumul CA réalisé 2016-17 | E75: 45000 | G75: 100000 | I75: 168000 | K75: 190000 | M75: 272000 | O75: 364000 | Q75: 454000 | S75: 546000 | U75: 636000 | W75: 727144 | Y75: 764844 | AA75: 847702
A76: Cumul CA réalisé 2017-18 | E76: =E71 -> 111463 | G76: =G71 -> 208926.18 | I76: =I71 -> 355070.18 | K76: =K71 -> 363091.18 | M76: =M71 -> 476992.18 | O76: =O71 -> 561427.18 | Q76: =Q71 -> 657549.28 | S76: =S71 -> 771563.28 | U76: =U71 -> 888586.28 | W76: =W71 -> 995143.32 | Y76: =Y71 -> 995143.32 | AA76: =AA71 -> 995143.32
A77: % évolution année n-1

Sheet 2018-19
D1: OCTOBRE | F1: NOVEMBRE | H1: DECEMBRE | J1: JANVIER | L1: FEVRIER | N1: MARS | P1: AVRIL | R1: MAI | T1: JUIN | V1: JUILLET | X1: AOUT | Z1: SEPTEMBRE
A2: NOM | B2: CA/contrat | C2: CA/prevision | D2: prévu | E2: réalisé | F2: prévu | G2: réalisé | H2: prévu | I2: réalisé | J2: prévu | K2: réalisé | L2: prévu | M2: réalisé | N2: prévu | O2: réalisé | P2: prévu | Q2: réalisé | R2: prévu | S2: réalisé | T2: prévu | U2: réalisé | V2: prévu | W2: réalisé | X2: prévu | Y2: réalisé | Z2: prévu | AA2: réalisé
A3: PASQUET commission | V3: 145 | W3: 145 | Z3: =916.9+1570 -> 2486.9 | AA3: =917+1570 -> 2487
A4: Commission ST | B4: 422 | C4: 422 | N4: 422 | O4: 422 | V4: =143+578 -> 721 | W4: 721 | X4: 578 | Y4: 578 | Z4: 738 | AA4: 738
A5: pasquet menuiseries
A6: PELTIER | B6: 7082 | C6: 7082 | F6: 0 | H6: 0 | J6: 0 | N6: 7562 | O6: 7562
A7: MORLET blonville sur mer | B7: 47889 | C7: =112.89+47776 -> 47888.89 | F7: 33590 | G7: 33590 | H7: 937 | I7: 937 | J7: =112.89+13217 -> 13329.89 | K7: 13330
A8: QUEMENER | B8: 25132 | C8: 25132 | D8: 0 | F8: 0 | H8: 10969 | I8: 10969 | J8: 14163 | K8: 14163
A9: GOULAIN | B9: 15973 | C9: 15973 | D9: 10333 | E9: 10333 | J9: 0 | L9: 3398 | M9: 3398 | N9: 0
A10: GUIBOUT | B10: =71065+5867 -> 76932 | C10: =71065+5867 -> 76932 | D10: 0 | F10: 0 | H10: 15997 | I10: 15997 | J10: 20524 | K10: 20524 | N10: 15454 | O10: 15454 | P10: 10336 | Q10: 10336 | Z10: =5871+5867 -> 11738 | AA10: =5871+5867 -> 11738
A11: GABRIEL | B11: 11184 | C11: 11184 | D11: 0 | F11: 0 | H11: 10592 | I11: 10592 | J11: 0 | N11: =382.54+1026.93 -> 1409.47 | O11: 1409
A12: GERMAIN | B12: 136516 | C12: 136516 | H12: 21166 | I12: 21166 | J12: 29539 | K12: 29539 | N12: 33628 | O12: 33628 | P12: 30034 | Q12: 30034 | R12: 6094.4 | S12: 6094 | T12: 11020 | U12: 11020 | V12: 5035 | W12: 5035
A13: LEDORZE | B13: 9088 | C13: =5603.29+3485 -> 9088.29 | D13: 9088 | E13: 9088
A14: SCI IFL | B14: 4967 | C14: 4967 | D14: 4967 | E14: 4967 | AB14: TOTAL
A15: SARL LA FOURNEE | C15: 7697 | F15: 0
A16: FERARD | B16: 52246 | C16: 52246 | F16: 0 | J16: 6265 | K16: 6265 | N16: 24109 | O16: 24109 | P16: 15667 | Q16: 15667
A18: SCI DES MOTTETS | B18: 10544 | C18: 10544 | H18: 4004 | I18: 4004 | J18: =5966.85+298.57+274.49 -> 6539.91 | K18: 6540
A19: MOREL | C19: 128702
A22: TALMAR | B22: 6420 | C22: 6420 | F22: 6420 | G22: 6420
A23: FOUREY | B23: 3963 | C23: 3963 | N23: 3963 | O23: 3963
A24: CHAMPION | B24: 1620 | C24: 1620 | D24: 1042 | E24: 1042 | J24: 0 | R24: 1620 | S24: 1620
A25: PAPILLON | B25: 16756 | C25: 16756 | J25: 3032.54 | K25: 3033 | N25: 13723 | O25: 13723
A26: LOPEZ | B26: 4221 | C26: 4221 | J26: 4221 | K26: 4221
A27: MANCHE | B27: 62896 | C27: 62896 | R27: 18868 | S27: 18868 | T27: 0 | V27: 19393 | W27: 19393 | Z27: 22852 | AA27: 22852
A28: MOROTTI | B28: 8451 | C28: 8451 | D28: 0 | F28: 8451 | G28: 8451
A29: DEFLIN | B29: 1372.46 | C29: 1372.46 | D29: 1372 | E29: 1372
F30: 0
A31: ESTORGES | B31: 1337 | C31: 1337 | F31: 0 | H31: 1337 | I31: 1337
A32: LASTELLE | B32: 29492 | C32: 29492 | J32: 9558 | K32: 9558 | N32: 19934 | O32: 19934
A33: VERGRIETE | B33: 50956 | C33: 50956 | X33: 14207 | Y33: 14207 | Z33: 0
A34: MARIE | B34: 81382 | C34: 81382 | X34: 15242 | Y34: 15242 | Z34: 14391 | AA34: 14391
A35: KITE SURF | C35: 54304 | Z35: 0
A36: GIRARD | C36: 79325
A38: CADIEU NOURY | C38: 86613
A39: FLAGUAIS | B39: 42611 | C39: 42611 | N39: 11365 | O39: 11365 | R39: 21018 | S39: 21018 | X39: 10226 | Y39: 10226
A40: BOUET | B40: 5336 | C40: =4056+1280 -> 5336 | L40: 5336 | M40: 5336
A41: DLH | C41: 26000
A42: JOLY | B42: 1438 | C42: 1438 | L42: 1438 | M42: 1438
A43: NOGENT | B43: 19583 | C43: 19583 | T43: 9463.47 | U43: 9463 | V43: 10119 | W43: 10119
A44: DARDE | B44: 31830 | C44: 31830 | R44: 10720 | S44: 10720 | T44: 14992 | U44: 14992 | V44: 4418 | W44: 4418
A45: DUPONT CHALESLE | B45: 72581 | C45: 72581 | T45: 11711 | U45: 11711 | V45: 28531 | W45: 28531 | Z45: 12690 | AA45: 12690
A46: GIRRE | B46: 13327 | C46: 13327 | P46: 13327 | Q46: 13327
A47: VAUCHER | C47: 30574
A48: LOZACH MARY | B48: 48438 | C48: 48438 | X48: 8670 | Y48: 8670 | Z48: 11550 | AA48: 11550
A50: LOBERGER | B50: 11536 | C50: 11536 | X50: 3060 | Y50: 3060 | Z50: 4286 | AA50: 4286
A51: SOFINAB (crocus) | B51: 29041 | C51: 29041 | P51: 29041 | Q51: 29041
A52: LE LOUARN | B52: 43362 | C52: 43632 | T52: 13089 | U52: 13089 | V52: 27895 | W52: 27895
A53: BILLET | B53: 15440 | C53: 15440 | P53: 3778 | Q53: 3778 | T53: 11662 | U53: 11662
A54: SINIGAGLIA | B54: 27156 | C54: 27156 | P54: 9974 | Q54: 9974 | Z54: 0
A55: DAGORN | B55: 91038 | C55: 91038
A56: MARABETTI | B56: 30150 | C56: 30150 | P56: 8508 | Q56: 8508 | T56: 21642 | U56: 21642
A57: AGELIA | B57: 3211 | C57: 3211 | R57: 3211 | S57: 3211
A58: ANQUETIL | B58: 11957 | C58: 11957
A59: SCI PRJ | C59: 5165
A60: rf ablin | B60: 491 | C60: 491 | R60: 491 | S60: 491
A61: LEVEQUE | C61: 116253
A62: COYER | C62: 40676
A63: LOCK QUEST | B63: 21652 | C63: 21652 | T63: 21652 | U63: 21652
A64: DE JEAN | B64: 1749 | C64: 1749 | V64: 1749 | W64: 1749
A65: LE MASSON | C65: 15702
A66: MAINCENT | C66: 28000
A67: ROHRBACH | B67: 38516 | C67: 38516 | Z67: 0
A68: JOUAULT | C68: 32089
A69: BRETEAU | B69: 36066 | C69: 36066 | X69: 10678 | Y69: 10678 | Z69: 12354 | AA69: 12354
A70: spie batignol | B70: 3077 | C70: 3077 | Z70: 3077 | AA70: 3077
A71: TESSON | B71: 118578 | C71: 118578 | Z71: 45274 | AA71: 45274 | AB71: TOTAL
A72: TOTAL CA mensuel prévu | B72: =SUM(B3:B71) -> 1385005.5 | C72: =SUM(C3:C71) -> 2036375.6 | D72: =SUM(D3:D71) -> 26802 | F72: =SUM(F3:F71) -> 48461 | H72: =SUM(H3:H71) -> 65002 | J72: =SUM(J3:J71) -> 107172.34 | L72: =SUM(L3:L71) -> 10172 | N72: =SUM(N3:N71) -> 131569.47 | P72: =SUM(P3:P71) -> 120665 | R72: =SUM(R3:R71) -> 62022.4 | T72: =SUM(T3:T71) -> 115231.47 | V72: =SUM(V3:V71) -> 98006 | X72: =SUM(X3:X71) -> 62661 | Z72: =SUM(Z3:Z71) -> 141436.9 | AB72: =SUM(D72:AA72) -> 989201.58 | AC72: prévu
A73: TOTAL CA mensuel réalisé | E73: =SUM(E3:E72) -> 26802 | G73: =SUM(G3:G72) -> 48461 | I73: =SUM(I3:I72) -> 65002 | K73: =SUM(K3:K72) -> 107173 | M73: =SUM(M3:M72) -> 10172 | O73: =SUM(O3:O72) -> 131569 | Q73: =SUM(Q3:Q72) -> 120665 | S73: =SUM(S3:S72) -> 62022 | U73: =SUM(U3:U72) -> 115231 | W73: =SUM(W3:W72) -> 98006 | Y73: =SUM(Y3:Y72) -> 62661 | AA73: =SUM(AA3:AA72) -> 141437 | AB73: =SUM(D73:AA73) -> 989201 | AC73: réalisé
A74: TOTAL CA prévu cumulé | D74: =D72 -> 26802 | F74: =F72+D74 -> 75263 | H74: =H72+F74 -> 140265 | J74: =J72+H74 -> 247437.34 | L74: =L72+J74 -> 257609.34 | N74: =N72+L74 -> 389178.81 | P74: =P72+N74 -> 509843.81 | R74: =R72+P74 -> 571866.21 | T74: =T72+R74 -> 687097.68 | V74: =V72+T74 -> 785103.68 | X74: =X72+V74 -> 847764.68 | Z74: =Z72+X74 -> 989201.58
A75: TOTAL CA réalisé cumulé | E75: =E73 -> 26802 | G75: =G73+E75 -> 75263 | I75: =I73+G75 -> 140265 | K75: =K73+I75 -> 247438 | M75: =M73+K75 -> 257610 | O75: =O73+M75 -> 389179 | Q75: =Q73+O75 -> 509844 | S75: =S73+Q75 -> 571866 | U75: =U73+S75 -> 687097 | W75: =W73+U75 -> 785103 | Y75: =Y73+W75 -> 847764 | AA75: =AA73+Y75 -> 989201
A79: Cumul CA réalisé 2017-18 | E79: ='2017-18'!E76 -> 111463 | G79: ='2017-18'!G76 -> 208926.18 | I79: ='2017-18'!I76 -> 355070.18 | K79: ='2017-18'!K76 -> 363091.18 | M79: ='2017-18'!M76 -> 476992.18 | O79: ='2017-18'!O76 -> 561427.18 | Q79: ='2017-18'!Q76 -> 657549.28 | S79: ='2017-18'!S76 -> 771563.28 | U79: ='2017-18'!U76 -> 888586.28 | W79: ='2017-18'!W76 -> 995143.32 | Y79: 1000486 | AA79: 1106623
A80: Cumul CA réalisé 2018-19 | E80: =E75 -> 26802 | G80: =G75 -> 75263 | I80: =I75 -> 140265 | K80: =K75 -> 247438 | M80: =M75 -> 257610 | O80: =O75 -> 389179 | Q80: =Q75 -> 509844 | S80: =S75 -> 571866 | U80: =U75 -> 687097 | W80: =W75 -> 785103 | Y80: =Y75 -> 847764 | AA80: =AA75 -> 989201
A81: % évolution année n-1 | AA81: =AA79/AA80 -> 1.1187039 | AB81: =AA8-12% -> -0.12

Sheet 2019-20
E1: OCTOBRE | G1: NOVEMBRE | I1: DECEMBRE | K1: JANVIER | M1: FEVRIER | O1: MARS | Q1: AVRIL | S1: MAI | U1: JUIN | W1: JUILLET | Y1: AOUT | AA1: SEPTEMBRE
A2: NOM | C2: CA/contrat | D2: CA/prevision | E2: prévu | F2: réalisé | G2: prévu | H2: réalisé | I2: prévu | J2: réalisé | K2: prévu | L2: réalisé | M2: prévu | N2: réalisé | O2: prévu | P2: réalisé | Q2: prévu | R2: réalisé | S2: prévu | T2: réalisé | U2: prévu | V2: réalisé | W2: prévu | X2: réalisé | Y2: prévu | Z2: réalisé | AA2: prévu | AB2: réalisé
A3: Commission PASQUET | C3: =882+300+1211 -> 2393 | D3: =882+300+1211 -> 2393 | G3: =423+459 -> 882 | H3: 882 | K3: 300 | L3: 300 | M3: 1211.1 | N3: 1211.1 | Q3: 715.41 | R3: 715.41 | U3: =276.26+1078.87 -> 1355.13 | V3: 1355 | AA3: 1334.3 | AB3: 1334.3
A4: Commission ST | C4: =1231+1000+564 -> 2795 | D4: 2795 | I4: 1000 | J4: 1000 | K4: 1230.87 | L4: 1230.87 | M4: 564.03 | N4: 564.03 | Q4: =988.4+183.02 -> 1171.42 | R4: 1171 | S4: =132.5+262.38 -> 394.88 | T4: 395 | W4: 934 | X4: 934
A6: GERNAULT - IBANESCU | D6: 97245 | AC6: =D6-U6-W6-Y6-AA6 -> 97245
A7: SCHIEL | D7: 137101 | AC7: =D7-U7-W7-Y7-AA7 -> 137101
A8: GEZE | D8: 46977 | AC8: =D8-U8-W8-Y8-AA8 -> 46977
A9: THIRE | D9: 45339 | AC9: =D9-U9-W9-Y9-AA9 -> 45339
A10: LEROULLIER | C10: 43205 | D10: 43205 | AC10: =D10-U10-W10-Y10-AA10 -> 43205
A11: CHESNEL | C11: 23403 | D11: 23403 | AC11: =D11-U11-W11-Y11-AA11 -> 23403
A12: RF ROUSSEL | C12: 51345 | D12: 51345 | AC12: =D12-U12-W12-Y12-AA12 -> 51345
A13: JAGER | C13: 70682 | D13: 70682 | AC13: =D13-U13-W13-Y13-AA13 -> 70682
A14: HULIN | C14: 35372 | D14: 35372.24 | AC14: =D14-U14-W14-Y14-AA14 -> 35372.24
A15: DARCILLON | D15: 68020 | AC15: =D15-U15-W15-Y15-AA15 -> 68020
A16: LALLOZ | C16: 4865.8 | D16: 4865.8 | AC16: 4865.8
A17: FROGER | C17: 1913 | D17: 1913 | AC17: 1913.88
A18: ROUILLARD | C18: 11993.73 | D18: 11993.73 | AC18: =D18-U18-W18-Y18-AA18 -> 11993.73
A19: BICARD | C19: 13428 | D19: 13428 | AC19: =D19-U19-W19-Y19-AA19 -> 13428
A20: BOEUVE | C20: 22297 | D20: 22297 | AC20: =D20-U20-W20-Y20-AA20 -> 22297
A21: GERMAIN | C21: 2019 | D21: 2019 | AC21: =D21-U21-W21-Y21-AA21 -> 2019
A22: ROUSSEL | C22: 86048 | D22: 86048 | Y22: 14221.6 | Z22: 14222 | AC22: =D22-U22-W22-Y22-AA22 -> 71826.4
A23: RF FLIPO | C23: 12911 | D23: 12911 | O23: 6053.31 | P23: 6053.31 | S23: 2073 | T23: 2073 | AC23: =D23-O23-S23-U23-W23-Y23-AA23 -> 4784.69
A24: SHACHER | C24: 35629 | D24: 35629.01 | W24: 9593.87 | X24: 9593.87 | AC24: =D24-U24-W24-Y24-AA24 -> 26035.14
A25: LEVEQUE GARAGE | C25: 16424.62 | D25: 16424.62 | W25: 3012.79 | X25: 3012.79 | AC25: =D25-U25-W25-Y25-AA25 -> 13411.83
A26: LEVEQUE | C26: =56621.6+90 -> 56711.6 | D26: =56621.6+90 -> 56711.6 | I26: =27727.11+2871.46 -> 30598.57 | J26: 30599 | K26: =5116.74+1825.21 -> 6941.95 | L26: 6942 | M26: 14328.36 | N26: 14328 | W26: =1260+3582.72 -> 4842.72 | X26: 4843 | AC26: =D26-I26-K26-M26-U26-W26-Y26-AA26 -> -1.8189894e-12
A27: DAGORN | C27: 60469 | D27: 60469 | W27: 18141.35 | X27: 18141.35 | AC27: =D27-U27-W27-Y27-AA27 -> 42327.65
A28: CAUCE via joris cenier | C28: 20274 | D28: 20274 | W28: 5109.75 | X28: 5109.75 | AC28: =D28-U28-W28-Y28-AA28 -> 15164.25
A29: DARDE | C29: =1700+2657 -> 4357 | D29: 4357 | S29: 2657.57 | T29: 2658 | AC29: =D29-S29-U29-W29-Y29-AA29 -> 1699.43
A30: BRODIN | C30: 27757 | D30: 27757 | Y30: 6161.14 | Z30: 6161.14 | AA30: 7658.33 | AB30: 7658.06 | AC30: =D30-U30-W30-Y30-AA30 -> 13937.53
A31: JOUAULT | C31: 21815.39 | D31: 21815.39 | AA31: 5291.09 | AB31: 5291.09 | AC31: =D31-U31-W31-Y31-AA31 -> 16524.3
A32: CHAUVEL | C32: 77453 | D32: 77453 | Y32: 15033.91 | Z32: 15034 | AA32: 18933.43 | AB32: 18933.43 | AC32: =D32-U32-W32-Y32-AA32 -> 43485.66
A33: SCI WATIER | C33: 36413 | D33: 36413 | AA33: =18113.56+11560.07 -> 29673.63 | AB33: =11560.07+18113.56 -> 29673.63 | AC33: =D33-U33-W33-Y33-AA33 -> 6739.37
A34: COYER | C34: =32007+368.45 -> 32375.45 | D34: 32375 | S34: 5652.23 | T34: 5652 | W34: 7196.88 | X34: 7197 | Y34: 5944.21 | Z34: 5944.21 | AA34: =6194.32+368.45 -> 6562.77 | AB34: 6563 | AC34: =D34-S34-U34-W34-Y34-AA34 -> 7018.91
A35: CADIEU NOURY | C35: =88130-2411.28+1388.91 -> 87107.63 | D35: =88130+1388.91-2411.28 -> 87107.63 | G35: 9456 | H35: 9456 | I35: 18664 | J35: 18664 | K35: 16738 | L35: 16737.55 | M35: 12574.17 | N35: 12574.17 | O35: 5332.53 | P35: 5332.53 | U35: 18992 | V35: 18992 | W35: 3425 | X35: 3425 | AA35: =D35-X35-V35-P35-N35-L35-J35-H35 -> 1926.38 | AB35: 1926 | AC35: =D35-G35-I35-K35-M35-O35-Q35-S35-U35-W35-Y35-AA35 -> -0.45
A36: MAINCENT | C36: 28887 | D36: 28887 | S36: 7157.29 | T36: 7157 | U36: 4298 | V36: 4298 | W36: 4501.84 | X36: 4502 | AA36: 12930 | AB36: 12930 | AC36: =D36-S36-U36-W36-Y36-AA36 -> -0.13
A37: SINIGAGLIA | C37: =17182+2877.27 -> 20059.27 | D37: =17182+2877.27 -> 20059.27 | U37: 9488 | V37: 9488 | W37: =14102.37-U37 -> 4614.37 | X37: 4614 | AA37: =3080+2877.27 -> 5957.27 | AB37: 5957 | AC37: =D37-U37-W37-Y37-AA37 -> -0.37
A38: RAOULT | C38: =106191.06+1844.06 -> 108035.12 | D38: 108035 | S38: 31760.01 | T38: 31760 | U38: 31208 | V38: 31208 | W38: 40428.81 | X38: 40429 | AA38: =D38-T38-V38-X38 -> 4638 | AB38: 4638 | AC38: =D38-S38-U38-W38-Y38-AA38 -> 0.18
A39: TESSON | C39: =68578+4726 -> 73304 | D39: 73304 | G39: 8735.21 | H39: 8735 | I39: 12421 | J39: 12421 | K39: 4746 | L39: 4746.41 | M39: 40465 | N39: 40465 | W39: =6937-9618.45 -> -2681.45 | X39: -2681 | AA39: =2964+1029.91 -> 3993.91 | AB39: 3994 | AC39: cee | AD39: 11500
A40: MAHE | C40: 458.33 | D40: 458.33 | AA40: 458 | AB40: 458
A41: EXAEQUO | C41: 1500 | D41: 1500 | AA41: 1500 | AB41: 1500
A42: LEROUX | C42: 2250 | D42: 2250 | AA42: 2250 | AB42: 2250
A43: PINCON | C43: 4198 | D43: 4198 | Y43: 4198 | Z43: 4198 | AC43: =D43-U43-W43-Y43-AA43 -> 0
A44: BROUARD | C44: 2835.36 | D44: 2835.36 | Y44: 2835 | Z44: 2835 | AC44: =D44-U44-W44-Y44-AA44 -> 0.36
A45: SOURDIN | C45: 878 | D45: 878 | Y45: 878 | Z45: 878
A46: ATILLA (Bardage) | C46: 255 | D46: 255 | W46: 255 | X46: 255 | AC46: =D46-U46-W46-Y46-AA46 -> 0
A47: HAMEL | C47: 5023 | D47: 5023 | W47: 5023 | X47: 5023
A48: ZAGHBOUNI | C48: =1945+1152+906 -> 4003 | D48: =3097+906 -> 4003 | U48: =576+1945 -> 2521 | V48: 2521 | W48: =3097-U48+906 -> 1482 | X48: 1482
A49: POTET | C49: 52582.92 | D49: 52582.92 | Q49: 12848 | R49: 12848 | U49: 26066 | V49: 26066 | W49: =D49-Q49-S49-U49 -> 13668.92 | X49: 13669
A50: DUBREUL | C50: =22311+5643 -> 27954 | D50: 27954 | O50: =2803.36+1797 -> 4600.36 | P50: =2803.36+1797 -> 4600.36 | S50: =6580.7+3131.41 -> 9712.11 | T50: 9712 | U50: =12150+715.48 -> 12865.48 | V50: 12865 | W50: =13642-U50 -> 776.52 | X50: 777
A51: AGREN | C51: 330 | D51: 330 | W51: 330 | X51: 330
A52: PREVEL | C52: =32080+5039 -> 37119 | D52: 37119 | O52: 11136.12 | P52: 11136.12 | Q52: 7185.75 | R52: 7185.75 | S52: =9988.44+3527.63 -> 13516.07 | T52: 13516 | W52: 5282 | X52: 5282
A53: PHILIPPE | C53: 4050 | D53: 4050 | S53: 1128.9 | T53: 1128.9 | U53: 2921 | V53: 2921
A54: GOSSET | C54: 18311 | D54: =17291+1143.46-123.29 -> 18311.17 | Q54: 2573.45 | R54: 2573.45 | S54: 7397.45 | T54: 7397 | U54: =7320.53+1143.46-123.29 -> 8340.7 | V54: 8341
A55: LE MASSON | C55: 16094 | D55: 16094 | O55: 4828.21 | P55: 4828.21 | Q55: 6905.12 | R55: 6905.12 | S55: 2048.38 | T55: 2048 | U55: =C55-O55-Q55-S55 -> 2312.29 | V55: 2312
A56: MARIE | C56: =51048-2700 -> 48348 | D56: =51048-2700 -> 48348 | E56: 15605 | F56: 15604.9 | G56: 7359.96 | H56: 7360 | I56: 10221 | J56: 10221 | K56: 2111.2 | L56: 2111.2 | O56: 8285.81 | P56: 8285.81 | S56: -442 | T56: -442
A57: GUIMOND | C57: =8400+450 -> 8850 | D57: 8850 | Q57: 2520 | R57: 2520 | U57: =5880+450 -> 6330 | V57: 6330
A58: CABOURG | C58: 5757 | D58: 5757 | O58: 1727.25 | P58: 1725.25 | S58: 4030.17 | T58: 4030.17
A59: ATILLA (EPSM) | C59: 6000 | D59: 6000 | Q59: 3120 | R59: 3120 | S59: 2880 | T59: 2880
A60: MAILLARD | C60: 6000 | D60: 6000 | Q60: 6000 | R60: 6000
A61: CHAO | C61: 344 | D61: 344 | Q61: 344 | R61: 344
A62: VAUCHER | C62: 20557 | D62: 20557 | O62: =5139.26+5139.26 -> 10278.52 | P62: =5139.26*2 -> 10278.52 | Q62: =20557-O62 -> 10278.48 | R62: 10278
A63: HULIN | C63: 7631 | D63: 7631 | I63: 1748 | J63: 1748 | M63: 1737.12 | N63: 1737.12 | O63: 4145.6 | P63: 4145.6
A64: LOZACH MARY | C64: =28218+226.86 -> 28444.86 | D64: =28218+226.86 -> 28444.86 | G64: 17797 | H64: 17797 | K64: 7076.03 | L64: 7076.03 | M64: 3345 | N64: 3345 | AA64: 226.86 | AB64: 226.86
A65: BENOIST | C65: 11253 | D65: 11253 | M65: 11252.7 | N65: 11252.7
A66: ANQUETIL | C66: 11957 | D66: 11957 | E66: 9622 | F66: 9621.54 | M66: 2336.28 | N66: 2336.28
A67: KITE SURF | C67: 60272 | D67: 60272 | G67: 27302 | H67: 27302 | I67: 8602 | J67: 8602 | K67: =3645.28+20722.96 -> 24368.24 | L67: =3645.28+20722.96 -> 24368.24
A68: VERGRIETE | C68: 36749 | D68: 36749 | G68: 18576 | H68: 18576 | I68: 11252 | J68: 11252 | K68: 6920 | L68: 6920
A69: ROHRBACH | C69: 38516 | D69: 38516 | G69: 19610 | H69: 19610 | I69: 4011 | J69: 4011 | K69: =10224.61+4679.97 -> 14904.58 | L69: 14905
A70: MANCHE | C70: 1783 | D70: 1783 | K70: 1781.5 | L70: 1781.5
A71: DUPONT CHALESLE iso ext | C71: 27209 | D71: 27209 | G71: 11759 | H71: 11759 | I71: 15450 | J71: 15450
A72: BRETEAU | C72: 13034 | D72: 13034 | E72: 6812 | F72: 6812 | I72: 6222 | J72: 6222
A73: DESFEUX | C73: 3887 | D73: 3887 | I73: 3887 | J73: 3887
A74: DUPONT CHALESLE | C74: =15000+4649 -> 19649 | D74: 19649 | E74: 8114 | F74: 8114.37 | I74: 11533 | J74: 11533
A75: LOBERGER | C75: =5476-1286 -> 4190 | D75: 4190 | E75: 3115 | F75: 3114.52 | G75: 1075 | H75: 1075
A76: DELAMARE | C76: 4299 | D76: 4299 | G76: 4299 | H76: 4299
A77: SCI PRJ | C77: 5165 | D77: 5165 | G77: 5165 | H77: 5165
A78: LETOURNEUR | C78: 556 | D78: 556 | E78: 556 | F78: 556
A79: COLORE CAEN | C79: 500 | D79: 500 | E79: 500 | F79: 500
A80: PARISOTTO | C80: 1990 | D80: 1990 | E80: 1990 | F80: 1990.11
AC82: =SUM(AC6:AC81) -> 938161.4 | AD82: 394000 | AE82: =AC82-AD82 -> 544161.4
A84: TOTAL CA mensuel prévu | C84: =SUM(C3:C82) -> 1642525.1 | D84: =SUM(D3:D82) -> 2037206.9 | E84: =SUM(E3:E81) -> 46314 | G84: =SUM(G3:G81) -> 132016.17 | I84: =SUM(I3:I81) -> 135609.57 | K84: =SUM(K3:K81) -> 87118.37 | M84: =SUM(M3:M81) -> 87813.76 | O84: =SUM(O3:O81) -> 56387.71 | Q84: =SUM(Q3:Q81) -> 53661.63 | S84: =SUM(S3:S63) -> 89966.06 | U84: =SUM(U3:U63) -> 126697.6 | W84: =SUM(W3:W63) -> 125937.37 | Y84: =SUM(Y3:Y63) -> 49271.86 | AA84: =SUM(AA3:AA83) -> 103333.97
A85: TOTAL CA mensuel réalisé | F85: =SUM(F3:F82) -> 46313.44 | H85: =SUM(H3:H82) -> 132016 | J85: =SUM(J3:J82) -> 135610 | L85: =SUM(L3:L82) -> 87118.8 | N85: =SUM(N3:N82) -> 87813.4 | P85: =SUM(P3:P82) -> 56385.71 | R85: =SUM(R3:R82) -> 53660.73 | T85: =SUM(T3:T82) -> 89965.07 | V85: =SUM(V3:V82) -> 126697 | X85: =SUM(X3:X82) -> 125938.76 | Z85: =SUM(Z3:Z82) -> 49272.35 | AB85: =SUM(AB3:AB82) -> 103333.37
A87: TOTAL CA prévu cumulé | E87: =E84 -> 46314 | G87: =G84+E87 -> 178330.17 | I87: =I84+G87 -> 313939.74 | K87: =K84+I87 -> 401058.11 | M87: =M84+K87 -> 488871.87 | O87: =O84+M87 -> 545259.58 | Q87: =Q84+O87 -> 598921.21 | S87: =S84+Q87 -> 688887.27 | U87: =U84+S87 -> 815584.87 | W87: =W84+U87 -> 941522.24 | Y87: =Y84+W87 -> 990794.1 | AA87: =AA84+Y87 -> 1094128.1
A88: TOTAL CA réalisé cumulé 2019 2020 | F88: =F85 -> 46313.44 | H88: =H85+F88 -> 178329.44 | J88: =J85+H88 -> 313939.44 | L88: =L85+J88 -> 401058.24 | N88: =N85+L88 -> 488871.64 | P88: =P85+N88 -> 545257.35 | R88: =R85+P88 -> 598918.08 | T88: =T85+R88 -> 688883.15 | V88: =V85+T88 -> 815580.15 | X88: =X85+V88 -> 941518.91 | Z88: =Z85+X88 -> 990791.26 | AB88: =AB85+Z88 -> 1094124.6
A90: TOTAL CA réalisé cumulé 2018-2019 | F90: 26802 | H90: 75263 | J90: 140265 | L90: 247438 | N90: 257610 | P90: 389179 | R90: 509844 | T90: 571886 | V90: 687097 | X90: 785109 | Z90: 848665 | AB90: 990681
A91: % évolution année n-1 | F91: =(F88-F90)/F90 -> 0.72798448 | H91: =(H88-H90)/H90 -> 1.3694171 | J91: =(J88-J90)/J90 -> 1.238188 | L91: =(L88-L90)/L90 -> 0.62084336 | N91: =(N88-N90)/N90 -> 0.89771996 | P91: =(P88-P90)/P90 -> 0.40104515 | R91: =(R88-R90)/R90 -> 0.1747085 | T91: =(T88-T90)/T90 -> 0.20458125 | V91: =(V88-V90)/V90 -> 0.18699419 | X91: =(X88-X90)/X90 -> 0.19922063 | Z91: =(Z88-Z90)/Z90 -> 0.16747039 | AB91: =(AB88-AB90)/AB90 -> 0.10441669

Sheet 2020-21
F4: OSSATURE | G4: OB | H4: CHARPENTE | I4: CB | J4: MENUISERIE | K4: MX | L4: BARDAGE | M4: BA | N4: ISOLATION | O4: IEA | P4: PLATRERIE | Q4: PII | R4: DIVERS | S4: DIV | U4: OCTOBRE | W4: NOVEMBRE | Y4: DECEMBRE | AA4: JANVIER | AC4: FEVRIER | AE4: MARS | AG4: AVRIL | AI4: MAI | AK4: JUIN | AM4: JUILLET | AO4: AOUT | AQ4: SEPTEMBRE
A5: NOM | C5: CA/prevision | D5: CA/contrat | F5: BOIS | G5: % | H5: BOIS | I5: % | J5: EXTERIEURE | K5: % | L5: EXT | M5: % | N5: ETANCHEITE | O5: % | P5: ISO INT MI | Q5: % | S5: % | U5: prévu | V5: réalisé | W5: prévu | X5: réalisé | Y5: prévu | Z5: réalisé | AA5: prévu | AB5: réalisé | AC5: prévu | AD5: réalisé | AE5: prévu | AF5: réalisé | AG5: prévu | AH5: réalisé | AI5: prévu | AJ5: réalisé | AK5: prévu | AL5: réalisé | AM5: prévu | AN5: réalisé | AO5: prévu | AP5: réalisé | AQ5: prévu | AR5: réalisé | AS5: 2021/2022
A7: Commission PASQUET | Y7: =1520.96 -> 1520.96 | Z7: =1520.96 -> 1520.96 | AI7: -608.7 | AJ7: -608.7
A8: Commission PASQUET | AI8: -1344.3 | AJ8: -1344
A9: Commission PASQUET | AI9: 855 | AJ9: 855
A10: Commission PASQUET | AI10: 608.7 | AJ10: 608.7
A11: Commission ST
A12: loret avoir | AI12: -564 | AJ12: -564
G13: =F13/E13 -> #DIV/0! | I13: =H13/E13 -> #DIV/0! | K13: =J13/E13 -> #DIV/0! | M13: =L13/E13 -> #DIV/0! | O13: =N13/E13 -> #DIV/0! | Q13: =P13/E13 -> #DIV/0! | S13: =R13/E13 -> #DIV/0! | T13: =S13+Q13+O13+M13+K13+I13+G13 -> #DIV/0! | AA13: =D13-U13-W13-Y13 -> 0 | AC13: =D13-U13-W13-Y13-AA13 -> 0 | AE13: =D13-U13-W13-Y13-AA13-AC13 -> 0 | AG13: =D13-U13-W13-Y13-AA13-AC13-AE13 -> 0 | AI13: =D13-U13-W13-Y13-AA13-AC13-AE13-AG13 -> 0 | AK13: =D13-U13-W13-Y13-AA13-AC13-AE13-AG13-AI13 -> 0 | AM13: =D13-U13-W13-Y13-AA13-AC13-AE13-AG13-AI13-AK13 -> 0 | AO13: =D13-U13-W13-Y13-AA13-AC13-AE13-AG13-AI13-AK13-AM13 -> 0 | AQ13: =D13-U13-W13-Y13-AA13-AC13-AE13-AG13-AI13-AK13-AM13-AO13 -> 0 | AS13: =D13-U13-W13-Y13-AA13-AC13-AE13-AG13-AI13-AK13-AM13-AO13-AQ13 -> 0
G14: =F14/E14 -> #DIV/0! | I14: =H14/E14 -> #DIV/0! | K14: =J14/E14 -> #DIV/0! | M14: =L14/E14 -> #DIV/0! | O14: =N14/E14 -> #DIV/0! | Q14: =P14/E14 -> #DIV/0! | S14: =R14/E14 -> #DIV/0! | T14: =S14+Q14+O14+M14+K14+I14+G14 -> #DIV/0! | AA14: =D14-U14-W14-Y14 -> 0 | AC14: =D14-U14-W14-Y14-AA14 -> 0 | AE14: =D14-U14-W14-Y14-AA14-AC14 -> 0 | AG14: =D14-U14-W14-Y14-AA14-AC14-AE14 -> 0 | AI14: =D14-U14-W14-Y14-AA14-AC14-AE14-AG14 -> 0 | AK14: =D14-U14-W14-Y14-AA14-AC14-AE14-AG14-AI14 -> 0 | AM14: =D14-U14-W14-Y14-AA14-AC14-AE14-AG14-AI14-AK14 -> 0 | AO14: =D14-U14-W14-Y14-AA14-AC14-AE14-AG14-AI14-AK14-AM14 -> 0 | AQ14: =D14-U14-W14-Y14-AA14-AC14-AE14-AG14-AI14-AK14-AM14-AO14 -> 0 | AS14: =D14-U14-W14-Y14-AA14-AC14-AE14-AG14-AI14-AK14-AM14-AO14-AQ14 -> 0
G15: =F15/E15 -> #DIV/0! | I15: =H15/E15 -> #DIV/0! | K15: =J15/E15 -> #DIV/0! | M15: =L15/E15 -> #DIV/0! | O15: =N15/E15 -> #DIV/0! | Q15: =P15/E15 -> #DIV/0! | S15: =R15/E15 -> #DIV/0! | T15: =S15+Q15+O15+M15+K15+I15+G15 -> #DIV/0! | AA15: =D15-U15-W15-Y15 -> 0 | AC15: =D15-U15-W15-Y15-AA15 -> 0 | AE15: =D15-U15-W15-Y15-AA15-AC15 -> 0 | AG15: =D15-U15-W15-Y15-AA15-AC15-AE15 -> 0 | AI15: =D15-U15-W15-Y15-AA15-AC15-AE15-AG15 -> 0 | AK15: =D15-U15-W15-Y15-AA15-AC15-AE15-AG15-AI15 -> 0 | AM15: =D15-U15-W15-Y15-AA15-AC15-AE15-AG15-AI15-AK15 -> 0 | AO15: =D15-U15-W15-Y15-AA15-AC15-AE15-AG15-AI15-AK15-AM15 -> 0 | AQ15: =D15-U15-W15-Y15-AA15-AC15-AE15-AG15-AI15-AK15-AM15-AO15 -> 0 | AS15: =D15-U15-W15-Y15-AA15-AC15-AE15-AG15-AI15-AK15-AM15-AO15-AQ15 -> 0
A16: MARTINS | C16: 23433.53 | D16: 23433.53 | F16: =5274.01+900 -> 6174.01 | G16: =F16/E16 -> #DIV/0! | H16: 1870.13 | I16: =H16/E16 -> #DIV/0! | J16: 3332.67 | K16: =J16/E16 -> #DIV/0! | L16: 6800.94 | M16: =L16/E16 -> #DIV/0! | N16: 1406.23 | O16: =N16/E16 -> #DIV/0! | P16: 2475.19 | Q16: =P16/E16 -> #DIV/0! | R16: =976.86+397.5 -> 1374.36 | S16: =R16/E16 -> #DIV/0! | T16: =S16+Q16+O16+M16+K16+I16+G16 -> #DIV/0! | AA16: 0 | AC16: 0 | AE16: 0 | AG16: 0 | AI16: 0 | AK16: 0 | AM16: 0 | AO16: 0 | AQ16: 0 | AS16: =D16-U16-W16-Y16-AA16-AC16-AE16-AG16-AI16-AK16-AM16-AO16-AQ16 -> 23433.53
A17: Mairie de MOULT | C17: 22356.5 | D17: 22357 | G17: =F17/E17 -> #DIV/0! | H17: =900+18576.5 -> 19476.5 | I17: =H17/E17 -> #DIV/0! | K17: =J17/E17 -> #DIV/0! | M17: =L17/E17 -> #DIV/0! | O17: =N17/E17 -> #DIV/0! | Q17: =P17/E17 -> #DIV/0! | R17: =1440+1440 -> 2880 | S17: =R17/E17 -> #DIV/0! | T17: =S17+Q17+O17+M17+K17+I17+G17 -> #DIV/0! | AA17: 0 | AC17: 0 | AE17: 0 | AG17: 0 | AI17: 0 | AK17: 0 | AM17: 0 | AO17: 0 | AQ17: 0 | AS17: =D17-U17-W17-Y17-AA17-AC17-AE17-AG17-AI17-AK17-AM17-AO17-AQ17 -> 22357
A18: CROCHARD | C18: 20600 | D18: 20600 | G18: =F18/E18 -> #DIV/0! | H18: =4263.46+857.31+744 -> 5864.77 | I18: =H18/E18 -> #DIV/0! | J18: 2638.69 | K18: =J18/E18 -> #DIV/0! | M18: =L18/E18 -> #DIV/0! | O18: =N18/E18 -> #DIV/0! | Q18: =P18/E18 -> #DIV/0! | R18: 12602.14 | S18: =R18/E18 -> #DIV/0! | T18: =S18+Q18+O18+M18+K18+I18+G18 -> #DIV/0! | AA18: 0 | AC18: 0 | AE18: 0 | AG18: 0 | AI18: 0 | AK18: 0 | AM18: 0 | AO18: 0 | AQ18: 0 | AS18: =D18-U18-W18-Y18-AA18-AC18-AE18-AG18-AI18-AK18-AM18-AO18-AQ18 -> 20600
A19: HERBLOT | C19: 61500 | D19: 61500 | F19: =900+10152.75 -> 11052.75 | G19: =F19/E19 -> #DIV/0! | H19: 11036.29 | I19: =H19/E19 -> #DIV/0! | J19: 8633.38 | K19: =J19/E19 -> #DIV/0! | L19: 12184.11 | M19: =L19/E19 -> #DIV/0! | N19: 3363.76 | O19: =N19/E19 -> #DIV/0! | P19: 15203.61 | Q19: =P19/E19 -> #DIV/0! | S19: =R19/E19 -> #DIV/0! | T19: =S19+Q19+O19+M19+K19+I19+G19 -> #DIV/0! | AA19: 0 | AC19: 0 | AE19: 0 | AG19: 0 | AI19: 0 | AK19: 0 | AM19: 0 | AO19: 0 | AQ19: 0 | AS19: =D19-U19-W19-Y19-AA19-AC19-AE19-AG19-AI19-AK19-AM19-AO19-AQ19 -> 61500
A20: JAGER | C20: 81301.93 | D20: =C20 -> 81301.93 | E20: 14288.15 | F20: =11033.19+1450 -> 12483.19 | G20: =F20/E20 -> 0.87367434 | H20: 1904.96 | I20: =H20/E20 -> 0.13332447 | K20: =J20/E20 -> 0 | M20: =L20/E20 -> 0 | O20: =N20/E20 -> 0 | Q20: =P20/E20 -> 0 | S20: =R20/E20 -> 0 | T20: =S20+Q20+O20+M20+K20+I20+G20 -> 1.0069988 | AA20: 0 | AC20: 0 | AE20: 0 | AG20: 0 | AI20: 0 | AK20: 0 | AM20: 0 | AO20: 0 | AQ20: 14288 | AR20: 14288.15 | AS20: =D20-U20-W20-Y20-AA20-AC20-AE20-AG20-AI20-AK20-AM20-AO20-AQ20 -> 67013.93
A21: LEMOINE | C21: 42665 | D21: 42665 | E21: 42665 | G21: =F21/E21 -> 0 | I21: =H21/E21 -> 0 | J21: 42665 | K21: =J21/E21 -> 1 | M21: =L21/E21 -> 0 | O21: =N21/E21 -> 0 | Q21: =P21/E21 -> 0 | S21: =R21/E21 -> 0 | T21: =S21+Q21+O21+M21+K21+I21+G21 -> 1 | AA21: 0 | AC21: 0 | AE21: 0 | AG21: 0 | AI21: 0 | AK21: 0 | AM21: 33471 | AN21: 33471 | AO21: =D21-U21-W21-Y21-AA21-AC21-AE21-AG21-AI21-AK21-AM21 -> 9194 | AP21: 9194 | AQ21: =D21-U21-W21-Y21-AA21-AC21-AE21-AG21-AI21-AK21-AM21-AO21 -> 0 | AS21: =D21-U21-W21-Y21-AA21-AC21-AE21-AG21-AI21-AK21-AM21-AO21-AQ21 -> 0
A22: FRANCOIS | C22: 52084 | D22: 52084 | E22: 12354.85 | F22: =900+4011.91 -> 4911.91 | G22: =F22/E22 -> 0.39756938 | H22: 1141.89 | I22: =H22/E22 -> 0.092424433 | J22: 2216.25 | K22: =J22/E22 -> 0.179383 | L22: 4084.8 | M22: =L22/E22 -> 0.3306232 | O22: =N22/E22 -> 0 | Q22: =P22/E22 -> 0 | S22: =R22/E22 -> 0 | T22: =S22+Q22+O22+M22+K22+I22+G22 -> 1 | AA22: 0 | AC22: 0 | AE22: 0 | AG22: 0 | AI22: 0 | AK22: 0 | AM22: 0 | AQ22: 12355 | AR22: 12354.85 | AS22: =D22-U22-W22-Y22-AA22-AC22-AE22-AG22-AI22-AK22-AM22-AO22-AQ22 -> 39729
A23: CUVIGNY | C23: 18000 | D23: 18000 | E23: 18000 | F23: 8184 | G23: =F23/E23 -> 0.45466667 | H23: 1603 | I23: =H23/E23 -> 0.089055556 | J23: 2235 | K23: =J23/E23 -> 0.12416667 | L23: 4557 | M23: =L23/E23 -> 0.25316667 | N23: 1426 | O23: =N23/E23 -> 0.079222222 | Q23: =P23/E23 -> 0 | S23: =R23/E23 -> 0 | T23: =S23+Q23+O23+M23+K23+I23+G23 -> 1.0002778 | AA23: 0 | AC23: 0 | AE23: 0 | AG23: 0 | AI23: 0 | AK23: 4767.92 | AL23: 4767.92 | AM23: 4849 | AN23: 4849.37 | AO23: 0 | AQ23: =D23-U23-W23-Y23-AA23-AC23-AE23-AG23-AI23-AK23-AM23-AO23 -> 8383.08 | AR23: 8382.71 | AS23: =D23-U23-W23-Y23-AA23-AC23-AE23-AG23-AI23-AK23-AM23-AO23-AQ23 -> 0
A24: BASSIERE | C24: 25682.67 | D24: 25682.67 | E24: 25683 | F24: 8586 | G24: =F24/E24 -> 0.33430674 | H24: 1603 | I24: =H24/E24 -> 0.062414827 | J24: 5901 | K24: 0 | L24: 8165 | M24: =L24/E24 -> 0.31791457 | N24: 1426 | O24: =N24/E24 -> 0.055523109 | Q24: =P24/E24 -> 0 | S24: =R24/E24 -> 0 | T24: =S24+Q24+O24+M24+K24+I24+G24 -> 0.77015925 | AA24: 0 | AC24: 0 | AE24: 0 | AG24: 0 | AI24: 0 | AK24: 6332.4 | AL24: 6332.4 | AM24: 5465 | AN24: 5464.8 | AO24: 0 | AQ24: =D24-U24-W24-Y24-AA24-AC24-AE24-AG24-AI24-AK24-AM24-AO24 -> 13885.27 | AR24: 13885.47 | AS24: =D24-U24-W24-Y24-AA24-AC24-AE24-AG24-AI24-AK24-AM24-AO24-AQ24 -> 0
A25: EXAEQUO | C25: 533.33 | D25: 533.33 | E25: 533 | G25: =F25/E25 -> 0 | I25: =H25/E25 -> 0 | K25: =J25/E25 -> 0 | M25: =L25/E25 -> 0 | O25: =N25/E25 -> 0 | Q25: =P25/E25 -> 0 | R25: 533 | S25: =R25/E25 -> 1 | T25: =S25+Q25+O25+M25+K25+I25+G25 -> 1 | AA25: 0 | AC25: 0 | AE25: 0 | AG25: 533.33 | AH25: 533.33 | AI25: =D25-U25-W25-Y25-AA25-AC25-AE25-AG25 -> 0 | AK25: =D25-U25-W25-Y25-AA25-AC25-AE25-AG25-AI25 -> 0 | AM25: =D25-U25-W25-Y25-AA25-AC25-AE25-AG25-AI25-AK25 -> 0 | AO25: =D25-U25-W25-Y25-AA25-AC25-AE25-AG25-AI25-AK25-AM25 -> 0 | AQ25: =D25-U25-W25-Y25-AA25-AC25-AE25-AG25-AI25-AK25-AM25-AO25 -> 0 | AS25: =D25-U25-W25-Y25-AA25-AC25-AE25-AG25-AI25-AK25-AM25-AO25-AQ25 -> 0
A26: PREVOST | C26: 1821 | D26: 1821 | E26: 1821 | G26: =F26/E26 -> 0 | I26: =H26/E26 -> 0 | K26: =J26/E26 -> 0 | M26: =L26/E26 -> 0 | O26: =N26/E26 -> 0 | Q26: =P26/E26 -> 0 | R26: 1821 | S26: =R26/E26 -> 1 | T26: =S26+Q26+O26+M26+K26+I26+G26 -> 1 | AA26: 0 | AC26: 0 | AE26: 0 | AG26: =D26-U26-W26-Y26-AA26-AC26-AE26 -> 1821 | AH26: 1821.21 | AI26: =D26-U26-W26-Y26-AA26-AC26-AE26-AG26 -> 0 | AK26: =D26-U26-W26-Y26-AA26-AC26-AE26-AG26-AI26 -> 0 | AM26: =D26-U26-W26-Y26-AA26-AC26-AE26-AG26-AI26-AK26 -> 0 | AO26: =D26-U26-W26-Y26-AA26-AC26-AE26-AG26-AI26-AK26-AM26 -> 0 | AQ26: =D26-U26-W26-Y26-AA26-AC26-AE26-AG26-AI26-AK26-AM26-AO26 -> 0 | AS26: =D26-U26-W26-Y26-AA26-AC26-AE26-AG26-AI26-AK26-AM26-AO26-AQ26 -> 0
A27: DUCHENNE | C27: 21204 | D27: 21204 | E27: 4550.16 | F27: =1311.23+350 -> 1661.23 | G27: =F27/E27 -> 0.36509266 | H27: 546.73 | I27: =H27/E27 -> 0.12015621 | J27: 1080.47 | K27: =J27/E27 -> 0.23745758 | L27: 1261.73 | M27: =L27/E27 -> 0.27729355 | O27: =N27/E27 -> 0 | Q27: =P27/E27 -> 0 | S27: =R27/E27 -> 0 | T27: =S27+Q27+O27+M27+K27+I27+G27 -> 1 | AA27: 0 | AC27: 0 | AE27: 0 | AG27: 0 | AK27: 0 | AM27: 0 | AO27: 0 | AQ27: 4550 | AR27: 4550.16 | AS27: =D27-U27-W27-Y27-AA27-AC27-AE27-AG27-AI27-AK27-AM27-AO27-AQ27 -> 16654
A28: RAOULT | C28: 6537 | D28: 6537 | E28: 6537 | G28: =F28/E28 -> 0 | I28: =H28/E28 -> 0 | K28: =J28/E28 -> 0 | L28: 6537 | M28: =L28/E28 -> 1 | O28: =N28/E28 -> 0 | Q28: =P28/E28 -> 0 | S28: =R28/E28 -> 0 | T28: =S28+Q28+O28+M28+K28+I28+G28 -> 1 | AA28: 0 | AC28: 0 | AE28: 0 | AG28: 2200 | AH28: 2200 | AI28: 2200 | AJ28: 2200 | AK28: =D28-U28-W28-Y28-AA28-AC28-AE28-AG28-AI28 -> 2137 | AL28: 2137 | AM28: =D28-U28-W28-Y28-AA28-AC28-AE28-AG28-AI28-AK28 -> 0 | AO28: =D28-U28-W28-Y28-AA28-AC28-AE28-AG28-AI28-AK28-AM28 -> 0 | AQ28: =D28-U28-W28-Y28-AA28-AC28-AE28-AG28-AI28-AK28-AM28-AO28 -> 0 | AS28: =D28-U28-W28-Y28-AA28-AC28-AE28-AG28-AI28-AK28-AM28-AO28-AQ28 -> 0
A29: VIVIER | C29: 9276 | D29: 9276 | G29: =F29/E29 -> #DIV/0! | I29: =H29/E29 -> #DIV/0! | K29: =J29/E29 -> #DIV/0! | M29: =L29/E29 -> #DIV/0! | O29: =N29/E29 -> #DIV/0! | Q29: =P29/E29 -> #DIV/0! | S29: =R29/E29 -> #DIV/0! | T29: =S29+Q29+O29+M29+K29+I29+G29 -> #DIV/0! | AA29: 0 | AC29: 0 | AE29: 0 | AG29: 0 | AI29: 0 | AK29: 0 | AM29: 0 | AO29: 0 | AS29: =D29-U29-W29-Y29-AA29-AC29-AE29-AG29-AI29-AK29-AM29-AO29-AQ29 -> 9276
A30: FOUQUES mam bassene | C30: 4328 | D30: 4328 | E30: 4328 | G30: =F30/E30 -> 0 | I30: =H30/E30 -> 0 | K30: =J30/E30 -> 0 | M30: =L30/E30 -> 0 | N30: 4328 | O30: =N30/E30 -> 1 | Q30: =P30/E30 -> 0 | S30: =R30/E30 -> 0 | T30: =S30+Q30+O30+M30+K30+I30+G30 -> 1 | AA30: 0 | AC30: 0 | AE30: 0 | AG30: 0 | AI30: 0 | AK30: 0 | AM30: 0 | AO30: =D30-U30-W30-Y30-AA30-AC30-AE30-AG30-AI30-AK30-AM30 -> 4328 | AP30: 4328 | AQ30: =D30-U30-W30-Y30-AA30-AC30-AE30-AG30-AI30-AK30-AM30-AO30 -> 0 | AS30: =D30-U30-W30-Y30-AA30-AC30-AE30-AG30-AI30-AK30-AM30-AO30-AQ30 -> 0
A31: ARCHE DES BEBES | C31: 220000 | D31: 220000 | G31: =F31/E31 -> #DIV/0! | I31: =H31/E31 -> #DIV/0! | K31: =J31/E31 -> #DIV/0! | M31: =L31/E31 -> #DIV/0! | O31: =N31/E31 -> #DIV/0! | Q31: =P31/E31 -> #DIV/0! | S31: =R31/E31 -> #DIV/0! | T31: =S31+Q31+O31+M31+K31+I31+G31 -> #DIV/0! | AA31: 0 | AC31: 0 | AE31: 0 | AG31: 0 | AI31: 0 | AK31: 0 | AQ31: 0 | AS31: =D31-U31-W31-Y31-AA31-AC31-AE31-AG31-AI31-AK31-AM31-AO31-AQ31 -> 220000
A32: CHATELIN | C32: 31053 | D32: 31053 | E32: 7316.17 | F32: 1953.41 | G32: =F32/E32 -> 0.26699899 | H32: 1837.35 | I32: =H32/E32 -> 0.2511355 | J32: 1413.6 | K32: =J32/E32 -> 0.19321585 | L32: 1860.32 | M32: =L32/E32 -> 0.25427512 | N32: 251.49 | O32: =N32/E32 -> 0.034374543 | Q32: =P32/E32 -> 0 | S32: =R32/E32 -> 0 | T32: =S32+Q32+O32+M32+K32+I32+G32 -> 1 | AA32: 0 | AC32: 0 | AE32: 0 | AG32: 0 | AI32: 0 | AK32: 0 | AM32: 0 | AO32: 0 | AQ32: 7316 | AR32: 7316.17 | AS32: =D32-U32-W32-Y32-AA32-AC32-AE32-AG32-AI32-AK32-AM32-AO32-AQ32 -> 23737
A33: MONTFOURNY | C33: 113900 | D33: 113900 | G33: =F33/E33 -> #DIV/0! | I33: =H33/E33 -> #DIV/0! | K33: =J33/E33 -> #DIV/0! | M33: =L33/E33 -> #DIV/0! | O33: =N33/E33 -> #DIV/0! | Q33: =P33/E33 -> #DIV/0! | S33: =R33/E33 -> #DIV/0! | T33: =S33+Q33+O33+M33+K33+I33+G33 -> #DIV/0! | AA33: 0 | AC33: 0 | AE33: 0 | AG33: 0 | AI33: 0 | AK33: 0 | AM33: 0 | AO33: 0 | AQ33: 0 | AS33: =D33-U33-W33-Y33-AA33-AC33-AE33-AG33-AI33-AK33-AM33-AO33-AQ33 -> 113900
A34: BRETAGNE | C34: =1278+23805.27+513.94 -> 25597.21 | D34: 25597 | E34: 25083 | F34: 5735 | G34: =F34/E34 -> 0.22864091 | H34: 2756 | I34: =H34/E34 -> 0.10987521 | J34: 3968 | K34: =J34/E34 -> 0.15819479 | M34: =L34/E34 -> 0 | N34: 5536 | O34: =N34/E34 -> 0.22070725 | P34: 2972 | Q34: =P34/E34 -> 0.11848662 | S34: =R34/E34 -> 0 | T34: =S34+Q34+O34+M34+K34+I34+G34 -> 0.8359048 | AA34: 0 | AC34: 0 | AE34: 0 | AG34: 4638.88 | AH34: 4638.88 | AI34: 12125.54 | AJ34: 12125.54 | AK34: =513.94+6693.13 -> 7207.07 | AL34: 7207 | AM34: 0 | AO34: 0 | AQ34: =D34-U34-W34-Y34-AA34-AC34-AE34-AG34-AI34-AK34-AM34-AO34 -> 1625.51 | AR34: =347.72+1278.22 -> 1625.94 | AS34: =D34-U34-W34-Y34-AA34-AC34-AE34-AG34-AI34-AK34-AM34-AO34-AQ34 -> 0
A35: GERBAULT - IBANESCU | C35: 103994 | D35: 103994 | E35: 54793.82 | F35: =28672.11+900 -> 29572.11 | G35: =F35/E35 -> 0.53969791 | H35: 8865.66 | I35: =H35/E35 -> 0.16180036 | J35: 6042.28 | K35: =J35/E35 -> 0.11027302 | L35: 5353.73 | M35: =L35/E35 -> 0.097706822 | N35: 4960.04 | O35: =N35/E35 -> 0.090521887 | Q35: =P35/E35 -> 0 | S35: =R35/E35 -> 0 | T35: =S35+Q35+O35+M35+K35+I35+G35 -> 1 | AA35: 0 | AC35: 0 | AE35: 0 | AG35: 0 | AI35: 0 | AK35: 0 | AM35: 17873 | AN35: 17872.65 | AO35: 20956 | AP35: 20956.29 | AQ35: 15965 | AR35: 15964.88 | AS35: =D35-U35-W35-Y35-AA35-AC35-AE35-AG35-AI35-AK35-AM35-AO35-AQ35 -> 49200
A36: flipo portail | C36: 1156 | D36: 1156 | E36: =D36 -> 1156 | G36: =F36/E36 -> 0 | I36: =H36/E36 -> 0 | K36: =J36/E36 -> 0 | M36: =L36/E36 -> 0 | O36: =N36/E36 -> 0 | Q36: =P36/E36 -> 0 | R36: 1156 | S36: =R36/E36 -> 1 | T36: =S36+Q36+O36+M36+K36+I36+G36 -> 1 | AA36: 0 | AC36: 0 | AE36: 0 | AG36: 0 | AK36: 1156 | AL36: 1156 | AM36: 0 | AQ36: =D36-U36-W36-Y36-AA36-AC36-AE36-AG36-AI36-AK36-AM36-AO36 -> 0 | AS36: =D36-U36-W36-Y36-AA36-AC36-AE36-AG36-AI36-AK36-AM36-AO36-AQ36 -> 0
A37: LECLEIR | C37: 29905.67 | D37: 29905.67 | E37: 23943.63 | F37: =900+4166.86 -> 5066.86 | G37: =F37/E37 -> 0.2116162 | H37: 4047.32 | I37: =H37/E37 -> 0.16903536 | J37: 6779.41 | K37: =J37/E37 -> 0.28314044 | L37: 6401.03 | M37: =L37/E37 -> 0.26733749 | N37: 1649.01 | O37: =N37/E37 -> 0.06887051 | P37: 0 | Q37: =P37/E37 -> 0 | S37: =R37/E37 -> 0 | T37: =S37+Q37+O37+M37+K37+I37+G37 -> 1 | AA37: 0 | AC37: 0 | AE37: 0 | AG37: 0 | AI37: 0 | AK37: 9114 | AL37: 9114 | AM37: 0 | AO37: 0 | AQ37: 14829 | AR37: 14829.45 | AS37: =D37-U37-W37-Y37-AA37-AC37-AE37-AG37-AI37-AK37-AM37-AO37-AQ37 -> 5962.67
A38: PORET | C38: =102969+4565.34 -> 107534.34 | D38: =C38 -> 107534.34 | E38: =D38 -> 107534.34 | F38: =900+30470.52 -> 31370.52 | G38: =F38/E38 -> 0.2917256 | H38: 7411.6 | I38: =H38/E38 -> 0.068923099 | J38: 26534.23 | K38: =J38/E38 -> 0.24675122 | L38: 32026.98 | M38: =L38/E38 -> 0.29783026 | N38: 5626.38 | O38: =N38/E38 -> 0.052321705 | Q38: =P38/E38 -> 0 | S38: =R38/E38 -> 0 | T38: =S38+Q38+O38+M38+K38+I38+G38 -> 0.95755189 | AA38: 0 | AC38: 0 | AE38: 0 | AG38: 0 | AI38: 24126.36 | AJ38: 24126.36 | AK38: 0 | AM38: 45000 | AN38: 44999.97 | AO38: 0 | AQ38: =D38-U38-W38-Y38-AA38-AC38-AE38-AG38-AI38-AK38-AM38-AO38 -> 38407.98 | AR38: =33843.38+4565.34 -> 38408.72 | AS38: =D38-U38-W38-Y38-AA38-AC38-AE38-AG38-AI38-AK38-AM38-AO38-AQ38 -> 0
A39: CLET CARON | C39: 176738.45 | D39: 176738 | E39: 155790.78 | F39: =1125+37272.35+3789.69 -> 42187.04 | G39: =F39/E39 -> 0.27079292 | H39: =15386.94+3582.6 -> 18969.54 | I39: =H39/E39 -> 0.12176292 | J39: =23156.77+868 -> 24024.77 | K39: =J39/E39 -> 0.15421176 | L39: =28481.54+3341.42 -> 31822.96 | M39: =L39/E39 -> 0.20426729 | N39: 11789.22 | O39: =N39/E39 -> 0.075673413 | P39: =25531.58+1465.67 -> 26997.25 | Q39: =P39/E39 -> 0.17329171 | S39: =R39/E39 -> 0 | T39: =S39+Q39+O39+M39+K39+I39+G39 -> 1 | AA39: 0 | AC39: 0 | AE39: 0 | AG39: 15114 | AH39: 15113.6 | AI39: 20142.54 | AJ39: 20142.54 | AK39: 45108.16 | AL39: 45108.16 | AM39: 25071 | AN39: 25071.24 | AO39: 37411 | AP39: 37411.21 | AQ39: 12944 | AR39: 12944 | AS39: =D39-U39-W39-Y39-AA39-AC39-AE39-AG39-AI39-AK39-AM39-AO39-AQ39 -> 20947.3
A40: BICART | C40: 7093 | D40: 7093 | E40: 7093 | G40: =F40/E40 -> 0 | I40: =H40/E40 -> 0 | K40: =J40/E40 -> 0 | M40: =L40/E40 -> 0 | O40: =N40/E40 -> 0 | Q40: =P40/E40 -> 0 | R40: 7093 | S40: =R40/E40 -> 1 | T40: =S40+Q40+O40+M40+K40+I40+G40 -> 1 | AA40: 0 | AC40: 0 | AE40: 0 | AG40: 7093 | AH40: 7092.9 | AI40: =D40-U40-W40-Y40-AA40-AC40-AE40-AG40 -> 0 | AK40: =D40-U40-W40-Y40-AA40-AC40-AE40-AG40-AI40 -> 0 | AM40: =D40-U40-W40-Y40-AA40-AC40-AE40-AG40-AI40-AK40 -> 0 | AO40: =D40-U40-W40-Y40-AA40-AC40-AE40-AG40-AI40-AK40-AM40 -> 0 | AQ40: =D40-U40-W40-Y40-AA40-AC40-AE40-AG40-AI40-AK40-AM40-AO40 -> 0 | AS40: =D40-U40-W40-Y40-AA40-AC40-AE40-AG40-AI40-AK40-AM40-AO40-AQ40 -> 0
A41: MAIRIE EVRECY | C41: 8521 | D41: 8521 | E41: =D41 -> 8521 | G41: =F41/E41 -> 0 | I41: =H41/E41 -> 0 | K41: =J41/E41 -> 0 | L41: 8521 | M41: =L41/E41 -> 1 | O41: =N41/E41 -> 0 | Q41: =P41/E41 -> 0 | S41: =R41/E41 -> 0 | T41: =S41+Q41+O41+M41+K41+I41+G41 -> 1 | AA41: 0 | AC41: 0 | AE41: 0 | AG41: =D41-U41-W41-Y41-AA41-AC41-AE41 -> 8521 | AH41: 8521.3 | AI41: =D41-U41-W41-Y41-AA41-AC41-AE41-AG41 -> 0 | AK41: =D41-U41-W41-Y41-AA41-AC41-AE41-AG41-AI41 -> 0 | AM41: =D41-U41-W41-Y41-AA41-AC41-AE41-AG41-AI41-AK41 -> 0 | AO41: =D41-U41-W41-Y41-AA41-AC41-AE41-AG41-AI41-AK41-AM41 -> 0 | AQ41: =D41-U41-W41-Y41-AA41-AC41-AE41-AG41-AI41-AK41-AM41-AO41 -> 0 | AS41: =D41-U41-W41-Y41-AA41-AC41-AE41-AG41-AI41-AK41-AM41-AO41-AQ41 -> 0
A42: HUARD | C42: 36011 | D42: 36011 | G42: =F42/E42 -> #DIV/0! | I42: =H42/E42 -> #DIV/0! | K42: =J42/E42 -> #DIV/0! | M42: =L42/E42 -> #DIV/0! | O42: =N42/E42 -> #DIV/0! | Q42: =P42/E42 -> #DIV/0! | S42: =R42/E42 -> #DIV/0! | T42: =S42+Q42+O42+M42+K42+I42+G42 -> #DIV/0! | AA42: 0 | AC42: 0 | AE42: 0 | AG42: 0 | AI42: 0 | AK42: 0 | AM42: 0 | AO42: 0 | AQ42: 5122 | AR42: 5121.79 | AS42: =D42-U42-W42-Y42-AA42-AC42-AE42-AG42-AI42-AK42-AM42-AO42-AQ42 -> 30889
A43: GUEDON | C43: 124336 | D43: 124336 | E43: 76047.9 | F43: =21526.05+900 -> 22426.05 | G43: =F43/E43 -> 0.29489374 | H43: 13992 | I43: =H43/E43 -> 0.1839893 | J43: 20605 | K43: =J43/E43 -> 0.27094765 | L43: 10804.32 | M43: =L43/E43 -> 0.14207256 | N43: 3606.93 | O43: =N43/E43 -> 0.047429712 | P43: 4612.89 | Q43: =P43/E43 -> 0.060657691 | R43: 0 | S43: =R43/E43 -> 0 | T43: =S43+Q43+O43+M43+K43+I43+G43 -> 0.99999066 | AA43: 0 | AC43: 0 | AE43: 0 | AG43: 15130.7 | AH43: 15130.7 | AI43: 0 | AK43: 26642.61 | AL43: 26642.61 | AM43: 10462 | AN43: 10462.29 | AO43: 0 | AQ43: 23812 | AR43: 23812.3 | AS43: =D43-U43-W43-Y43-AA43-AC43-AE43-AG43-AI43-AK43-AM43-AO43-AQ43 -> 48288.69
A44: FROGER | C44: ='2019-20'!AC17 -> 1913.88 | D44: =C44 -> 1913.88 | G44: =F44/E44 -> #DIV/0! | I44: =H44/E44 -> #DIV/0! | K44: =J44/E44 -> #DIV/0! | M44: =L44/E44 -> #DIV/0! | O44: =N44/E44 -> #DIV/0! | Q44: =P44/E44 -> #DIV/0! | S44: =R44/E44 -> #DIV/0! | T44: =S44+Q44+O44+M44+K44+I44+G44 -> #DIV/0! | AA44: 0 | AC44: 0 | AE44: 0 | AG44: 0 | AI44: 0 | AK44: 0 | AM44: 0 | AO44: 0 | AQ44: 0 | AS44: =D44-U44-W44-Y44-AA44-AC44-AE44-AG44-AI44-AK44-AM44-AO44-AQ44 -> 1913.88
A45: BOUILLET | C45: 2925 | D45: 2925 | E45: 2925 | G45: =F45/E45 -> 0 | I45: =H45/E45 -> 0 | K45: =J45/E45 -> 0 | M45: =L45/E45 -> 0 | O45: =N45/E45 -> 0 | Q45: =P45/E45 -> 0 | R45: 2925 | S45: =R45/E45 -> 1 | T45: =S45+Q45+O45+M45+K45+I45+G45 -> 1 | AA45: 0 | AC45: 0 | AE45: 0 | AG45: =D45-U45-W45-Y45-AA45-AC45-AE45 -> 2925 | AH45: 2925 | AI45: =D45-U45-W45-Y45-AA45-AC45-AE45-AG45 -> 0 | AK45: =D45-U45-W45-Y45-AA45-AC45-AE45-AG45-AI45 -> 0 | AM45: =D45-U45-W45-Y45-AA45-AC45-AE45-AG45-AI45-AK45 -> 0 | AO45: =D45-U45-W45-Y45-AA45-AC45-AE45-AG45-AI45-AK45-AM45 -> 0 | AQ45: =D45-U45-W45-Y45-AA45-AC45-AE45-AG45-AI45-AK45-AM45-AO45 -> 0 | AS45: =D45-U45-W45-Y45-AA45-AC45-AE45-AG45-AI45-AK45-AM45-AO45-AQ45 -> 0
A46: DUMAT MATTA | C46: 4018 | D46: 4018 | E46: 4018 | G46: =F46/E46 -> 0 | I46: =H46/E46 -> 0 | K46: =J46/E46 -> 0 | M46: =L46/E46 -> 0 | O46: =N46/E46 -> 0 | Q46: =P46/E46 -> 0 | R46: 4018 | S46: =R46/E46 -> 1 | T46: =S46+Q46+O46+M46+K46+I46+G46 -> 1 | AA46: 0 | AC46: 0 | AE46: 4018.04 | AF46: 4018 | AG46: 0 | AI46: 0 | AK46: =D46-U46-W46-Y46-AA46-AC46-AE46-AG46-AI46 -> -0.04 | AM46: =D46-U46-W46-Y46-AA46-AC46-AE46-AG46-AI46-AK46 -> 0 | AO46: =D46-U46-W46-Y46-AA46-AC46-AE46-AG46-AI46-AK46-AM46 -> 0 | AQ46: =D46-U46-W46-Y46-AA46-AC46-AE46-AG46-AI46-AK46-AM46-AO46 -> 0 | AS46: =D46-U46-W46-Y46-AA46-AC46-AE46-AG46-AI46-AK46-AM46-AO46-AQ46 -> 0
A47: GIRARD | C47: =39855.29+10471+9230 -> 59556.29 | D47: 59556 | E47: =D47 -> 59556 | F47: =950+18256.51 -> 19206.51 | G47: =F47/E47 -> 0.32249496 | H47: 20648.78 | I47: =H47/E47 -> 0.346712 | J47: 2000 | K47: =J47/E47 -> 0.033581839 | L47: 7230 | M47: =L47/E47 -> 0.12139835 | N47: 10471.2 | O47: =N47/E47 -> 0.17582108 | Q47: =P47/E47 -> 0 | S47: =R47/E47 -> 0 | T47: =S47+Q47+O47+M47+K47+I47+G47 -> 1.0000082 | AA47: 0 | AC47: 0 | AE47: 33537.14 | AF47: 33534.14 | AG47: 5506.61 | AH47: 5506.61 | AI47: 0 | AK47: 2572.5 | AL47: 2572.5 | AM47: 7899 | AN47: 7898.7 | AO47: 0 | AQ47: 0 | AS47: =D47-U47-W47-Y47-AA47-AC47-AE47-AG47-AI47-AK47-AM47-AO47-AQ47 -> 10040.75
A48: ROHRBACH | C48: 1661 | D48: 1661 | E48: 1661 | G48: =F48/E48 -> 0 | I48: =H48/E48 -> 0 | J48: 1661 | K48: =J48/E48 -> 1 | M48: =L48/E48 -> 0 | O48: =N48/E48 -> 0 | Q48: =P48/E48 -> 0 | S48: =R48/E48 -> 0 | T48: =S48+Q48+O48+M48+K48+I48+G48 -> 1 | AA48: 0 | AC48: 0 | AE48: 1660.99 | AF48: 1660.99 | AG48: =D48-U48-W48-Y48-AA48-AC48-AE48 -> 0.01 | AI48: =D48-U48-W48-Y48-AA48-AC48-AE48-AG48 -> 0 | AK48: =D48-U48-W48-Y48-AA48-AC48-AE48-AG48-AI48 -> 0 | AM48: =D48-U48-W48-Y48-AA48-AC48-AE48-AG48-AI48-AK48 -> 0 | AO48: =D48-U48-W48-Y48-AA48-AC48-AE48-AG48-AI48-AK48-AM48 -> 0 | AQ48: =D48-U48-W48-Y48-AA48-AC48-AE48-AG48-AI48-AK48-AM48-AO48 -> 0 | AS48: =D48-U48-W48-Y48-AA48-AC48-AE48-AG48-AI48-AK48-AM48-AO48-AQ48 -> 0
A49: GESLIN | C49: 26119 | D49: 26119 | E49: 26119 | F49: 8411 | G49: =F49/E49 -> 0.32202611 | H49: 1498 | I49: =H49/E49 -> 0.057352885 | J49: 4707 | K49: =J49/E49 -> 0.18021364 | M49: =L49/E49 -> 0 | N49: 1533 | O49: =N49/E49 -> 0.058692906 | P49: 3832 | Q49: =P49/E49 -> 0.14671312 | R49: 6142 | S49: =R49/E49 -> 0.23515449 | T49: =S49+Q49+O49+M49+K49+I49+G49 -> 1.0001531 | AA49: 0 | AC49: 0 | AE49: 4501.38 | AF49: 4501.38 | AG49: 0 | AI49: =19446.39+2170.93 -> 21617.32 | AJ49: 21617 | AK49: 0 | AM49: =D49-U49-W49-Y49-AA49-AC49-AE49-AG49-AI49-AK49 -> 0.3 | AO49: =D49-U49-W49-Y49-AA49-AC49-AE49-AG49-AI49-AK49-AM49 -> 0 | AQ49: =D49-U49-W49-Y49-AA49-AC49-AE49-AG49-AI49-AK49-AM49-AO49 -> 0 | AS49: =D49-U49-W49-Y49-AA49-AC49-AE49-AG49-AI49-AK49-AM49-AO49-AQ49 -> 0
A50: CHAVENTRE | C50: 1600 | D50: 1600 | E50: 1600 | G50: =F50/E50 -> 0 | I50: =H50/E50 -> 0 | J50: 1600 | K50: =J50/E50 -> 1 | M50: =L50/E50 -> 0 | O50: =N50/E50 -> 0 | Q50: =P50/E50 -> 0 | S50: =R50/E50 -> 0 | T50: =S50+Q50+O50+M50+K50+I50+G50 -> 1 | AA50: 0 | AC50: 0 | AE50: 1600 | AF50: 1600 | AG50: =D50-U50-W50-Y50-AA50-AC50-AE50 -> 0 | AI50: =D50-U50-W50-Y50-AA50-AC50-AE50-AG50 -> 0 | AK50: =D50-U50-W50-Y50-AA50-AC50-AE50-AG50-AI50 -> 0 | AM50: =D50-U50-W50-Y50-AA50-AC50-AE50-AG50-AI50-AK50 -> 0 | AO50: =D50-U50-W50-Y50-AA50-AC50-AE50-AG50-AI50-AK50-AM50 -> 0 | AQ50: =D50-U50-W50-Y50-AA50-AC50-AE50-AG50-AI50-AK50-AM50-AO50 -> 0 | AS50: =D50-U50-W50-Y50-AA50-AC50-AE50-AG50-AI50-AK50-AM50-AO50-AQ50 -> 0
A51: THIRE | C51: 30000 | D51: 30000 | E51: =D51 -> 30000 | F51: 8169 | G51: =F51/E51 -> 0.2723 | H51: 4295 | I51: =H51/E51 -> 0.14316667 | J51: 7243 | K51: =J51/E51 -> 0.24143333 | L51: 10294 | M51: =L51/E51 -> 0.34313333 | O51: =N51/E51 -> 0 | Q51: =P51/E51 -> 0 | S51: =R51/E51 -> 0 | T51: =S51+Q51+O51+M51+K51+I51+G51 -> 1.0000333 | AA51: 0 | AC51: 0 | AG51: 0 | AI51: 30000 | AJ51: 30000 | AK51: =D51-U51-W51-Y51-AA51-AC51-AE51-AG51-AI51 -> 0 | AM51: =D51-U51-W51-Y51-AA51-AC51-AE51-AG51-AI51-AK51 -> 0 | AO51: =D51-U51-W51-Y51-AA51-AC51-AE51-AG51-AI51-AK51-AM51 -> 0 | AQ51: =D51-U51-W51-Y51-AA51-AC51-AE51-AG51-AI51-AK51-AM51-AO51 -> 0 | AS51: =D51-U51-W51-Y51-AA51-AC51-AE51-AG51-AI51-AK51-AM51-AO51-AQ51 -> 0
A52: GEZE extension | C52: =24421.78-550 -> 23871.78 | D52: =C52 -> 23871.78 | E52: =D52 -> 23871.78 | F52: 8361 | G52: =F52/E52 -> 0.35024619 | H52: 1773 | I52: =H52/E52 -> 0.074271797 | J52: =4778-550 -> 4228 | K52: =J52/E52 -> 0.17711289 | M52: =L52/E52 -> 0 | N52: 2167 | O52: =N52/E52 -> 0.090776641 | P52: 5981 | Q52: =P52/E52 -> 0.25054688 | R52: 1359 | S52: =R52/E52 -> 0.056929144 | T52: =S52+Q52+O52+M52+K52+I52+G52 -> 0.99988354 | AA52: 0 | AC52: 11579 | AD52: 11579 | AE52: 7162.76 | AF52: 7162.76 | AG52: 0 | AI52: 3859.33 | AJ52: 3859 | AK52: 0 | AM52: 1271 | AN52: 1271.24 | AO52: 0 | AQ52: 0 | AS52: =D52-U52-W52-Y52-AA52-AC52-AE52-AG52-AI52-AK52-AM52-AO52-AQ52 -> -0.31
A53: GEZE existant | C53: =15567.02+993.32 -> 16560.34 | D53: 16560 | E53: =D53 -> 16560 | G53: =F53/E53 -> 0 | I53: =H53/E53 -> 0 | J53: 7059 | K53: =J53/E53 -> 0.42626812 | M53: =L53/E53 -> 0 | O53: =N53/E53 -> 0 | P53: 9501 | Q53: =P53/E53 -> 0.57373188 | S53: =R53/E53 -> 0 | T53: =S53+Q53+O53+M53+K53+I53+G53 -> 1 | AA53: 0 | AC53: 0 | AD53: 0 | AE53: 4803.45 | AF53: 4803.45 | AG53: 0 | AI53: 9363.62 | AJ53: 9364 | AK53: 0 | AM53: =D53-U53-W53-Y53-AA53-AC53-AE53-AG53-AI53-AK53 -> 2392.93 | AN53: =1399.95+993.32 -> 2393.27 | AO53: =D53-U53-W53-Y53-AA53-AC53-AE53-AG53-AI53-AK53-AM53 -> 0 | AQ53: =D53-U53-W53-Y53-AA53-AC53-AE53-AG53-AI53-AK53-AM53-AO53 -> 0 | AS53: =D53-U53-W53-Y53-AA53-AC53-AE53-AG53-AI53-AK53-AM53-AO53-AQ53 -> 0
A54: DELENTE | C54: 4831.04 | D54: 4831 | E54: =D54 -> 4831 | G54: =F54/E54 -> 0 | I54: =H54/E54 -> 0 | K54: =J54/E54 -> 0 | M54: =L54/E54 -> 0 | O54: =N54/E54 -> 0 | Q54: =P54/E54 -> 0 | R54: 4831 | S54: =R54/E54 -> 1 | T54: =S54+Q54+O54+M54+K54+I54+G54 -> 1 | AA54: 0 | AC54: 3483.5 | AD54: 3483.5 | AE54: =D54-U54-W54-Y54-AA54-AC54 -> 1347.5 | AF54: 1348 | AG54: =D54-U54-W54-Y54-AA54-AC54-AE54 -> 0 | AI54: =D54-U54-W54-Y54-AA54-AC54-AE54-AG54 -> 0 | AK54: =D54-U54-W54-Y54-AA54-AC54-AE54-AG54-AI54 -> 0 | AM54: =D54-U54-W54-Y54-AA54-AC54-AE54-AG54-AI54-AK54 -> 0 | AO54: =D54-U54-W54-Y54-AA54-AC54-AE54-AG54-AI54-AK54-AM54 -> 0 | AQ54: =D54-U54-W54-Y54-AA54-AC54-AE54-AG54-AI54-AK54-AM54-AO54 -> 0 | AS54: =D54-U54-W54-Y54-AA54-AC54-AE54-AG54-AI54-AK54-AM54-AO54-AQ54 -> 0
A55: DAGORN | C55: ='2019-20'!AC27 -> 42327.65 | D55: =C55 -> 42327.65 | E55: =D55 -> 42327.65 | F55: 20000 | G55: =F55/E55 -> 0.47250438 | H55: 11800 | I55: =H55/E55 -> 0.27877758 | K55: =J55/E55 -> 0 | L55: 5749 | M55: =L55/E55 -> 0.13582138 | N55: 4774 | O55: =N55/E55 -> 0.1127868 | Q55: =P55/E55 -> 0 | S55: =R55/E55 -> 0 | T55: =S55+Q55+O55+M55+K55+I55+G55 -> 0.99989014 | W55: 30997.05 | X55: 30997.05 | AA55: 9255.51 | AB55: 9256 | AC55: 0 | AE55: 2075.14 | AF55: 2075.14 | AG55: =D55-U55-W55-Y55-AA55-AC55-AE55 -> -0.05 | AI55: =D55-U55-W55-Y55-AA55-AC55-AE55-AG55 -> 0 | AK55: =D55-U55-W55-Y55-AA55-AC55-AE55-AG55-AI55 -> 0 | AM55: =D55-U55-W55-Y55-AA55-AC55-AE55-AG55-AI55-AK55 -> 0 | AO55: =D55-U55-W55-Y55-AA55-AC55-AE55-AG55-AI55-AK55-AM55 -> 0 | AQ55: =D55-U55-W55-Y55-AA55-AC55-AE55-AG55-AI55-AK55-AM55-AO55 -> 0 | AS55: =D55-U55-W55-Y55-AA55-AC55-AE55-AG55-AI55-AK55-AM55-AO55-AQ55 -> 0
A56: DARCILLON | C56: 67570 | D56: 67570 | E56: =D56 -> 67570 | F56: 27469 | G56: =F56/E56 -> 0.40652657 | H56: 12370 | I56: =H56/E56 -> 0.18306941 | J56: 19239 | K56: =J56/E56 -> 0.28472695 | L56: 3974 | M56: =L56/E56 -> 0.058813083 | N56: 4517 | O56: =N56/E56 -> 0.066849193 | Q56: =P56/E56 -> 0 | S56: =R56/E56 -> 0 | T56: =S56+Q56+O56+M56+K56+I56+G56 -> 0.9999852 | W56: 14016.15 | X56: 14016.15 | AA56: 9405.02 | AB56: 9405 | AC56: 24623.04 | AD56: 24623.04 | AE56: 16713.32 | AF56: 16713.32 | AG56: 2812.83 | AH56: 2812.83 | AI56: =D56-U56-W56-Y56-AA56-AC56-AE56-AG56 -> -0.36 | AK56: =D56-U56-W56-Y56-AA56-AC56-AE56-AG56-AI56 -> 0 | AM56: =D56-U56-W56-Y56-AA56-AC56-AE56-AG56-AI56-AK56 -> 0 | AO56: =D56-U56-W56-Y56-AA56-AC56-AE56-AG56-AI56-AK56-AM56 -> 0 | AQ56: =D56-U56-W56-Y56-AA56-AC56-AE56-AG56-AI56-AK56-AM56-AO56 -> 0 | AS56: =D56-U56-W56-Y56-AA56-AC56-AE56-AG56-AI56-AK56-AM56-AO56-AQ56 -> 0
A57: BANSE BROTELANDE | C57: 48518.45 | D57: 48518.45 | E57: =D57 -> 48518.45 | G57: =F57/E57 -> 0 | I57: =H57/E57 -> 0 | K57: =J57/E57 -> 0 | M57: =L57/E57 -> 0 | O57: =N57/E57 -> 0 | Q57: =P57/E57 -> 0 | S57: =R57/E57 -> 0 | T57: =S57+Q57+O57+M57+K57+I57+G57 -> 0 | AA57: 6258.22 | AB57: 6258 | AC57: 11116 | AD57: 11116 | AE57: 28341.43 | AF57: 28341.43 | AG57: 2802.49 | AH57: 2802.49 | AI57: =D57-U57-W57-Y57-AA57-AC57-AE57-AG57 -> 0.31 | AK57: =D57-U57-W57-Y57-AA57-AC57-AE57-AG57-AI57 -> 0 | AM57: =D57-U57-W57-Y57-AA57-AC57-AE57-AG57-AI57-AK57 -> 0 | AO57: =D57-U57-W57-Y57-AA57-AC57-AE57-AG57-AI57-AK57-AM57 -> 0 | AQ57: =D57-U57-W57-Y57-AA57-AC57-AE57-AG57-AI57-AK57-AM57-AO57 -> 0 | AS57: =D57-U57-W57-Y57-AA57-AC57-AE57-AG57-AI57-AK57-AM57-AO57-AQ57 -> 0
A58: ROBIN | C58: 29150 | D58: 29150 | E58: =D58 -> 29150 | F58: 9259 | G58: =F58/E58 -> 0.31763293 | H58: 3865 | I58: =H58/E58 -> 0.13259005 | J58: 7473 | K58: =J58/E58 -> 0.25636364 | L58: 8552 | M58: =L58/E58 -> 0.29337907 | O58: =N58/E58 -> 0 | Q58: =P58/E58 -> 0 | S58: =R58/E58 -> 0 | T58: =S58+Q58+O58+M58+K58+I58+G58 -> 0.99996569 | AA58: 4508.76 | AB58: 4509 | AC58: 0 | AE58: 22906.19 | AF58: 22906.19 | AG58: =D58-U58-W58-Y58-AA58-AC58-AE58 -> 1735.05 | AI58: =D58-U58-W58-Y58-AA58-AC58-AE58-AG58 -> 0 | AK58: =D58-U58-W58-Y58-AA58-AC58-AE58-AG58-AI58 -> 0 | AM58: =D58-U58-W58-Y58-AA58-AC58-AE58-AG58-AI58-AK58 -> 0 | AO58: =D58-U58-W58-Y58-AA58-AC58-AE58-AG58-AI58-AK58-AM58 -> 0 | AQ58: =D58-U58-W58-Y58-AA58-AC58-AE58-AG58-AI58-AK58-AM58-AO58 -> 0 | AS58: =D58-U58-W58-Y58-AA58-AC58-AE58-AG58-AI58-AK58-AM58-AO58-AQ58 -> 0
A59: CHESNEL | C59: ='2019-20'!AC11 -> 23403 | D59: =C59+905 -> 24308 | E59: =D59 -> 24308 | F59: 5632 | G59: =F59/E59 -> 0.23169327 | H59: 1427 | I59: =H59/E59 -> 0.058704953 | J59: 2335 | K59: =J59/E59 -> 0.096058911 | L59: 4821 | M59: =L59/E59 -> 0.19832977 | N59: 3390 | O59: =N59/E59 -> 0.13946026 | P59: 5072 | Q59: =P59/E59 -> 0.20865559 | R59: 905 | S59: =R59/E59 -> 0.037230541 | T59: =S59+Q59+O59+M59+K59+I59+G59 -> 0.97013329 | W59: 3129.3 | X59: 3129.3 | Y59: 8008.3 | Z59: 8008.3 | AA59: 6950 | AB59: 6950 | AC59: 5315.4 | AD59: 5315.4 | AE59: 905 | AF59: 905 | AG59: =D59-U59-W59-Y59-AA59-AC59-AE59 -> 1.8189894e-12 | AI59: =D59-U59-W59-Y59-AA59-AC59-AE59-AG59 -> 0 | AK59: =D59-U59-W59-Y59-AA59-AC59-AE59-AG59-AI59 -> 0 | AM59: =D59-U59-W59-Y59-AA59-AC59-AE59-AG59-AI59-AK59 -> 0 | AO59: =D59-U59-W59-Y59-AA59-AC59-AE59-AG59-AI59-AK59-AM59 -> 0 | AQ59: =D59-U59-W59-Y59-AA59-AC59-AE59-AG59-AI59-AK59-AM59-AO59 -> 0 | AS59: =D59-U59-W59-Y59-AA59-AC59-AE59-AG59-AI59-AK59-AM59-AO59-AQ59 -> 0
A60: ROUSSEL | C60: ='2019-20'!AC22-1536+1893.93 -> 72184.33 | D60: =C60 -> 72184.33 | E60: =D60 -> 72184.33 | F60: 27700 | G60: =F60/E60 -> 0.3837398 | H60: 5316 | I60: =H60/E60 -> 0.073644792 | J60: 8600 | K60: =J60/E60 -> 0.11913943 | L60: 19100 | M60: =L60/E60 -> 0.26460036 | N60: 11490 | O60: =N60/E60 -> 0.15917582 | Q60: =P60/E60 -> 0 | S60: =R60/E60 -> 0 | T60: =S60+Q60+O60+M60+K60+I60+G60 -> 1.0003002 | W60: 8508.65 | X60: 8508.65 | Y60: 18218.49 | Z60: 18218.49 | AA60: 20505 | AB60: 20505 | AC60: 23058 | AD60: 23058.28 | AE60: =D60-U60-W60-Y60-AA60-AC60 -> 1894.19 | AF60: 1893.93 | AG60: =D60-U60-W60-Y60-AA60-AC60-AE60 -> 0 | AI60: =D60-U60-W60-Y60-AA60-AC60-AE60-AG60 -> 0 | AK60: =D60-U60-W60-Y60-AA60-AC60-AE60-AG60-AI60 -> 0 | AM60: =D60-U60-W60-Y60-AA60-AC60-AE60-AG60-AI60-AK60 -> 0 | AO60: =D60-U60-W60-Y60-AA60-AC60-AE60-AG60-AI60-AK60-AM60 -> 0 | AQ60: =D60-U60-W60-Y60-AA60-AC60-AE60-AG60-AI60-AK60-AM60-AO60 -> 0 | AS60: =D60-U60-W60-Y60-AA60-AC60-AE60-AG60-AI60-AK60-AM60-AO60-AQ60 -> 0
A61: HULIN | C61: ='2019-20'!AC14+560 -> 35932.24 | D61: =C61 -> 35932.24 | E61: =D61 -> 35932.24 | F61: 9712 | G61: =F61/E61 -> 0.27028652 | H61: 2964 | I61: =H61/E61 -> 0.082488595 | J61: 1250 | K61: =J61/E61 -> 0.0347877 | L61: 11748 | M61: =L61/E61 -> 0.32694872 | N61: 2933 | O61: =N61/E61 -> 0.08162586 | P61: 7325 | Q61: =P61/E61 -> 0.20385592 | S61: =R61/E61 -> 0 | T61: =S61+Q61+O61+M61+K61+I61+G61 -> 0.99999332 | U61: 9698.83 | V61: 9698.63 | W61: 12109 | X61: 12109 | Y61: 13564.41 | Z61: 13564 | AA61: 0 | AC61: 0 | AE61: 560 | AF61: 560 | AG61: =D61-U61-W61-Y61-AA61-AC61-AE61 -> -3.6379788e-12 | AI61: =D61-U61-W61-Y61-AA61-AC61-AE61-AG61 -> 0 | AK61: =D61-U61-W61-Y61-AA61-AC61-AE61-AG61-AI61 -> 0 | AM61: =D61-U61-W61-Y61-AA61-AC61-AE61-AG61-AI61-AK61 -> 0 | AO61: =D61-U61-W61-Y61-AA61-AC61-AE61-AG61-AI61-AK61-AM61 -> 0 | AQ61: =D61-U61-W61-Y61-AA61-AC61-AE61-AG61-AI61-AK61-AM61-AO61 -> 0 | AS61: =D61-U61-W61-Y61-AA61-AC61-AE61-AG61-AI61-AK61-AM61-AO61-AQ61 -> 0
A62: SCI LABRADORITE | C62: 41267.73 | D62: =C62 -> 41267.73 | E62: =D62 -> 41267.73 | G62: =F62/E62 -> 0 | H62: 38268 | I62: =H62/E62 -> 0.92731052 | J62: 3000 | K62: =J62/E62 -> 0.072696027 | M62: =L62/E62 -> 0 | O62: =N62/E62 -> 0 | Q62: =P62/E62 -> 0 | S62: =R62/E62 -> 0 | T62: =S62+Q62+O62+M62+K62+I62+G62 -> 1.0000065 | W62: 11484.41 | X62: 11484.41 | AA62: 27025 | AB62: 27025 | AC62: =D62-U62-W62-Y62-AA62 -> 2758.32 | AD62: 2758 | AE62: =D62-U62-W62-Y62-AA62-AC62 -> 0 | AG62: =D62-U62-W62-Y62-AA62-AC62-AE62 -> 0 | AI62: =D62-U62-W62-Y62-AA62-AC62-AE62-AG62 -> 0 | AK62: =D62-U62-W62-Y62-AA62-AC62-AE62-AG62-AI62 -> 0 | AM62: =D62-U62-W62-Y62-AA62-AC62-AE62-AG62-AI62-AK62 -> 0 | AO62: =D62-U62-W62-Y62-AA62-AC62-AE62-AG62-AI62-AK62-AM62 -> 0 | AQ62: =D62-U62-W62-Y62-AA62-AC62-AE62-AG62-AI62-AK62-AM62-AO62 -> 0 | AS62: =D62-U62-W62-Y62-AA62-AC62-AE62-AG62-AI62-AK62-AM62-AO62-AQ62 -> 0
A63: COYER | C63: ='2019-20'!AC34-151 -> 6867.91 | D63: =C63 -> 6867.91 | E63: =D63 -> 6867.91 | G63: =F63/E63 -> 0 | I63: =H63/E63 -> 0 | K63: =J63/E63 -> 0 | M63: =L63/E63 -> 0 | O63: =N63/E63 -> 0 | P63: 6868 | Q63: =P63/E63 -> 1.0000131 | S63: =R63/E63 -> 0 | T63: =S63+Q63+O63+M63+K63+I63+G63 -> 1.0000131 | U63: 6481.29 | V63: 6481.29 | AA63: 0 | AC63: 386.14 | AD63: 386.14 | AE63: =D63-U63-W63-Y63-AA63-AC63 -> 0.48 | AG63: =D63-U63-W63-Y63-AA63-AC63-AE63 -> 0 | AI63: =D63-U63-W63-Y63-AA63-AC63-AE63-AG63 -> 0 | AK63: =D63-U63-W63-Y63-AA63-AC63-AE63-AG63-AI63 -> 0 | AM63: =D63-U63-W63-Y63-AA63-AC63-AE63-AG63-AI63-AK63 -> 0 | AO63: =D63-U63-W63-Y63-AA63-AC63-AE63-AG63-AI63-AK63-AM63 -> 0 | AQ63: =D63-U63-W63-Y63-AA63-AC63-AE63-AG63-AI63-AK63-AM63-AO63 -> 0 | AS63: =D63-U63-W63-Y63-AA63-AC63-AE63-AG63-AI63-AK63-AM63-AO63-AQ63 -> 0
A64: RF ROUSSEL | C64: 52092 | D64: 52092 | E64: =D64 -> 52092 | G64: =F64/E64 -> 0 | H64: 25000 | I64: =H64/E64 -> 0.47992014 | K64: =J64/E64 -> 0 | L64: 27092 | M64: =L64/E64 -> 0.52007986 | O64: =N64/E64 -> 0 | Q64: =P64/E64 -> 0 | S64: =R64/E64 -> 0 | T64: =S64+Q64+O64+M64+K64+I64+G64 -> 1 | W64: 34836.95 | X64: 34836.95 | AA64: 0 | AC64: =D64-W64 -> 17255.05 | AD64: 17255 | AE64: =D64-U64-W64-Y64-AA64-AC64 -> 0 | AG64: =D64-U64-W64-Y64-AA64-AC64-AE64 -> 0 | AI64: =D64-U64-W64-Y64-AA64-AC64-AE64-AG64 -> 0 | AK64: =D64-U64-W64-Y64-AA64-AC64-AE64-AG64-AI64 -> 0 | AM64: =D64-U64-W64-Y64-AA64-AC64-AE64-AG64-AI64-AK64 -> 0 | AO64: =D64-U64-W64-Y64-AA64-AC64-AE64-AG64-AI64-AK64-AM64 -> 0 | AQ64: =D64-U64-W64-Y64-AA64-AC64-AE64-AG64-AI64-AK64-AM64-AO64 -> 0 | AS64: =D64-U64-W64-Y64-AA64-AC64-AE64-AG64-AI64-AK64-AM64-AO64-AQ64 -> 0
A65: ROUILLARD | C65: 12418.93 | D65: =C65 -> 12418.93 | E65: =D65 -> 12418.93 | G65: =F65/E65 -> 0 | I65: =H65/E65 -> 0 | K65: =J65/E65 -> 0 | M65: =L65/E65 -> 0 | O65: =N65/E65 -> 0 | Q65: =P65/E65 -> 0 | R65: 12419 | S65: =R65/E65 -> 1.0000056 | T65: =S65+Q65+O65+M65+K65+I65+G65 -> 1.0000056 | Y65: =8338.69+3309.25 -> 11647.94 | Z65: =8339+3309.25 -> 11648.25 | AA65: 0 | AC65: =D65-U65-W65-Y65-AA65 -> 770.99 | AD65: 771 | AE65: =D65-U65-W65-Y65-AA65-AC65 -> 0 | AG65: =D65-U65-W65-Y65-AA65-AC65-AE65 -> 0 | AI65: =D65-U65-W65-Y65-AA65-AC65-AE65-AG65 -> 0 | AK65: =D65-U65-W65-Y65-AA65-AC65-AE65-AG65-AI65 -> 0 | AM65: =D65-U65-W65-Y65-AA65-AC65-AE65-AG65-AI65-AK65 -> 0 | AO65: =D65-U65-W65-Y65-AA65-AC65-AE65-AG65-AI65-AK65-AM65 -> 0 | AQ65: =D65-U65-W65-Y65-AA65-AC65-AE65-AG65-AI65-AK65-AM65-AO65 -> 0 | AS65: =D65-U65-W65-Y65-AA65-AC65-AE65-AG65-AI65-AK65-AM65-AO65-AQ65 -> 0
A66: LALLOZ | C66: =4885.8+715 -> 5600.8 | D66: =C66 -> 5600.8 | E66: =D66 -> 5600.8 | G66: =F66/E66 -> 0 | H66: 5601 | I66: =H66/E66 -> 1.0000357 | K66: =J66/E66 -> 0 | M66: =L66/E66 -> 0 | O66: =N66/E66 -> 0 | Q66: =P66/E66 -> 0 | S66: =R66/E66 -> 0 | T66: =S66+Q66+O66+M66+K66+I66+G66 -> 1.0000357 | AA66: 0 | AC66: =D66-U66-W66-Y66-AA66 -> 5600.8 | AD66: 5601 | AE66: =D66-U66-W66-Y66-AA66-AC66 -> 0 | AG66: =D66-U66-W66-Y66-AA66-AC66-AE66 -> 0 | AI66: =D66-U66-W66-Y66-AA66-AC66-AE66-AG66 -> 0 | AK66: =D66-U66-W66-Y66-AA66-AC66-AE66-AG66-AI66 -> 0 | AM66: =D66-U66-W66-Y66-AA66-AC66-AE66-AG66-AI66-AK66 -> 0 | AO66: =D66-U66-W66-Y66-AA66-AC66-AE66-AG66-AI66-AK66-AM66 -> 0 | AQ66: =D66-U66-W66-Y66-AA66-AC66-AE66-AG66-AI66-AK66-AM66-AO66 -> 0 | AS66: =D66-U66-W66-Y66-AA66-AC66-AE66-AG66-AI66-AK66-AM66-AO66-AQ66 -> 0
A67: BROSSARD | C67: 480 | D67: 480 | E67: =D67 -> 480 | G67: =F67/E67 -> 0 | I67: =H67/E67 -> 0 | K67: =J67/E67 -> 0 | M67: =L67/E67 -> 0 | O67: =N67/E67 -> 0 | Q67: =P67/E67 -> 0 | R67: 480 | S67: =R67/E67 -> 1 | T67: =S67+Q67+O67+M67+K67+I67+G67 -> 1 | AA67: 0 | AC67: =D67-U67-W67-Y67-AA67 -> 480 | AD67: 480 | AE67: =D67-U67-W67-Y67-AA67-AC67 -> 0 | AG67: =D67-U67-W67-Y67-AA67-AC67-AE67 -> 0 | AI67: =D67-U67-W67-Y67-AA67-AC67-AE67-AG67 -> 0 | AK67: =D67-U67-W67-Y67-AA67-AC67-AE67-AG67-AI67 -> 0 | AM67: =D67-U67-W67-Y67-AA67-AC67-AE67-AG67-AI67-AK67 -> 0 | AO67: =D67-U67-W67-Y67-AA67-AC67-AE67-AG67-AI67-AK67-AM67 -> 0 | AQ67: =D67-U67-W67-Y67-AA67-AC67-AE67-AG67-AI67-AK67-AM67-AO67 -> 0 | AS67: =D67-U67-W67-Y67-AA67-AC67-AE67-AG67-AI67-AK67-AM67-AO67-AQ67 -> 0
A68: LEDORZE | C68: 3250 | D68: 3250 | E68: =D68 -> 3250 | G68: =F68/E68 -> 0 | I68: =H68/E68 -> 0 | K68: =J68/E68 -> 0 | M68: =L68/E68 -> 0 | O68: =N68/E68 -> 0 | Q68: =P68/E68 -> 0 | R68: 3250 | S68: =R68/E68 -> 1 | T68: =S68+Q68+O68+M68+K68+I68+G68 -> 1 | AA68: 0 | AC68: =D68-U68-W68-Y68-AA68 -> 3250 | AD68: 3250 | AE68: =D68-U68-W68-Y68-AA68-AC68 -> 0 | AG68: =D68-U68-W68-Y68-AA68-AC68-AE68 -> 0 | AI68: =D68-U68-W68-Y68-AA68-AC68-AE68-AG68 -> 0 | AK68: =D68-U68-W68-Y68-AA68-AC68-AE68-AG68-AI68 -> 0 | AM68: =D68-U68-W68-Y68-AA68-AC68-AE68-AG68-AI68-AK68 -> 0 | AO68: =D68-U68-W68-Y68-AA68-AC68-AE68-AG68-AI68-AK68-AM68 -> 0 | AQ68: =D68-U68-W68-Y68-AA68-AC68-AE68-AG68-AI68-AK68-AM68-AO68 -> 0 | AS68: =D68-U68-W68-Y68-AA68-AC68-AE68-AG68-AI68-AK68-AM68-AO68-AQ68 -> 0
A69: RF FLIPO | C69: ='2019-20'!AC23+3331.53+2239.55 -> 10355.77 | D69: =C69 -> 10355.77 | E69: =D69 -> 10355.77 | G69: =F69/E69 -> 0 | H69: 10356 | I69: =H69/E69 -> 1.0000222 | K69: =J69/E69 -> 0 | M69: =L69/E69 -> 0 | O69: =N69/E69 -> 0 | Q69: =P69/E69 -> 0 | S69: =R69/E69 -> 0 | T69: =S69+Q69+O69+M69+K69+I69+G69 -> 1.0000222 | AA69: 8116 | AB69: 8116 | AC69: 0 | AE69: 0 | AG69: 0 | AI69: =D69-U69-W69-Y69-AA69-AC69-AE69-AG69 -> 2239.77 | AJ69: 2240 | AK69: =D69-U69-W69-Y69-AA69-AC69-AE69-AG69-AI69 -> 0 | AM69: =D69-U69-W69-Y69-AA69-AC69-AE69-AG69-AI69-AK69 -> 0 | AO69: =D69-U69-W69-Y69-AA69-AC69-AE69-AG69-AI69-AK69-AM69 -> 0 | AQ69: =D69-U69-W69-Y69-AA69-AC69-AE69-AG69-AI69-AK69-AM69-AO69 -> 0 | AS69: =D69-U69-W69-Y69-AA69-AC69-AE69-AG69-AI69-AK69-AM69-AO69-AQ69 -> 0
A70: BOEUVE | C70: ='2019-20'!AC20 -> 22297 | D70: =C70 -> 22297 | E70: =D70 -> 22297 | G70: =F70/E70 -> 0 | I70: =H70/E70 -> 0 | K70: =J70/E70 -> 0 | M70: =L70/E70 -> 0 | O70: =N70/E70 -> 0 | Q70: =P70/E70 -> 0 | S70: =R70/E70 -> 0 | T70: =S70+Q70+O70+M70+K70+I70+G70 -> 0 | U70: 5024.95 | V70: 5024.95 | W70: 0 | Y70: 7803.37 | Z70: 7803 | AA70: =D70-U70-W70-Y70 -> 9468.68 | AB70: 9469 | AC70: =D70-U70-W70-Y70-AA70 -> 0 | AE70: =D70-U70-W70-Y70-AA70-AC70 -> 0 | AG70: =D70-U70-W70-Y70-AA70-AC70-AE70 -> 0 | AI70: =D70-U70-W70-Y70-AA70-AC70-AE70-AG70 -> 0 | AK70: =D70-U70-W70-Y70-AA70-AC70-AE70-AG70-AI70 -> 0 | AM70: =D70-U70-W70-Y70-AA70-AC70-AE70-AG70-AI70-AK70 -> 0 | AO70: =D70-U70-W70-Y70-AA70-AC70-AE70-AG70-AI70-AK70-AM70 -> 0 | AQ70: =D70-U70-W70-Y70-AA70-AC70-AE70-AG70-AI70-AK70-AM70-AO70 -> 0 | AS70: =D70-U70-W70-Y70-AA70-AC70-AE70-AG70-AI70-AK70-AM70-AO70-AQ70 -> 0
A71: SHACHER | C71: ='2019-20'!AC24 -> 26035.14 | D71: =C71 -> 26035.14 | E71: =D71 -> 26035.14 | G71: =F71/E71 -> 0 | H71: 26035 | I71: =H71/E71 -> 0.99999462 | K71: =J71/E71 -> 0 | M71: =L71/E71 -> 0 | O71: =N71/E71 -> 0 | Q71: =P71/E71 -> 0 | S71: =R71/E71 -> 0 | T71: =S71+Q71+O71+M71+K71+I71+G71 -> 0.99999462 | U71: 14599.17 | V71: 14599.17 | W71: 0 | AA71: =D71-U71-W71-Y71 -> 11435.97 | AB71: 11436 | AC71: =D71-U71-W71-Y71-AA71 -> 0 | AE71: =D71-U71-W71-Y71-AA71-AC71 -> 0 | AG71: =D71-U71-W71-Y71-AA71-AC71-AE71 -> 0 | AI71: =D71-U71-W71-Y71-AA71-AC71-AE71-AG71 -> 0 | AK71: =D71-U71-W71-Y71-AA71-AC71-AE71-AG71-AI71 -> 0 | AM71: =D71-U71-W71-Y71-AA71-AC71-AE71-AG71-AI71-AK71 -> 0 | AO71: =D71-U71-W71-Y71-AA71-AC71-AE71-AG71-AI71-AK71-AM71 -> 0 | AQ71: =D71-U71-W71-Y71-AA71-AC71-AE71-AG71-AI71-AK71-AM71-AO71 -> 0 | AS71: =D71-U71-W71-Y71-AA71-AC71-AE71-AG71-AI71-AK71-AM71-AO71-AQ71 -> 0
A72: LEBOUCHER | C72: 14652 | D72: 14652 | E72: =D72 -> 14652 | G72: =F72/E72 -> 0 | I72: =H72/E72 -> 0 | K72: =J72/E72 -> 0 | M72: =L72/E72 -> 0 | O72: =N72/E72 -> 0 | Q72: =P72/E72 -> 0 | S72: =R72/E72 -> 0 | T72: =S72+Q72+O72+M72+K72+I72+G72 -> 0 | U72: 2993.77 | V72: 2993.77 | AA72: =D72-U72-W72-Y72 -> 11658.23 | AB72: 11658 | AC72: =D72-U72-W72-Y72-AA72 -> 0 | AE72: =D72-U72-W72-Y72-AA72-AC72 -> 0 | AG72: =D72-U72-W72-Y72-AA72-AC72-AE72 -> 0 | AI72: =D72-U72-W72-Y72-AA72-AC72-AE72-AG72 -> 0 | AK72: =D72-U72-W72-Y72-AA72-AC72-AE72-AG72-AI72 -> 0 | AM72: =D72-U72-W72-Y72-AA72-AC72-AE72-AG72-AI72-AK72 -> 0 | AO72: =D72-U72-W72-Y72-AA72-AC72-AE72-AG72-AI72-AK72-AM72 -> 0 | AQ72: =D72-U72-W72-Y72-AA72-AC72-AE72-AG72-AI72-AK72-AM72-AO72 -> 0 | AS72: =D72-U72-W72-Y72-AA72-AC72-AE72-AG72-AI72-AK72-AM72-AO72-AQ72 -> 0
A73: BICARD | C73: 12155 | D73: 12155 | E73: =D73 -> 12155 | G73: =F73/E73 -> 0 | I73: =H73/E73 -> 0 | K73: =J73/E73 -> 0 | M73: =L73/E73 -> 0 | O73: =N73/E73 -> 0 | Q73: =P73/E73 -> 0 | S73: =R73/E73 -> 0 | T73: =S73+Q73+O73+M73+K73+I73+G73 -> 0 | U73: 3207.02 | V73: 3207.02 | W73: 5961.33 | X73: 5961.33 | Y73: 2987.07 | Z73: 2987 | AA73: =D73-U73-W73-Y73 -> -0.42 | AC73: =D73-U73-W73-Y73-AA73 -> 0 | AE73: =D73-U73-W73-Y73-AA73-AC73 -> 0 | AG73: =D73-U73-W73-Y73-AA73-AC73-AE73 -> 0 | AI73: =D73-U73-W73-Y73-AA73-AC73-AE73-AG73 -> 0 | AK73: =D73-U73-W73-Y73-AA73-AC73-AE73-AG73-AI73 -> 0 | AM73: =D73-U73-W73-Y73-AA73-AC73-AE73-AG73-AI73-AK73 -> 0 | AO73: =D73-U73-W73-Y73-AA73-AC73-AE73-AG73-AI73-AK73-AM73 -> 0 | AQ73: =D73-U73-W73-Y73-AA73-AC73-AE73-AG73-AI73-AK73-AM73-AO73 -> 0 | AS73: =D73-U73-W73-Y73-AA73-AC73-AE73-AG73-AI73-AK73-AM73-AO73-AQ73 -> 0
A74: JOUAULT | C74: ='2019-20'!AC31 -> 16524.3 | D74: =C74 -> 16524.3 | E74: =D74 -> 16524.3 | G74: =F74/E74 -> 0 | H74: 4668 | I74: =H74/E74 -> 0.28249306 | J74: 448 | K74: =J74/E74 -> 0.027111587 | L74: 5122 | M74: =L74/E74 -> 0.30996774 | N74: 4954 | O74: =N74/E74 -> 0.2998009 | Q74: =P74/E74 -> 0 | R74: 835 | S74: =R74/E74 -> 0.050531641 | T74: =S74+Q74+O74+M74+K74+I74+G74 -> 0.96990493 | W74: 12600.83 | X74: 12600.83 | Y74: =C74-W74 -> 3923.47 | Z74: 3923 | AA74: =D74-U74-W74-Y74 -> 0 | AC74: =D74-U74-W74-Y74-AA74 -> 0 | AE74: =D74-U74-W74-Y74-AA74-AC74 -> 0 | AG74: =D74-U74-W74-Y74-AA74-AC74-AE74 -> 0 | AI74: =D74-U74-W74-Y74-AA74-AC74-AE74-AG74 -> 0 | AK74: =D74-U74-W74-Y74-AA74-AC74-AE74-AG74-AI74 -> 0 | AM74: =D74-U74-W74-Y74-AA74-AC74-AE74-AG74-AI74-AK74 -> 0 | AO74: =D74-U74-W74-Y74-AA74-AC74-AE74-AG74-AI74-AK74-AM74 -> 0 | AQ74: =D74-U74-W74-Y74-AA74-AC74-AE74-AG74-AI74-AK74-AM74-AO74 -> 0 | AS74: =D74-U74-W74-Y74-AA74-AC74-AE74-AG74-AI74-AK74-AM74-AO74-AQ74 -> 0
A75: BRODIN | C75: ='2019-20'!AC30 -> 13937.53 | D75: =C75 -> 13937.53 | E75: =D75 -> 13937.53 | G75: =F75/E75 -> 0 | I75: =H75/E75 -> 0 | K75: =J75/E75 -> 0 | M75: =L75/E75 -> 0 | O75: =N75/E75 -> 0 | Q75: =P75/E75 -> 0 | S75: =R75/E75 -> 0 | T75: =S75+Q75+O75+M75+K75+I75+G75 -> 0 | U75: 6587.11 | V75: 6587.11 | W75: 5042.38 | X75: 5042.38 | Y75: =D75-U75-W75 -> 2308.04 | Z75: 2309 | AA75: =D75-U75-W75-Y75 -> 0 | AC75: =D75-U75-W75-Y75-AA75 -> 0 | AE75: =D75-U75-W75-Y75-AA75-AC75 -> 0 | AG75: =D75-U75-W75-Y75-AA75-AC75-AE75 -> 0 | AI75: =D75-U75-W75-Y75-AA75-AC75-AE75-AG75 -> 0 | AK75: =D75-U75-W75-Y75-AA75-AC75-AE75-AG75-AI75 -> 0 | AM75: =D75-U75-W75-Y75-AA75-AC75-AE75-AG75-AI75-AK75 -> 0 | AO75: =D75-U75-W75-Y75-AA75-AC75-AE75-AG75-AI75-AK75-AM75 -> 0 | AQ75: =D75-U75-W75-Y75-AA75-AC75-AE75-AG75-AI75-AK75-AM75-AO75 -> 0 | AS75: =D75-U75-W75-Y75-AA75-AC75-AE75-AG75-AI75-AK75-AM75-AO75-AQ75 -> 0
A76: CHAUVEL | C76: ='2019-20'!AC32 -> 43485.66 | D76: =C76 -> 43485.66 | E76: =D76 -> 43485.66 | G76: =F76/E76 -> 0 | I76: =H76/E76 -> 0 | K76: =J76/E76 -> 0 | M76: =L76/E76 -> 0 | O76: =N76/E76 -> 0 | Q76: =P76/E76 -> 0 | S76: =R76/E76 -> 0 | T76: =S76+Q76+O76+M76+K76+I76+G76 -> 0 | U76: =6787.86+9328.37 -> 16116.23 | V76: 16116 | W76: =23306.67+1656.59 -> 24963.26 | X76: =23306.67+1656.59 -> 24963.26 | Y76: =D76-U76-W76 -> 2406.17 | Z76: 2406 | AA76: =D76-U76-W76-Y76 -> 0 | AC76: =D76-U76-W76-Y76-AA76 -> 0 | AE76: =D76-U76-W76-Y76-AA76-AC76 -> 0 | AG76: =D76-U76-W76-Y76-AA76-AC76-AE76 -> 0 | AI76: =D76-U76-W76-Y76-AA76-AC76-AE76-AG76 -> 0 | AK76: =D76-U76-W76-Y76-AA76-AC76-AE76-AG76-AI76 -> 0 | AM76: =D76-U76-W76-Y76-AA76-AC76-AE76-AG76-AI76-AK76 -> 0 | AO76: =D76-U76-W76-Y76-AA76-AC76-AE76-AG76-AI76-AK76-AM76 -> 0 | AQ76: =D76-U76-W76-Y76-AA76-AC76-AE76-AG76-AI76-AK76-AM76-AO76 -> 0 | AS76: =D76-U76-W76-Y76-AA76-AC76-AE76-AG76-AI76-AK76-AM76-AO76-AQ76 -> 0
A77: MANOIR POMMERAIE | C77: 1657.27 | D77: 1657.27 | E77: =D77 -> 1657.27 | G77: =F77/E77 -> 0 | I77: =H77/E77 -> 0 | K77: =J77/E77 -> 0 | M77: =L77/E77 -> 0 | N77: 1657 | O77: =N77/E77 -> 0.99983708 | Q77: =P77/E77 -> 0 | S77: =R77/E77 -> 0 | T77: =S77+Q77+O77+M77+K77+I77+G77 -> 0.99983708 | W77: 1657.27 | X77: 1657.27 | AA77: =D77-U77-W77-Y77 -> 0 | AC77: =D77-U77-W77-Y77-AA77 -> 0 | AE77: =D77-U77-W77-Y77-AA77-AC77 -> 0 | AG77: =D77-U77-W77-Y77-AA77-AC77-AE77 -> 0 | AI77: =D77-U77-W77-Y77-AA77-AC77-AE77-AG77 -> 0 | AK77: =D77-U77-W77-Y77-AA77-AC77-AE77-AG77-AI77 -> 0 | AM77: =D77-U77-W77-Y77-AA77-AC77-AE77-AG77-AI77-AK77 -> 0 | AO77: =D77-U77-W77-Y77-AA77-AC77-AE77-AG77-AI77-AK77-AM77 -> 0 | AQ77: =D77-U77-W77-Y77-AA77-AC77-AE77-AG77-AI77-AK77-AM77-AO77 -> 0 | AS77: =D77-U77-W77-Y77-AA77-AC77-AE77-AG77-AI77-AK77-AM77-AO77-AQ77 -> 0
A78: LEVEQUE GARAGE | C78: ='2019-20'!AC25+2846.05+1857.2 -> 18115.08 | D78: =C78 -> 18115.08 | E78: =D78 -> 18115.08 | F78: 5295 | G78: =F78/E78 -> 0.29229791 | H78: 2882 | I78: =H78/E78 -> 0.15909397 | K78: =J78/E78 -> 0 | L78: 7090 | M78: =L78/E78 -> 0.39138662 | O78: =N78/E78 -> 0 | Q78: =P78/E78 -> 0 | R78: 2846 | S78: =R78/E78 -> 0.15710668 | T78: =S78+Q78+O78+M78+K78+I78+G78 -> 0.99988518 | U78: 9499.23 | V78: 9499.23 | Y78: =D78-U78-2846.05-1857.2 -> 3912.6 | Z78: 3913 | AA78: 0 | AC78: 0 | AE78: 0 | AG78: 0 | AI78: 0 | AK78: =D78-U78-W78-Y78-AA78-AC78-AE78-AG78-AI78 -> 4703.25 | AL78: 4703 | AM78: =D78-U78-W78-Y78-AA78-AC78-AE78-AG78-AI78-AK78 -> 0 | AO78: =D78-U78-W78-Y78-AA78-AC78-AE78-AG78-AI78-AK78-AM78 -> 0 | AQ78: =D78-U78-W78-Y78-AA78-AC78-AE78-AG78-AI78-AK78-AM78-AO78 -> 0 | AS78: =D78-U78-W78-Y78-AA78-AC78-AE78-AG78-AI78-AK78-AM78-AO78-AQ78 -> 0
A79: CAUCE via joris cenier | C79: ='2019-20'!AC28 -> 15164.25 | D79: =C79 -> 15164.25 | E79: =D79 -> 15164.25 | G79: =F79/E79 -> 0 | I79: =H79/E79 -> 0 | K79: =J79/E79 -> 0 | M79: =L79/E79 -> 0 | O79: =N79/E79 -> 0 | Q79: =P79/E79 -> 0 | S79: =R79/E79 -> 0 | T79: =S79+Q79+O79+M79+K79+I79+G79 -> 0 | U79: 12569.76 | V79: 12569.76 | Y79: =D79-U79-W79 -> 2594.49 | Z79: 2594 | AA79: =D79-U79-W79-Y79 -> 0 | AC79: =D79-U79-W79-Y79-AA79 -> 0 | AE79: =D79-U79-W79-Y79-AA79-AC79 -> 0 | AG79: =D79-U79-W79-Y79-AA79-AC79-AE79 -> 0 | AI79: =D79-U79-W79-Y79-AA79-AC79-AE79-AG79 -> 0 | AK79: =D79-U79-W79-Y79-AA79-AC79-AE79-AG79-AI79 -> 0 | AM79: =D79-U79-W79-Y79-AA79-AC79-AE79-AG79-AI79-AK79 -> 0 | AO79: =D79-U79-W79-Y79-AA79-AC79-AE79-AG79-AI79-AK79-AM79 -> 0 | AQ79: =D79-U79-W79-Y79-AA79-AC79-AE79-AG79-AI79-AK79-AM79-AO79 -> 0 | AS79: =D79-U79-W79-Y79-AA79-AC79-AE79-AG79-AI79-AK79-AM79-AO79-AQ79 -> 0
A80: SCI WATIER | C80: ='2019-20'!AC33 -> 6739.37 | D80: =C80 -> 6739.37 | E80: =D80 -> 6739.37 | G80: =F80/E80 -> 0 | H80: 6739 | I80: =H80/E80 -> 0.9999451 | K80: =J80/E80 -> 0 | M80: =L80/E80 -> 0 | O80: =N80/E80 -> 0 | Q80: =P80/E80 -> 0 | S80: =R80/E80 -> 0 | T80: =S80+Q80+O80+M80+K80+I80+G80 -> 0.9999451 | U80: =D80 -> 6739.37 | V80: 6739 | AA80: =D80-U80-W80-Y80 -> 0 | AC80: =D80-U80-W80-Y80-AA80 -> 0 | AE80: =D80-U80-W80-Y80-AA80-AC80 -> 0 | AG80: =D80-U80-W80-Y80-AA80-AC80-AE80 -> 0 | AI80: =D80-U80-W80-Y80-AA80-AC80-AE80-AG80 -> 0 | AK80: =D80-U80-W80-Y80-AA80-AC80-AE80-AG80-AI80 -> 0 | AM80: =D80-U80-W80-Y80-AA80-AC80-AE80-AG80-AI80-AK80 -> 0 | AO80: =D80-U80-W80-Y80-AA80-AC80-AE80-AG80-AI80-AK80-AM80 -> 0 | AQ80: =D80-U80-W80-Y80-AA80-AC80-AE80-AG80-AI80-AK80-AM80-AO80 -> 0 | AS80: =D80-U80-W80-Y80-AA80-AC80-AE80-AG80-AI80-AK80-AM80-AO80-AQ80 -> 0
C84: =SUM(C7:C83) -> 2192400.4 | D84: =SUM(D7:D83) -> 2193304.5 | E84: =SUM(E13:E81) -> 1412268 | F84: =SUM(F13:F81) -> 340578.59 | G84: =F84/E84 -> 0.2411572 | H84: =SUM(H13:H81) -> 288432.52 | I84: =H84/E84 -> 0.20423356 | J84: =SUM(J13:J81) -> 228912.75 | K84: =J84/E84 -> 0.16208875 | L84: =SUM(L13:L81) -> 251152.92 | M84: =L84/E84 -> 0.17783659 | N84: =SUM(L13:L81) -> 251152.92 | O84: =N84/E84 -> 0.17783659 | P84: =SUM(P13:P81) -> 90839.94 | Q84: =P84/E84 -> 0.064322027 | R84: =SUM(R13:R81) -> 67469.5 | S84: =R84/E84 -> 0.047773865 | T84: =S84+Q84+O84+M84+K84+I84+G84 -> 1.0752486
A86: TOTAL CA mensuel prévu | U86: =SUM(U7:U83) -> 93516.73 | W86: =SUM(W7:W83) -> 165306.58 | Y86: =SUM(Y7:Y83) -> 78895.31 | AA86: =SUM(AA7:AA83) -> 124585.97 | AC86: =SUM(AC7:AC83) -> 109676.24 | AE86: =SUM(AE7:AE83) -> 132027.01 | AG86: =SUM(AG7:AG83) -> 70833.85 | AI86: =SUM(AI7:AI81) -> 124621.13 | AK86: =SUM(AK7:AK81) -> 109740.87 | AM86: =SUM(AM7:AM85) -> 153754.23 | AO86: =SUM(AO7:AO81) -> 71889 | AQ86: =SUM(AQ7:AQ81) -> 173482.84
A87: TOTAL CA mensuel réalisé | V87: =SUM(V7:V84) -> 93515.93 | X87: =SUM(X7:X84) -> 165306.58 | Z87: =SUM(Z7:Z84) -> 78895 | AB87: =SUM(AB7:AB84) -> 124587 | AD87: =SUM(AD7:AD84) -> 109676.36 | AF87: =SUM(AF7:AF84) -> 132023.73 | AH87: =SUM(AH7:AH84) -> 69098.85 | AJ87: =SUM(AJ7:AJ84) -> 124621.44 | AL87: =SUM(AL7:AL84) -> 109740.59 | AN87: =SUM(AN7:AN84) -> 153754.53 | AP87: =SUM(AP7:AP84) -> 71889.5 | AR87: =SUM(AR7:AR84) -> 173484.59
A88: TOTAL CA mensuel réalisé N-1 | V88: ='2019-20'!F85 -> 46313.44 | X88: ='2019-20'!H85 -> 132016 | Z88: ='2019-20'!J85 -> 135610 | AB88: ='2019-20'!L85 -> 87118.8 | AD88: ='2019-20'!N85 -> 87813.4 | AF88: ='2019-20'!P85 -> 56385.71 | AH88: ='2019-20'!R85 -> 53660.73 | AJ88: ='2019-20'!T85 -> 89965.07 | AL88: ='2019-20'!V85 -> 126697 | AN88: ='2019-20'!X85 -> 125938.76 | AP88: ='2019-20'!Z85 -> 49272.35 | AR88: ='2019-20'!AB85 -> 103333.37
A89: TOTAL CA mensuel réalisé N-2 | V89: ='2018-19'!E73 -> 26802 | X89: ='2018-19'!G73 -> 48461 | Z89: ='2018-19'!I73 -> 65002 | AB89: ='2018-19'!K73 -> 107173 | AD89: ='2018-19'!M73 -> 10172 | AF89: ='2018-19'!O73 -> 131569 | AH89: ='2018-19'!Q73 -> 120665 | AJ89: ='2018-19'!S73 -> 62022 | AL89: ='2018-19'!U73 -> 115231 | AN89: ='2018-19'!W73 -> 98006 | AP89: ='2018-19'!Y73 -> 62661 | AR89: ='2018-19'!AA73 -> 141437
AS90: PREV 2021/2022
A91: TOTAL CA prévu cumulé | U91: =U86 -> 93516.73 | W91: =W86+U91 -> 258823.31 | Y91: =Y86+W91 -> 337718.62 | AA91: =AA86+Y91 -> 462304.59 | AC91: =AC86+AA91 -> 571980.83 | AE91: =AE86+AC91 -> 704007.84 | AG91: =AG86+AE91 -> 774841.69 | AI91: =AI86+AG91 -> 899462.82 | AK91: =AK86+AI91 -> 1009203.7 | AM91: =AM86+AK91 -> 1162957.9 | AO91: =AO86+AM91 -> 1234846.9 | AQ91: =AQ86+AO91 -> 1408329.8 | AS91: =SUM(AS7:AS84) -> 785442.44
A92: TOTAL CA réalisé cumulé 2020 2021 | V92: =V87 -> 93515.93 | X92: =X87+V92 -> 258822.51 | Z92: =Z87+X92 -> 337717.51 | AB92: =AB87+Z92 -> 462304.51 | AD92: =AD87+AB92 -> 571980.87 | AF92: =AF87+AD92 -> 704004.6 | AH92: =AH87+AF92 -> 773103.45 | AJ92: =AJ87+AH92 -> 897724.89 | AL92: =AL87+AJ92 -> 1007465.5 | AN92: =AN87+AL92 -> 1161220 | AP92: =AP87+AN92 -> 1233109.5 | AR92: =AR87+AP92 -> 1406594.1
A93: TOTAL CA réalisé cumulé N-1 | V93: ='2019-20'!F88 -> 46313.44 | X93: ='2019-20'!H88 -> 178329.44 | Z93: ='2019-20'!J88 -> 313939.44 | AB93: ='2019-20'!L88 -> 401058.24 | AD93: ='2019-20'!N88 -> 488871.64 | AF93: ='2019-20'!P88 -> 545257.35 | AH93: ='2019-20'!R88 -> 598918.08 | AJ93: ='2019-20'!T88 -> 688883.15 | AL93: ='2019-20'!V88 -> 815580.15 | AN93: ='2019-20'!X88 -> 941518.91 | AP93: ='2019-20'!Z88 -> 990791.26 | AR93: ='2019-20'!AB88 -> 1094124.6
A94: TOTAL CA réalisé cumulé N-2 | V94: =V89 -> 26802 | X94: =V94+X89 -> 75263 | Z94: =X94+Z89 -> 140265 | AB94: =Z94+AB89 -> 247438 | AD94: =AB94+AD89 -> 257610 | AF94: =AD94+AF89 -> 389179 | AH94: =AF94+AH89 -> 509844 | AJ94: =AH94+AJ89 -> 571866 | AL94: =AJ94+AL89 -> 687097 | AN94: =AL94+AN89 -> 785103 | AP94: =AN94+AP89 -> 847764 | AR94: =AP94+AR89 -> 989201
V95: ='2017-18'!E71 -> 111463 | X95: ='2017-18'!G71 -> 208926.18 | Z95: ='2017-18'!I71 -> 355070.18 | AB95: ='2017-18'!K71 -> 363091.18 | AD95: ='2017-18'!M71 -> 476992.18 | AF95: ='2017-18'!O71 -> 561427.18 | AH95: ='2017-18'!Q71 -> 657549.28 | AJ95: ='2017-18'!S71 -> 771563.28 | AL95: ='2017-18'!U71 -> 888586.28 | AN95: ='2017-18'!W71 -> 995143.32 | AP95: ='2017-18'!Y71 -> 995143.32 | AR95: ='2017-18'!AA71 -> 995143.32
V97: =V92-V93 -> 47202.49 | X97: =X92-X93 -> 80493.07 | Z97: =Z92-Z93 -> 23778.07 | AB97: =AB92-AB93 -> 61246.27 | AD97: =AD92-AD93 -> 83109.23 | AF97: =AF92-AF93 -> 158747.25 | AH97: =AH92-AH93 -> 174185.37 | AJ97: =AJ92-AJ93 -> 208841.74 | AL97: =AL92-AL93 -> 191885.33 | AN97: =AN92-AN93 -> 219701.1 | AP97: =AP92-AP93 -> 242318.25 | AR97: =AR92-AR93 -> 312469.47

Sheet 2021-22
D3: =D35+D36+D42+D54+D57+D58+D62+D66+D68+D69+D76 -> 400334.3
F4: OSSATURE | G4: OB | H4: CHARPENTE | I4: CB | J4: MENUISERIE | K4: MX | L4: BARDAGE | M4: BA | N4: ISOLATION | O4: IEA | P4: PLATRERIE | Q4: PII | R4: DIVERS | S4: DIV | T4: ETUDE SUIVI | U4: DIV | W4: OCTOBRE | Y4: NOVEMBRE | AA4: DECEMBRE | AC4: JANVIER | AE4: FEVRIER | AG4: MARS | AI4: AVRIL | AK4: MAI | AM4: JUIN | AO4: JUILLET | AQ4: AOUT | AS4: SEPTEMBRE
A5: NOM | C5: CA/prevision | D5: CA/contrat | F5: BOIS | G5: % | H5: BOIS | I5: % | J5: EXTERIEURE | K5: % | L5: EXT | M5: % | N5: ETANCHEITE | O5: % | P5: ISO INT MI | Q5: % | S5: % | U5: % | W5: prévu | X5: réalisé | Y5: prévu | Z5: réalisé | AA5: prévu | AB5: réalisé | AC5: prévu | AD5: réalisé | AE5: prévu | AF5: réalisé | AG5: prévu | AH5: réalisé | AI5: prévu | AJ5: réalisé | AK5: prévu | AL5: réalisé | AM5: prévu | AN5: réalisé | AO5: prévu | AP5: réalisé | AQ5: prévu | AR5: réalisé | AS5: prévu | AT5: réalisé | AU5: 2022/2023
A7: Commission PASQUET
A8: Commission PASQUET
A9: Commission PASQUET
A10: Commission PASQUET
A11: Commission ST
A12: loret avoir
D14: =C14 -> 0 | G14: =F14/E14 -> #DIV/0! | I14: =H14/E14 -> #DIV/0! | K14: =J14/E14 -> #DIV/0! | M14: =L14/E14 -> #DIV/0! | O14: =N14/E14 -> #DIV/0! | Q14: =P14/E14 -> #DIV/0! | S14: =R14/E14 -> #DIV/0! | U14: =T14/E14 -> #DIV/0! | V14: =U14+S14+Q14+O14+M14+K14+I14+G14 -> #DIV/0! | W14: 0 | Y14: =D14-W14 -> 0 | AA14: =D14-W14-Y14 -> 0 | AC14: =D14-W14-Y14-AA14 -> 0 | AE14: =D14-W14-Y14-AA14-AC14 -> 0 | AG14: =D14-W14-Y14-AA14-AC14-AE14 -> 0 | AI14: =D14-W14-Y14-AA14-AC14-AE14-AG14 -> 0 | AK14: =D14-W14-Y14-AA14-AC14-AE14-AG14-AI14 -> 0 | AM14: =D14-W14-Y14-AA14-AC14-AE14-AG14-AI14-AK14 -> 0 | AO14: =D14-W14-Y14-AA14-AC14-AE14-AG14-AI14-AK14-AM14 -> 0 | AQ14: =D14-W14-Y14-AA14-AC14-AE14-AG14-AI14-AK14-AM14-AO14 -> 0 | AS14: =D14-W14-Y14-AA14-AC14-AE14-AG14-AI14-AK14-AM14-AO14-AQ14 -> 0 | AU14: =D14-W14-Y14-AA14-AC14-AE14-AG14-AI14-AK14-AM14-AO14-AQ14-AS14 -> 0
D15: =C15 -> 0 | G15: =F15/E15 -> #DIV/0! | I15: =H15/E15 -> #DIV/0! | K15: =J15/E15 -> #DIV/0! | M15: =L15/E15 -> #DIV/0! | O15: =N15/E15 -> #DIV/0! | Q15: =P15/E15 -> #DIV/0! | S15: =R15/E15 -> #DIV/0! | U15: =T15/E15 -> #DIV/0! | V15: =U15+S15+Q15+O15+M15+K15+I15+G15 -> #DIV/0! | W15: 0 | Y15: =D15-W15 -> 0 | AA15: =D15-W15-Y15 -> 0 | AC15: =D15-W15-Y15-AA15 -> 0 | AE15: =D15-W15-Y15-AA15-AC15 -> 0 | AG15: =D15-W15-Y15-AA15-AC15-AE15 -> 0 | AI15: =D15-W15-Y15-AA15-AC15-AE15-AG15 -> 0 | AK15: =D15-W15-Y15-AA15-AC15-AE15-AG15-AI15 -> 0 | AM15: =D15-W15-Y15-AA15-AC15-AE15-AG15-AI15-AK15 -> 0 | AO15: =D15-W15-Y15-AA15-AC15-AE15-AG15-AI15-AK15-AM15 -> 0 | AQ15: =D15-W15-Y15-AA15-AC15-AE15-AG15-AI15-AK15-AM15-AO15 -> 0 | AS15: =D15-W15-Y15-AA15-AC15-AE15-AG15-AI15-AK15-AM15-AO15-AQ15 -> 0 | AU15: =D15-W15-Y15-AA15-AC15-AE15-AG15-AI15-AK15-AM15-AO15-AQ15-AS15 -> 0
D16: =C16 -> 0 | G16: =F16/E16 -> #DIV/0! | I16: =H16/E16 -> #DIV/0! | K16: =J16/E16 -> #DIV/0! | M16: =L16/E16 -> #DIV/0! | O16: =N16/E16 -> #DIV/0! | Q16: =P16/E16 -> #DIV/0! | S16: =R16/E16 -> #DIV/0! | U16: =T16/E16 -> #DIV/0! | V16: =U16+S16+Q16+O16+M16+K16+I16+G16 -> #DIV/0! | W16: 0 | Y16: 0 | AA16: =D16-W16-Y16 -> 0 | AC16: =D16-W16-Y16-AA16 -> 0 | AE16: =D16-W16-Y16-AA16-AC16 -> 0 | AG16: =D16-W16-Y16-AA16-AC16-AE16 -> 0 | AI16: =D16-W16-Y16-AA16-AC16-AE16-AG16 -> 0 | AK16: =D16-W16-Y16-AA16-AC16-AE16-AG16-AI16 -> 0 | AM16: =D16-W16-Y16-AA16-AC16-AE16-AG16-AI16-AK16 -> 0 | AO16: =D16-W16-Y16-AA16-AC16-AE16-AG16-AI16-AK16-AM16 -> 0 | AQ16: =D16-W16-Y16-AA16-AC16-AE16-AG16-AI16-AK16-AM16-AO16 -> 0 | AS16: =D16-W16-Y16-AA16-AC16-AE16-AG16-AI16-AK16-AM16-AO16-AQ16 -> 0 | AU16: =D16-W16-Y16-AA16-AC16-AE16-AG16-AI16-AK16-AM16-AO16-AQ16-AS16 -> 0
D17: =C17 -> 0 | G17: =F17/E17 -> #DIV/0! | I17: =H17/E17 -> #DIV/0! | K17: =J17/E17 -> #DIV/0! | M17: =L17/E17 -> #DIV/0! | O17: =N17/E17 -> #DIV/0! | Q17: =P17/E17 -> #DIV/0! | S17: =R17/E17 -> #DIV/0! | U17: =T17/E17 -> #DIV/0! | V17: =U17+S17+Q17+O17+M17+K17+I17+G17 -> #DIV/0! | W17: 0 | Y17: =D17-W17 -> 0 | AA17: =D17-W17-Y17 -> 0 | AC17: =D17-W17-Y17-AA17 -> 0 | AE17: =D17-W17-Y17-AA17-AC17 -> 0 | AG17: =D17-W17-Y17-AA17-AC17-AE17 -> 0 | AI17: =D17-W17-Y17-AA17-AC17-AE17-AG17 -> 0 | AK17: =D17-W17-Y17-AA17-AC17-AE17-AG17-AI17 -> 0 | AM17: =D17-W17-Y17-AA17-AC17-AE17-AG17-AI17-AK17 -> 0 | AO17: =D17-W17-Y17-AA17-AC17-AE17-AG17-AI17-AK17-AM17 -> 0 | AQ17: =D17-W17-Y17-AA17-AC17-AE17-AG17-AI17-AK17-AM17-AO17 -> 0 | AS17: =D17-W17-Y17-AA17-AC17-AE17-AG17-AI17-AK17-AM17-AO17-AQ17 -> 0 | AU17: =D17-W17-Y17-AA17-AC17-AE17-AG17-AI17-AK17-AM17-AO17-AQ17-AS17 -> 0
D18: =C18 -> 0 | G18: =F18/E18 -> #DIV/0! | I18: =H18/E18 -> #DIV/0! | K18: =J18/E18 -> #DIV/0! | M18: =L18/E18 -> #DIV/0! | O18: =N18/E18 -> #DIV/0! | Q18: =P18/E18 -> #DIV/0! | S18: =R18/E18 -> #DIV/0! | U18: =T18/E18 -> #DIV/0! | V18: =U18+S18+Q18+O18+M18+K18+I18+G18 -> #DIV/0! | W18: 0 | Y18: =D18-W18 -> 0 | AA18: =D18-W18-Y18 -> 0 | AC18: =D18-W18-Y18-AA18 -> 0 | AE18: =D18-W18-Y18-AA18-AC18 -> 0 | AG18: =D18-W18-Y18-AA18-AC18-AE18 -> 0 | AI18: =D18-W18-Y18-AA18-AC18-AE18-AG18 -> 0 | AK18: =D18-W18-Y18-AA18-AC18-AE18-AG18-AI18 -> 0 | AM18: =D18-W18-Y18-AA18-AC18-AE18-AG18-AI18-AK18 -> 0 | AO18: =D18-W18-Y18-AA18-AC18-AE18-AG18-AI18-AK18-AM18 -> 0 | AQ18: =D18-W18-Y18-AA18-AC18-AE18-AG18-AI18-AK18-AM18-AO18 -> 0 | AS18: =D18-W18-Y18-AA18-AC18-AE18-AG18-AI18-AK18-AM18-AO18-AQ18 -> 0 | AU18: =D18-W18-Y18-AA18-AC18-AE18-AG18-AI18-AK18-AM18-AO18-AQ18-AS18 -> 0
D19: =C19 -> 0 | G19: =F19/E19 -> #DIV/0! | I19: =H19/E19 -> #DIV/0! | K19: =J19/E19 -> #DIV/0! | M19: =L19/E19 -> #DIV/0! | O19: =N19/E19 -> #DIV/0! | Q19: =P19/E19 -> #DIV/0! | S19: =R19/E19 -> #DIV/0! | U19: =T19/E19 -> #DIV/0! | V19: =U19+S19+Q19+O19+M19+K19+I19+G19 -> #DIV/0! | W19: 0 | Y19: 0 | AA19: =D19-W19-Y19 -> 0 | AC19: =D19-W19-Y19-AA19 -> 0 | AE19: =D19-W19-Y19-AA19-AC19 -> 0 | AG19: =D19-W19-Y19-AA19-AC19-AE19 -> 0 | AI19: =D19-W19-Y19-AA19-AC19-AE19-AG19 -> 0 | AK19: =D19-W19-Y19-AA19-AC19-AE19-AG19-AI19 -> 0 | AM19: =D19-W19-Y19-AA19-AC19-AE19-AG19-AI19-AK19 -> 0 | AO19: =D19-W19-Y19-AA19-AC19-AE19-AG19-AI19-AK19-AM19 -> 0 | AQ19: =D19-W19-Y19-AA19-AC19-AE19-AG19-AI19-AK19-AM19-AO19 -> 0 | AS19: =D19-W19-Y19-AA19-AC19-AE19-AG19-AI19-AK19-AM19-AO19-AQ19 -> 0 | AU19: =D19-W19-Y19-AA19-AC19-AE19-AG19-AI19-AK19-AM19-AO19-AQ19-AS19 -> 0
A20: CHATELET | C20: 864 | D20: =C20 -> 864 | E20: =D20 -> 864 | G20: =F20/E20 -> 0 | I20: =H20/E20 -> 0 | K20: =J20/E20 -> 0 | M20: =L20/E20 -> 0 | O20: =N20/E20 -> 0 | Q20: =P20/E20 -> 0 | S20: =R20/E20 -> 0 | T20: 864 | U20: =T20/E20 -> 1 | V20: =U20+S20+Q20+O20+M20+K20+I20+G20 -> 1 | W20: 0 | Y20: 0 | AA20: 0 | AC20: 0 | AE20: 0 | AG20: 0 | AI20: 0 | AK20: 0 | AM20: 0 | AO20: 0 | AQ20: 0 | AS20: =D20-W20-Y20-AA20-AC20-AE20-AG20-AI20-AK20-AM20-AO20-AQ20 -> 864 | AT20: 864 | AU20: =D20-W20-Y20-AA20-AC20-AE20-AG20-AI20-AK20-AM20-AO20-AQ20-AS20 -> 0
A21: bernard | C21: =24478+1339.94 -> 25817.94 | D21: =23536+942+1339.94 -> 25817.94 | E21: 24478 | G21: =F21/E21 -> 0 | I21: =H21/E21 -> 0 | J21: 24478 | K21: =J21/E21 -> 1 | M21: =L21/E21 -> 0 | O21: =N21/E21 -> 0 | Q21: =P21/E21 -> 0 | S21: =R21/E21 -> 0 | U21: =T21/E21 -> 0 | V21: =U21+S21+Q21+O21+M21+K21+I21+G21 -> 1 | W21: 0 | Y21: 0 | AA21: 0 | AC21: 0 | AE21: 0 | AG21: 0 | AI21: 0 | AK21: 0 | AM21: 0 | AO21: 0 | AQ21: 24478 | AR21: 24478 | AS21: =D21-W21-Y21-AA21-AC21-AE21-AG21-AI21-AK21-AM21-AO21-AQ21 -> 1339.94 | AT21: 1339.94 | AU21: =D21-W21-Y21-AA21-AC21-AE21-AG21-AI21-AK21-AM21-AO21-AQ21-AS21 -> 0
A22: LEMOINE | C22: 51440.55 | D22: =C22 -> 51440.55 | G22: =F22/E22 -> #DIV/0! | I22: =H22/E22 -> #DIV/0! | K22: =J22/E22 -> #DIV/0! | M22: =L22/E22 -> #DIV/0! | O22: =N22/E22 -> #DIV/0! | Q22: =P22/E22 -> #DIV/0! | S22: =R22/E22 -> #DIV/0! | U22: =T22/E22 -> #DIV/0! | V22: =U22+S22+Q22+O22+M22+K22+I22+G22 -> #DIV/0! | W22: 0 | Y22: 0 | AA22: 0 | AC22: 0 | AE22: 0 | AG22: 0 | AI22: 0 | AK22: 0 | AM22: 0 | AO22: 0 | AQ22: 0 | AS22: 0 | AU22: =D22-W22-Y22-AA22-AC22-AE22-AG22-AI22-AK22-AM22-AO22-AQ22-AS22 -> 51440.55
A23: CHATRE | C23: 20149.4 | D23: =C23 -> 20149.4 | G23: =F23/E23 -> #DIV/0! | I23: =H23/E23 -> #DIV/0! | K23: =J23/E23 -> #DIV/0! | M23: =L23/E23 -> #DIV/0! | O23: =N23/E23 -> #DIV/0! | Q23: =P23/E23 -> #DIV/0! | S23: =R23/E23 -> #DIV/0! | U23: =T23/E23 -> #DIV/0! | V23: =U23+S23+Q23+O23+M23+K23+I23+G23 -> #DIV/0! | W23: 0 | Y23: 0 | AA23: 0 | AC23: 0 | AE23: 0 | AG23: 0 | AI23: 0 | AK23: 0 | AM23: 0 | AO23: 0 | AQ23: 0 | AS23: 0 | AU23: =D23-W23-Y23-AA23-AC23-AE23-AG23-AI23-AK23-AM23-AO23-AQ23-AS23 -> 20149.4
A24: BASSIERE 2 | C24: =400+6799.86+887.11+9560.51+10014.49+2380.91 -> 30042.88 | D24: =C24 -> 30042.88 | G24: =F24/E24 -> #DIV/0! | I24: =H24/E24 -> #DIV/0! | K24: =J24/E24 -> #DIV/0! | M24: =L24/E24 -> #DIV/0! | O24: =N24/E24 -> #DIV/0! | Q24: =P24/E24 -> #DIV/0! | S24: =R24/E24 -> #DIV/0! | U24: =T24/E24 -> #DIV/0! | V24: =U24+S24+Q24+O24+M24+K24+I24+G24 -> #DIV/0! | W24: 0 | Y24: 0 | AA24: 0 | AC24: 0 | AE24: 0 | AG24: 0 | AI24: 0 | AK24: 0 | AM24: 0 | AO24: 0 | AQ24: 0 | AS24: 0 | AU24: =D24-W24-Y24-AA24-AC24-AE24-AG24-AI24-AK24-AM24-AO24-AQ24-AS24 -> 30042.88
A25: LEPLE | C25: 98094.97 | D25: =C25 -> 98094.97 | G25: =F25/E25 -> #DIV/0! | I25: =H25/E25 -> #DIV/0! | K25: =J25/E25 -> #DIV/0! | M25: =L25/E25 -> #DIV/0! | O25: =N25/E25 -> #DIV/0! | Q25: =P25/E25 -> #DIV/0! | S25: =R25/E25 -> #DIV/0! | U25: =T25/E25 -> #DIV/0! | V25: =U25+S25+Q25+O25+M25+K25+I25+G25 -> #DIV/0! | W25: 0 | Y25: 0 | AA25: 0 | AC25: 0 | AE25: 0 | AG25: 0 | AI25: 0 | AK25: 0 | AM25: 0 | AO25: 0 | AQ25: 0 | AS25: 0 | AU25: =D25-W25-Y25-AA25-AC25-AE25-AG25-AI25-AK25-AM25-AO25-AQ25-AS25 -> 98094.97
A26: HOFLACK | C26: =7808.84+12085.6 -> 19894.44 | D26: =C26 -> 19894.44 | E26: =D26 -> 19894.44 | G26: =F26/E26 -> 0 | H26: =E26-480-576 -> 18838.44 | I26: =H26/E26 -> 0.94691984 | K26: =J26/E26 -> 0 | M26: =L26/E26 -> 0 | O26: =N26/E26 -> 0 | Q26: =P26/E26 -> 0 | S26: =R26/E26 -> 0 | T26: =E26-H26 -> 1056 | U26: =T26/E26 -> 0.053080157 | V26: =U26+S26+Q26+O26+M26+K26+I26+G26 -> 1 | W26: 0 | Y26: 0 | AA26: 0 | AC26: 0 | AE26: 0 | AG26: 0 | AI26: 0 | AK26: 0 | AM26: 0 | AO26: 0 | AQ26: 0 | AS26: 4384 | AT26: =1834.82+2549.19 -> 4384.01 | AU26: =D26-W26-Y26-AA26-AC26-AE26-AG26-AI26-AK26-AM26-AO26-AQ26-AS26 -> 15510.44
A27: KGBR | C27: =20418.25+366.7-141+1506 -> 22149.95 | D27: =C27 -> 22149.95 | E27: =D27 -> 22149.95 | F27: 17058 | G27: =F27/E27 -> 0.77011461 | I27: =H27/E27 -> 0 | K27: =J27/E27 -> 0 | M27: =L27/E27 -> 0 | N27: 1975 | O27: =N27/E27 -> 0.089164987 | P27: 1506 | Q27: =P27/E27 -> 0.067991124 | S27: =R27/E27 -> 0 | T27: 1614 | U27: =T27/E27 -> 0.072866982 | V27: =U27+S27+Q27+O27+M27+K27+I27+G27 -> 1.0001377 | W27: 0 | Y27: 0 | AA27: 0 | AC27: 0 | AE27: 0 | AG27: 0 | AI27: 0 | AK27: 0 | AO27: =20418.84+366.7 -> 20785.54 | AP27: 20786 | AQ27: -142 | AR27: -142 | AS27: 1506.81 | AT27: 1506.81 | AU27: =D27-W27-Y27-AA27-AC27-AE27-AG27-AI27-AK27-AM27-AO27-AQ27-AS27 -> -0.4
A28: GRARD | C28: 55005 | D28: =C28 -> 55005 | G28: =F28/E28 -> #DIV/0! | I28: =H28/E28 -> #DIV/0! | K28: =J28/E28 -> #DIV/0! | M28: =L28/E28 -> #DIV/0! | O28: =N28/E28 -> #DIV/0! | Q28: =P28/E28 -> #DIV/0! | S28: =R28/E28 -> #DIV/0! | U28: =T28/E28 -> #DIV/0! | V28: =U28+S28+Q28+O28+M28+K28+I28+G28 -> #DIV/0! | W28: 0 | Y28: 0 | AA28: 0 | AC28: 0 | AE28: 0 | AG28: 0 | AI28: 0 | AK28: 0 | AM28: 0 | AO28: 0 | AQ28: 0 | AS28: 0 | AU28: =D28-W28-Y28-AA28-AC28-AE28-AG28-AI28-AK28-AM28-AO28-AQ28-AS28 -> 55005
A29: LAINE JAMET | C29: 48991.13 | D29: =C29 -> 48991.13 | E29: 48991 | F29: 17111.92 | G29: =F29/E29 -> 0.34928701 | H29: 7777.07 | I29: =H29/E29 -> 0.15874487 | K29: =J29/E29 -> 0 | L29: 17708.7 | M29: =L29/E29 -> 0.36146843 | N29: 4953.44 | O29: =N29/E29 -> 0.10110918 | Q29: =P29/E29 -> 0 | S29: =R29/E29 -> 0 | T29: 1440 | U29: =T29/E29 -> 0.029393154 | V29: =U29+S29+Q29+O29+M29+K29+I29+G29 -> 1.0000027 | W29: 0 | Y29: 0 | AA29: 0 | AC29: 0 | AE29: 0 | AG29: 0 | AI29: 0 | AK29: 0 | AM29: 0 | AO29: 0 | AQ29: 0 | AS29: 0 | AU29: =D29-W29-Y29-AA29-AC29-AE29-AG29-AI29-AK29-AM29-AO29-AQ29-AS29 -> 48991.13
A30: mairie de perrière 2 | C30: 9393.34 | D30: =C30 -> 9393.34 | E30: 9393 | G30: =F30/E30 -> 0 | H30: 9393 | I30: =H30/E30 -> 1 | K30: =J30/E30 -> 0 | M30: =L30/E30 -> 0 | O30: =N30/E30 -> 0 | Q30: =P30/E30 -> 0 | S30: =R30/E30 -> 0 | U30: =T30/E30 -> 0 | V30: =U30+S30+Q30+O30+M30+K30+I30+G30 -> 1 | W30: 0 | Y30: 0 | AA30: 0 | AC30: 0 | AE30: 0 | AG30: 0 | AI30: 0 | AK30: 0 | AM30: 0 | AO30: 0 | AQ30: 0 | AS30: 0 | AU30: =D30-W30-Y30-AA30-AC30-AE30-AG30-AI30-AK30-AM30-AO30-AQ30-AS30 -> 9393.34
G31: =F31/E31 -> #DIV/0! | I31: =H31/E31 -> #DIV/0! | K31: =J31/E31 -> #DIV/0! | M31: =L31/E31 -> #DIV/0! | O31: =N31/E31 -> #DIV/0! | Q31: =P31/E31 -> #DIV/0! | S31: =R31/E31 -> #DIV/0! | U31: =T31/E31 -> #DIV/0! | V31: =U31+S31+Q31+O31+M31+K31+I31+G31 -> #DIV/0! | W31: 0 | Y31: 0 | AA31: 0 | AC31: 0 | AE31: 0 | AG31: 0 | AI31: 0 | AK31: 0 | AM31: 0 | AO31: =D31-W31-Y31-AA31-AC31-AE31-AG31-AI31-AK31-AM31 -> 0 | AQ31: =D31-W31-Y31-AA31-AC31-AE31-AG31-AI31-AK31-AM31-AO31 -> 0 | AS31: =D31-W31-Y31-AA31-AC31-AE31-AG31-AI31-AK31-AM31-AO31-AQ31 -> 0 | AU31: =D31-W31-Y31-AA31-AC31-AE31-AG31-AI31-AK31-AM31-AO31-AQ31-AS31 -> 0
G32: =F32/E32 -> #DIV/0! | I32: =H32/E32 -> #DIV/0! | K32: =J32/E32 -> #DIV/0! | M32: =L32/E32 -> #DIV/0! | O32: =N32/E32 -> #DIV/0! | Q32: =P32/E32 -> #DIV/0! | S32: =R32/E32 -> #DIV/0! | U32: =T32/E32 -> #DIV/0! | V32: =U32+S32+Q32+O32+M32+K32+I32+G32 -> #DIV/0! | W32: 0 | Y32: 0 | AA32: 0 | AC32: 0 | AE32: 0 | AG32: 0 | AI32: 0 | AK32: 0 | AM32: 0 | AO32: 0 | AQ32: 0 | AS32: 0 | AU32: =D32-W32-Y32-AA32-AC32-AE32-AG32-AI32-AK32-AM32-AO32-AQ32-AS32 -> 0
A33: PATIN | C33: 2559 | D33: =C33 -> 2559 | E33: 2559 | G33: =F33/E33 -> 0 | I33: =H33/E33 -> 0 | J33: 2559 | K33: =J33/E33 -> 1 | M33: =L33/E33 -> 0 | O33: =N33/E33 -> 0 | Q33: =P33/E33 -> 0 | S33: =R33/E33 -> 0 | U33: =T33/E33 -> 0 | V33: =U33+S33+Q33+O33+M33+K33+I33+G33 -> 1 | W33: 0 | Y33: 0 | AA33: 0 | AC33: 0 | AE33: 0 | AG33: 0 | AI33: 0 | AK33: =D33-W33-Y33-AA33-AC33-AE33-AG33-AI33 -> 2559 | AL33: 2559.55 | AM33: =D33-W33-Y33-AA33-AC33-AE33-AG33-AI33-AK33 -> 0 | AO33: =D33-W33-Y33-AA33-AC33-AE33-AG33-AI33-AK33-AM33 -> 0 | AQ33: =D33-W33-Y33-AA33-AC33-AE33-AG33-AI33-AK33-AM33-AO33 -> 0 | AS33: =D33-W33-Y33-AA33-AC33-AE33-AG33-AI33-AK33-AM33-AO33-AQ33 -> 0 | AU33: =D33-W33-Y33-AA33-AC33-AE33-AG33-AI33-AK33-AM33-AO33-AQ33-AS33 -> 0
A34: SAUSSAYE | C34: 64547 | D34: =C34 -> 64547 | G34: =F34/E34 -> #DIV/0! | I34: =H34/E34 -> #DIV/0! | K34: =J34/E34 -> #DIV/0! | M34: =L34/E34 -> #DIV/0! | O34: =N34/E34 -> #DIV/0! | Q34: =P34/E34 -> #DIV/0! | S34: =R34/E34 -> #DIV/0! | U34: =T34/E34 -> #DIV/0! | V34: =U34+S34+Q34+O34+M34+K34+I34+G34 -> #DIV/0! | W34: 0 | Y34: 0 | AA34: 0 | AC34: 0 | AE34: 0 | AG34: 0 | AI34: 0 | AK34: 0 | AM34: 0 | AO34: 0 | AQ34: 0 | AS34: 0 | AU34: =D34-W34-Y34-AA34-AC34-AE34-AG34-AI34-AK34-AM34-AO34-AQ34-AS34 -> 64547
A35: HERVIEUX | C35: 23000 | D35: =C35 -> 23000 | E35: 23000 | G35: =F35/E35 -> 0 | I35: =H35/E35 -> 0 | K35: =J35/E35 -> 0 | M35: =L35/E35 -> 0 | O35: =N35/E35 -> 0 | Q35: =P35/E35 -> 0 | S35: =R35/E35 -> 0 | U35: =T35/E35 -> 0 | V35: =U35+S35+Q35+O35+M35+K35+I35+G35 -> 0 | W35: 0 | Y35: 0 | AA35: 0 | AC35: 0 | AE35: 0 | AG35: 0 | AI35: 0 | AK35: 0 | AM35: 0 | AO35: 0 | AQ35: 0 | AS35: 0 | AU35: =D35-W35-Y35-AA35-AC35-AE35-AG35-AI35-AK35-AM35-AO35-AQ35-AS35 -> 23000
A36: Ecole Merville | C36: =36194.29-1143.13-4941.99+4912.2+744.92 -> 35766.29 | D36: =C36 -> 35766.29 | E36: =D36 -> 35766.29 | F36: =3920.74 -> 3920.74 | G36: =F36/E36 -> 0.1096211 | H36: 2018.6 | I36: =H36/E36 -> 0.056438619 | J36: =10127.62+744.92 -> 10872.54 | K36: =J36/E36 -> 0.30398848 | L36: 8307.1 | M36: =L36/E36 -> 0.2322606 | N36: 1332.34 | O36: =N36/E36 -> 0.037251278 | P36: 3442.77 | Q36: =P36/E36 -> 0.096257398 | S36: =R36/E36 -> 0 | T36: 960 | U36: =T36/E36 -> 0.026840916 | V36: =U36+S36+Q36+O36+M36+K36+I36+G36 -> 0.86265839 | W36: 0 | Y36: 0 | AA36: 0 | AC36: 0 | AE36: 0 | AG36: 0 | AI36: 0 | AK36: 0 | AM36: 0 | AO36: 23268.65 | AP36: 23268.65 | AQ36: =D36-W36-Y36-AA36-AC36-AE36-AG36-AI36-AK36-AM36-AO36 -> 12497.64 | AR36: =4912.2+6840.5 -> 11752.7 | AS36: 744.92 | AT36: 744.92 | AU36: =D36-W36-Y36-AA36-AC36-AE36-AG36-AI36-AK36-AM36-AO36-AQ36-AS36 -> -744.92
A37: CLAPAREDE | C37: 22650.26 | D37: =C37 -> 22650.26 | G37: =F37/E37 -> #DIV/0! | I37: =H37/E37 -> #DIV/0! | K37: =J37/E37 -> #DIV/0! | M37: =L37/E37 -> #DIV/0! | O37: =N37/E37 -> #DIV/0! | Q37: =P37/E37 -> #DIV/0! | S37: =R37/E37 -> #DIV/0! | U37: =T37/E37 -> #DIV/0! | V37: =U37+S37+Q37+O37+M37+K37+I37+G37 -> #DIV/0! | W37: 0 | Y37: 0 | AA37: 0 | AC37: 0 | AE37: 0 | AG37: 0 | AI37: 0 | AK37: 0 | AM37: 0 | AO37: 0 | AQ37: 0 | AS37: 0 | AU37: =D37-W37-Y37-AA37-AC37-AE37-AG37-AI37-AK37-AM37-AO37-AQ37-AS37 -> 22650.26
A38: GONI-LACAZA | C38: 49135 | D38: =C38 -> 49135 | E38: 49185 | G38: =F38/E38 -> 0 | I38: =H38/E38 -> 0 | K38: =J38/E38 -> 0 | M38: =L38/E38 -> 0 | O38: =N38/E38 -> 0 | Q38: =P38/E38 -> 0 | R38: 48157 | S38: =R38/E38 -> 0.97909932 | T38: 1028 | U38: =T38/E38 -> 0.020900681 | V38: =U38+S38+Q38+O38+M38+K38+I38+G38 -> 1 | W38: 0 | Y38: 0 | AA38: 0 | AC38: 0 | AE38: 0 | AG38: 0 | AI38: 0 | AK38: 35385.54 | AL38: 35385.54 | AM38: 13749.99 | AN38: 13749.99 | AO38: 0 | AQ38: 0 | AU38: 0
A39: mairie de perriere | C39: 11900.45 | D39: =C39 -> 11900.45 | E39: 11900.45 | G39: =F39/E39 -> 0 | H39: =11900.45-384 -> 11516.45 | I39: =H39/E39 -> 0.96773231 | K39: =J39/E39 -> 0 | M39: =L39/E39 -> 0 | O39: =N39/E39 -> 0 | Q39: =P39/E39 -> 0 | S39: =R39/E39 -> 0 | T39: 384 | U39: =T39/E39 -> 0.032267687 | V39: =U39+S39+Q39+O39+M39+K39+I39+G39 -> 1 | W39: 0 | Y39: 0 | AA39: 0 | AC39: 0 | AE39: 0 | AG39: 0 | AI39: 11900 | AJ39: 11900.45 | AK39: =D39-W39-Y39-AA39-AC39-AE39-AG39-AI39 -> 0.45 | AM39: =D39-W39-Y39-AA39-AC39-AE39-AG39-AI39-AK39 -> 0 | AO39: =D39-W39-Y39-AA39-AC39-AE39-AG39-AI39-AK39-AM39 -> 0 | AQ39: =D39-W39-Y39-AA39-AC39-AE39-AG39-AI39-AK39-AM39-AO39 -> 0 | AS39: =D39-W39-Y39-AA39-AC39-AE39-AG39-AI39-AK39-AM39-AO39-AQ39 -> 0 | AU39: =D39-W39-Y39-AA39-AC39-AE39-AG39-AI39-AK39-AM39-AO39-AQ39-AS39 -> 0
A40: JALALI | C40: 954.55 | D40: 955 | E40: 955 | G40: =F40/E40 -> 0 | I40: =H40/E40 -> 0 | K40: =J40/E40 -> 0 | M40: =L40/E40 -> 0 | O40: =N40/E40 -> 0 | P40: 955 | Q40: =P40/E40 -> 1 | S40: =R40/E40 -> 0 | U40: =T40/E40 -> 0 | V40: =U40+S40+Q40+O40+M40+K40+I40+G40 -> 1 | W40: 0 | Y40: 0 | AA40: 0 | AC40: 0 | AE40: 0 | AG40: =D40-W40-Y40-AA40-AC40-AE40 -> 955 | AH40: 955 | AI40: =D40-W40-Y40-AA40-AC40-AE40-AG40 -> 0 | AK40: =D40-W40-Y40-AA40-AC40-AE40-AG40-AI40 -> 0 | AM40: =D40-W40-Y40-AA40-AC40-AE40-AG40-AI40-AK40 -> 0 | AO40: =D40-W40-Y40-AA40-AC40-AE40-AG40-AI40-AK40-AM40 -> 0 | AQ40: =D40-W40-Y40-AA40-AC40-AE40-AG40-AI40-AK40-AM40-AO40 -> 0 | AS40: =D40-W40-Y40-AA40-AC40-AE40-AG40-AI40-AK40-AM40-AO40-AQ40 -> 0 | AU40: =D40-W40-Y40-AA40-AC40-AE40-AG40-AI40-AK40-AM40-AO40-AQ40-AS40 -> 0
A41: JAMIN | C41: 31728 | D41: =C41 -> 31728 | E41: 31728 | G41: =F41/E41 -> 0 | I41: =H41/E41 -> 0 | K41: =J41/E41 -> 0 | M41: =L41/E41 -> 0 | O41: =N41/E41 -> 0 | Q41: =P41/E41 -> 0 | S41: =R41/E41 -> 0 | U41: =T41/E41 -> 0 | V41: =U41+S41+Q41+O41+M41+K41+I41+G41 -> 0 | W41: 0 | Y41: 0 | AA41: 0 | AC41: 0 | AE41: 0 | AG41: 0 | AI41: 0 | AK41: 0 | AM41: 0 | AO41: 0 | AQ41: 0 | AS41: 0 | AU41: =D41-W41-Y41-AA41-AC41-AE41-AG41-AI41-AK41-AM41-AO41-AQ41-AS41 -> 31728
A42: STENOU/BALOCHE | C42: =2128.33+60399.07 -> 62527.4 | D42: =C42 -> 62527.4 | E42: 66003 | G42: =F42/E42 -> 0 | I42: =H42/E42 -> 0 | K42: =J42/E42 -> 0 | M42: =L42/E42 -> 0 | O42: =N42/E42 -> 0 | Q42: =P42/E42 -> 0 | S42: =R42/E42 -> 0 | U42: =T42/E42 -> 0 | V42: =U42+S42+Q42+O42+M42+K42+I42+G42 -> 0 | W42: 0 | Y42: 0 | AA42: 0 | AC42: 0 | AE42: 0 | AG42: 0 | AI42: 10120 | AJ42: 10119.89 | AK42: 0 | AM42: 15668 | AN42: 15667.87 | AO42: 19840.76 | AP42: 19840.76 | AQ42: 3049 | AR42: 3049.48 | AS42: 12992 | AT42: =10863.43+2128.33 -> 12991.76 | AU42: =D42-W42-Y42-AA42-AC42-AE42-AG42-AI42-AK42-AM42-AO42-AQ42-AS42 -> 857.64
A43: LVM14 | C43: 432 | D43: =C43 -> 432 | E43: 432 | G43: =F43/E43 -> 0 | I43: =H43/E43 -> 0 | K43: =J43/E43 -> 0 | M43: =L43/E43 -> 0 | O43: =N43/E43 -> 0 | Q43: =P43/E43 -> 0 | R43: 432 | S43: =R43/E43 -> 1 | U43: =T43/E43 -> 0 | V43: =U43+S43+Q43+O43+M43+K43+I43+G43 -> 1 | W43: 0 | Y43: 0 | AA43: 0 | AC43: 0 | AE43: 0 | AG43: 431.6 | AH43: 431.6 | AI43: 0 | AK43: =D43-W43-Y43-AA43-AC43-AE43-AG43-AI43 -> 0.4 | AM43: =D43-W43-Y43-AA43-AC43-AE43-AG43-AI43-AK43 -> 0 | AO43: =D43-W43-Y43-AA43-AC43-AE43-AG43-AI43-AK43-AM43 -> 0 | AQ43: =D43-W43-Y43-AA43-AC43-AE43-AG43-AI43-AK43-AM43-AO43 -> 0 | AS43: =D43-W43-Y43-AA43-AC43-AE43-AG43-AI43-AK43-AM43-AO43-AQ43 -> 0 | AU43: =D43-W43-Y43-AA43-AC43-AE43-AG43-AI43-AK43-AM43-AO43-AQ43-AS43 -> 0
A44: DUMAS | C44: 107161 | D44: =C44 -> 107161 | E44: 107161 | G44: =F44/E44 -> 0 | I44: =H44/E44 -> 0 | K44: =J44/E44 -> 0 | M44: =L44/E44 -> 0 | O44: =N44/E44 -> 0 | Q44: =P44/E44 -> 0 | S44: =R44/E44 -> 0 | U44: =T44/E44 -> 0 | V44: =U44+S44+Q44+O44+M44+K44+I44+G44 -> 0 | W44: 0 | Y44: 0 | AA44: 0 | AC44: 0 | AE44: 0 | AG44: 0 | AI44: 0 | AK44: 0 | AM44: 0 | AO44: 0 | AQ44: 0 | AS44: 19199.99 | AT44: 19199.99 | AU44: =D44-W44-Y44-AA44-AC44-AE44-AG44-AI44-AK44-AM44-AO44-AQ44-AS44 -> 87961.01
A45: DMUB SARLJULMAS | C45: 200 | D45: 200 | E45: 200 | G45: =F45/E45 -> 0 | H45: 200 | I45: =H45/E45 -> 1 | K45: =J45/E45 -> 0 | M45: =L45/E45 -> 0 | O45: =N45/E45 -> 0 | Q45: =P45/E45 -> 0 | S45: =R45/E45 -> 0 | U45: =T45/E45 -> 0 | V45: =U45+S45+Q45+O45+M45+K45+I45+G45 -> 1 | W45: 0 | Y45: 0 | AA45: 0 | AC45: 0 | AE45: =D45-W45-Y45-AA45-AC45 -> 200 | AF45: 200 | AG45: =D45-W45-Y45-AA45-AC45-AE45 -> 0 | AI45: =D45-W45-Y45-AA45-AC45-AE45-AG45 -> 0 | AK45: =D45-W45-Y45-AA45-AC45-AE45-AG45-AI45 -> 0 | AM45: =D45-W45-Y45-AA45-AC45-AE45-AG45-AI45-AK45 -> 0 | AO45: =D45-W45-Y45-AA45-AC45-AE45-AG45-AI45-AK45-AM45 -> 0 | AQ45: =D45-W45-Y45-AA45-AC45-AE45-AG45-AI45-AK45-AM45-AO45 -> 0 | AS45: =D45-W45-Y45-AA45-AC45-AE45-AG45-AI45-AK45-AM45-AO45-AQ45 -> 0 | AU45: =D45-W45-Y45-AA45-AC45-AE45-AG45-AI45-AK45-AM45-AO45-AQ45-AS45 -> 0
A46: GOURDIER | C46: 3659 | D46: =C46 -> 3659 | E46: 3659 | G46: =F46/E46 -> 0 | H46: 3656 | I46: =H46/E46 -> 0.9991801 | K46: =J46/E46 -> 0 | M46: =L46/E46 -> 0 | O46: =N46/E46 -> 0 | Q46: =P46/E46 -> 0 | S46: =R46/E46 -> 0 | U46: =T46/E46 -> 0 | V46: =U46+S46+Q46+O46+M46+K46+I46+G46 -> 0.9991801 | W46: 0 | Y46: 0 | AA46: 0 | AC46: 0 | AE46: 0 | AG46: 0 | AI46: 0 | AK46: 0 | AM46: 3659 | AN46: 3658.89 | AO46: =D46-W46-Y46-AA46-AC46-AE46-AG46-AI46-AK46-AM46 -> 0 | AQ46: =D46-W46-Y46-AA46-AC46-AE46-AG46-AI46-AK46-AM46-AO46 -> 0 | AS46: =D46-W46-Y46-AA46-AC46-AE46-AG46-AI46-AK46-AM46-AO46-AQ46 -> 0 | AU46: =D46-W46-Y46-AA46-AC46-AE46-AG46-AI46-AK46-AM46-AO46-AQ46-AS46 -> 0
A47: ROULLIER | C47: =4548+3720 -> 8268 | D47: =C47 -> 8268 | E47: =4548+3720 -> 8268 | G47: =F47/E47 -> 0 | I47: =H47/E47 -> 0 | K47: =J47/E47 -> 0 | M47: =L47/E47 -> 0 | O47: =N47/E47 -> 0 | Q47: =P47/E47 -> 0 | R47: =4548+3720 -> 8268 | S47: =R47/E47 -> 1 | U47: =T47/E47 -> 0 | V47: =U47+S47+Q47+O47+M47+K47+I47+G47 -> 1 | W47: 0 | Y47: 0 | AA47: 0 | AC47: 0 | AE47: 4548 | AF47: 4548 | AG47: 0 | AI47: =D47-W47-Y47-AA47-AC47-AE47-AG47 -> 3720 | AJ47: 3720 | AK47: =D47-W47-Y47-AA47-AC47-AE47-AG47-AI47 -> 0 | AM47: =D47-W47-Y47-AA47-AC47-AE47-AG47-AI47-AK47 -> 0 | AO47: =D47-W47-Y47-AA47-AC47-AE47-AG47-AI47-AK47-AM47 -> 0 | AQ47: =D47-W47-Y47-AA47-AC47-AE47-AG47-AI47-AK47-AM47-AO47 -> 0 | AS47: =D47-W47-Y47-AA47-AC47-AE47-AG47-AI47-AK47-AM47-AO47-AQ47 -> 0 | AU47: =D47-W47-Y47-AA47-AC47-AE47-AG47-AI47-AK47-AM47-AO47-AQ47-AS47 -> 0
A48: SCI FELAH | C48: =210085.78+258777.24-13481 -> 455382.02 | D48: =C48 -> 455382.02 | E48: 455382 | F48: 47742 | G48: =F48/E48 -> 0.10483945 | H48: =16250+59169+59169+72474-(4665+4665+4665) -> 193067 | I48: =H48/E48 -> 0.42396713 | J48: =(4665*3)+28944 -> 42939 | K48: =J48/E48 -> 0.094292265 | L48: =39344+617 -> 39961 | M48: =L48/E48 -> 0.0877527 | N48: =8009+18517 -> 26526 | O48: =N48/E48 -> 0.058249997 | P48: =25837+5064 -> 30901 | Q48: =P48/E48 -> 0.067857315 | R48: =17745+51989 -> 69734 | S48: =R48/E48 -> 0.15313297 | T48: =2016+2496 -> 4512 | U48: =T48/E48 -> 0.009908165 | V48: =U48+S48+Q48+O48+M48+K48+I48+G48 -> 1 | W48: 0 | Y48: 0 | AA48: 0 | AC48: 0 | AE48: 0 | AG48: 0 | AI48: 0 | AK48: 0 | AM48: 0 | AO48: 0 | AQ48: 41303 | AR48: 41303.29 | AS48: 0 | AU48: =D48-W48-Y48-AA48-AC48-AE48-AG48-AI48-AK48-AM48-AO48-AQ48-AS48 -> 414079.02
A49: LEDORZE | C49: 4088.95 | D49: =C49 -> 4088.95 | E49: 4088.95 | G49: =F49/E49 -> 0 | I49: =H49/E49 -> 0 | K49: =J49/E49 -> 0 | L49: 4088.95 | M49: =L49/E49 -> 1 | O49: =N49/E49 -> 0 | Q49: =P49/E49 -> 0 | S49: =R49/E49 -> 0 | U49: =T49/E49 -> 0 | V49: =U49+S49+Q49+O49+M49+K49+I49+G49 -> 1 | W49: 0 | Y49: 0 | AA49: 0 | AC49: 0 | AE49: =D49-W49-Y49-AA49-AC49 -> 4088.95 | AF49: 4088.95 | AG49: =D49-W49-Y49-AA49-AC49-AE49 -> 0 | AI49: =D49-W49-Y49-AA49-AC49-AE49-AG49 -> 0 | AK49: =D49-W49-Y49-AA49-AC49-AE49-AG49-AI49 -> 0 | AM49: =D49-W49-Y49-AA49-AC49-AE49-AG49-AI49-AK49 -> 0 | AO49: =D49-W49-Y49-AA49-AC49-AE49-AG49-AI49-AK49-AM49 -> 0 | AQ49: =D49-W49-Y49-AA49-AC49-AE49-AG49-AI49-AK49-AM49-AO49 -> 0 | AS49: =D49-W49-Y49-AA49-AC49-AE49-AG49-AI49-AK49-AM49-AO49-AQ49 -> 0 | AU49: =D49-W49-Y49-AA49-AC49-AE49-AG49-AI49-AK49-AM49-AO49-AQ49-AS49 -> 0
A50: AMRAM (charpente) | C50: 22500 | D50: =C50 -> 22500 | G50: =F50/E50 -> #DIV/0! | I50: =H50/E50 -> #DIV/0! | K50: =J50/E50 -> #DIV/0! | M50: =L50/E50 -> #DIV/0! | O50: =N50/E50 -> #DIV/0! | Q50: =P50/E50 -> #DIV/0! | S50: =R50/E50 -> #DIV/0! | U50: =T50/E50 -> #DIV/0! | V50: =U50+S50+Q50+O50+M50+K50+I50+G50 -> #DIV/0! | W50: 0 | Y50: 0 | AA50: 0 | AC50: 0 | AE50: 0 | AG50: 0 | AI50: 0 | AK50: 0 | AM50: 0 | AO50: 0 | AQ50: 0 | AS50: 0 | AU50: =D50-W50-Y50-AA50-AC50-AE50-AG50-AI50-AK50-AM50-AO50-AQ50-AS50 -> 22500
A51: DEVEZAUX | C51: 3201.05 | D51: =C51 -> 3201.05 | E51: 3201.05 | G51: =F51/E51 -> 0 | I51: =H51/E51 -> 0 | K51: =J51/E51 -> 0 | M51: =L51/E51 -> 0 | O51: =N51/E51 -> 0 | Q51: =P51/E51 -> 0 | R51: 3201.05 | S51: =R51/E51 -> 1 | U51: =T51/E51 -> 0 | V51: =U51+S51+Q51+O51+M51+K51+I51+G51 -> 1 | W51: 0 | Y51: 0 | AA51: 0 | AC51: 0 | AE51: 988 | AF51: 988 | AG51: =D51-W51-Y51-AA51-AC51-AE51 -> 2213.05 | AH51: 2213 | AI51: =D51-W51-Y51-AA51-AC51-AE51-AG51 -> 0 | AK51: =D51-W51-Y51-AA51-AC51-AE51-AG51-AI51 -> 0 | AM51: =D51-W51-Y51-AA51-AC51-AE51-AG51-AI51-AK51 -> 0 | AO51: =D51-W51-Y51-AA51-AC51-AE51-AG51-AI51-AK51-AM51 -> 0 | AQ51: =D51-W51-Y51-AA51-AC51-AE51-AG51-AI51-AK51-AM51-AO51 -> 0 | AS51: =D51-W51-Y51-AA51-AC51-AE51-AG51-AI51-AK51-AM51-AO51-AQ51 -> 0 | AU51: =D51-W51-Y51-AA51-AC51-AE51-AG51-AI51-AK51-AM51-AO51-AQ51-AS51 -> 0
A52: HOTEL ZENITH | C52: 8630.91 | D52: =C52 -> 8630.91 | E52: 8630.91 | F52: 7839.41 | G52: =F52/E52 -> 0.90829472 | I52: =H52/E52 -> 0 | K52: =J52/E52 -> 0 | M52: =L52/E52 -> 0 | O52: =N52/E52 -> 0 | Q52: =P52/E52 -> 0 | R52: 503.5 | S52: =R52/E52 -> 0.058336838 | T52: 288 | U52: =T52/E52 -> 0.03336844 | V52: =U52+S52+Q52+O52+M52+K52+I52+G52 -> 1 | W52: 0 | Y52: 0 | AA52: 0 | AC52: 0 | AE52: 2640.21 | AF52: 2640 | AG52: =D52-W52-Y52-AA52-AC52-AE52 -> 5990.7 | AH52: 5991 | AI52: =D52-W52-Y52-AA52-AC52-AE52-AG52 -> 0 | AK52: =D52-W52-Y52-AA52-AC52-AE52-AG52-AI52 -> 0 | AM52: =D52-W52-Y52-AA52-AC52-AE52-AG52-AI52-AK52 -> 0 | AO52: =D52-W52-Y52-AA52-AC52-AE52-AG52-AI52-AK52-AM52 -> 0 | AQ52: =D52-W52-Y52-AA52-AC52-AE52-AG52-AI52-AK52-AM52-AO52 -> 0 | AS52: =D52-W52-Y52-AA52-AC52-AE52-AG52-AI52-AK52-AM52-AO52-AQ52 -> 0 | AU52: =D52-W52-Y52-AA52-AC52-AE52-AG52-AI52-AK52-AM52-AO52-AQ52-AS52 -> 0
A53: THEREZE | C53: =49996.2-8477.39-2106.65-144.52 -> 39267.64 | D53: =C53 -> 39267.64 | E53: =D53 -> 39267.64 | F53: 6910.14 | G53: =F53/E53 -> 0.17597543 | H53: 4214.16 | I53: =H53/E53 -> 0.1073189 | J53: 9670.67 | K53: =J53/E53 -> 0.24627581 | L53: 10770.55 | M53: =L53/E53 -> 0.27428565 | N53: 2373.95 | O53: =N53/E53 -> 0.060455632 | P53: 4272.69 | Q53: =P53/E53 -> 0.10880944 | S53: =R53/E53 -> 0 | T53: 1200 | U53: =T53/E53 -> 0.030559514 | V53: =U53+S53+Q53+O53+M53+K53+I53+G53 -> 1.0036804 | W53: 0 | Y53: 0 | AA53: 0 | AC53: 0 | AE53: 0 | AG53: 0 | AI53: 0 | AK53: 0 | AM53: 0 | AO53: 0 | AQ53: 0 | AS53: 6351 | AT53: 6351.15 | AU53: =D53-W53-Y53-AA53-AC53-AE53-AG53-AI53-AK53-AM53-AO53-AQ53-AS53 -> 32916.64
A54: THOUVENIN | C54: =26978.9+3418.83 -> 30397.73 | D54: =C54 -> 30397.73 | E54: 26978.9 | F54: 4208.39 | G54: =F54/E54 -> 0.1559882 | H54: 1677.97 | I54: =H54/E54 -> 0.062195642 | J54: 3857.98 | K54: =J54/E54 -> 0.1429999 | L54: 7778.41 | M54: =L54/E54 -> 0.28831457 | N54: 1402.22 | O54: =N54/E54 -> 0.051974691 | P54: 2534.51 | Q54: =P54/E54 -> 0.093944156 | R54: 4319.42 | S54: =R54/E54 -> 0.16010364 | T54: 1200 | U54: =T54/E54 -> 0.044479204 | V54: =U54+S54+Q54+O54+M54+K54+I54+G54 -> 1 | W54: 0 | Y54: 0 | AA54: 0 | AC54: 0 | AE54: 0 | AG54: 0 | AI54: 0 | AK54: 0 | AM54: 2699.08 | AN54: 2699.08 | AO54: 0 | AQ54: 5408 | AR54: 5408.39 | AS54: 22290 | AT54: =18871.43+3418.83 -> 22290.26 | AU54: 0
A55: LECOEUR | C55: 54260 | D55: =C55 -> 54260 | G55: =F55/E55 -> #DIV/0! | I55: =H55/E55 -> #DIV/0! | K55: =J55/E55 -> #DIV/0! | M55: =L55/E55 -> #DIV/0! | O55: =N55/E55 -> #DIV/0! | Q55: =P55/E55 -> #DIV/0! | S55: =R55/E55 -> #DIV/0! | U55: =T55/E55 -> #DIV/0! | V55: =U55+S55+Q55+O55+M55+K55+I55+G55 -> #DIV/0! | W55: 0 | Y55: 0 | AA55: 0 | AC55: 0 | AE55: 0 | AG55: 0 | AI55: 0 | AK55: 0 | AM55: 0 | AO55: 0 | AQ55: 0 | AS55: 0 | AU55: =D55-W55-Y55-AA55-AC55-AE55-AG55-AI55-AK55-AM55-AO55-AQ55-AS55 -> 54260
A56: LEGRAS | C56: =34335+3454.21 -> 37789.21 | D56: =C56 -> 37789.21 | E56: =D56 -> 37789.21 | G56: =F56/E56 -> 0 | H56: =D56 -> 37789.21 | I56: =H56/E56 -> 1 | K56: =J56/E56 -> 0 | M56: =L56/E56 -> 0 | O56: =N56/E56 -> 0 | Q56: =P56/E56 -> 0 | S56: =R56/E56 -> 0 | U56: =T56/E56 -> 0 | V56: =U56+S56+Q56+O56+M56+K56+I56+G56 -> 1 | W56: 0 | Y56: 0 | AA56: 0 | AC56: 0 | AE56: 0 | AG56: 0 | AI56: 0 | AK56: 0 | AM56: 23029 | AN56: 23029.07 | AO56: 11306 | AP56: 11306 | AS56: 3454.21 | AT56: 3454.21 | AU56: =D56-W56-Y56-AA56-AC56-AE56-AG56-AI56-AK56-AM56-AO56-AQ56-AS56 -> 0
A57: FIEFFE | C57: =35361.59-2550.74 -> 32810.85 | D57: =C57 -> 32810.85 | E57: 35361.59 | F57: 6752.67 | G57: =F57/E57 -> 0.19096059 | H57: 5918.13 | I57: =H57/E57 -> 0.1673604 | J57: 5499.62 | K57: =J57/E57 -> 0.15552525 | L57: 11024.42 | M57: =L57/E57 -> 0.31176256 | N57: 1861.39 | O57: =N57/E57 -> 0.052638753 | P57: 2395.86 | Q57: =P57/E57 -> 0.067753175 | S57: =R57/E57 -> 0 | T57: =709.5+1200 -> 1909.5 | U57: =T57/E57 -> 0.053999269 | V57: =U57+S57+Q57+O57+M57+K57+I57+G57 -> 1 | Y57: 0 | AA57: 0 | AC57: 0 | AE57: 0 | AG57: 0 | AI57: 0 | AK57: 0 | AM57: 0 | AO57: 20258.82 | AP57: 20259 | AQ57: 3888 | AR57: 3887.72 | AS57: 8664 | AT57: =11215.05-2550.74 -> 8664.31 | AU57: =D57-W57-Y57-AA57-AC57-AE57-AG57-AI57-AK57-AM57-AO57-AQ57-AS57 -> 0.03
A58: Guilloux Materiaux | C58: 13324.99 | D58: =+C58 -> 13324.99 | E58: 13325 | F58: =9408.73+480 -> 9888.73 | G58: =F58/E58 -> 0.74211857 | I58: =H58/E58 -> 0 | J58: 505.12 | K58: =J58/E58 -> 0.037907692 | M58: =L58/E58 -> 0 | N58: 1846.94 | O58: =N58/E58 -> 0.13860713 | P58: 1084.2 | Q58: =P58/E58 -> 0.081365854 | S58: =R58/E58 -> 0 | U58: =T58/E58 -> 0 | V58: =U58+S58+Q58+O58+M58+K58+I58+G58 -> 0.99999925 | Y58: =D58-W58 -> 13324.99 | Z58: 13325 | AA58: =D58-W58-Y58 -> 0 | AC58: =D58-W58-Y58-AA58 -> 0 | AE58: =D58-W58-Y58-AA58-AC58 -> 0 | AG58: =D58-W58-Y58-AA58-AC58-AE58 -> 0 | AI58: =D58-W58-Y58-AA58-AC58-AE58-AG58 -> 0 | AK58: =D58-W58-Y58-AA58-AC58-AE58-AG58-AI58 -> 0 | AM58: =D58-W58-Y58-AA58-AC58-AE58-AG58-AI58-AK58 -> 0 | AO58: =D58-W58-Y58-AA58-AC58-AE58-AG58-AI58-AK58-AM58 -> 0 | AQ58: =D58-W58-Y58-AA58-AC58-AE58-AG58-AI58-AK58-AM58-AO58 -> 0 | AS58: =D58-W58-Y58-AA58-AC58-AE58-AG58-AI58-AK58-AM58-AO58-AQ58 -> 0 | AU58: =D58-W58-Y58-AA58-AC58-AE58-AG58-AI58-AK58-AM58-AO58-AQ58-AS58 -> 0
A59: BOUQUIN | C59: 119143.21 | D59: =C59 -> 119143.21 | E59: 119143 | F59: =38415.83+1223.99 -> 39639.82 | G59: =F59/E59 -> 0.33270792 | H59: 11636.36 | I59: =H59/E59 -> 0.097667173 | J59: 22545.9 | K59: =J59/E59 -> 0.18923395 | L59: 41656.39 | M59: =L59/E59 -> 0.34963355 | N59: 2764.74 | O59: =N59/E59 -> 0.023205224 | Q59: =P59/E59 -> 0 | S59: =R59/E59 -> 0 | T59: 900 | U59: =T59/E59 -> 0.0075539478 | V59: =U59+S59+Q59+O59+M59+K59+I59+G59 -> 1.0000018 | Y59: 0 | AA59: 0 | AC59: 0 | AE59: 0 | AG59: 15915.33 | AH59: 15915.33 | AI59: 52900 | AJ59: 52900.19 | AK59: 2646.86 | AL59: 2646.86 | AM59: 20400 | AN59: 20400.4 | AO59: 27281 | AP59: 27281 | AQ59: =D59-W59-Y59-AA59-AC59-AE59-AG59-AI59-AK59-AM59-AO59 -> 0.02 | AS59: =D59-W59-Y59-AA59-AC59-AE59-AG59-AI59-AK59-AM59-AO59-AQ59 -> 0 | AU59: =D59-W59-Y59-AA59-AC59-AE59-AG59-AI59-AK59-AM59-AO59-AQ59-AS59 -> 0
A60: LEFRANCOIS (Evrecy) | C60: =5791.04+8453.84 -> 14244.88 | D60: =+C60 -> 14244.88 | E60: 14225 | G60: =F60/E60 -> 0 | I60: =H60/E60 -> 0 | K60: =J60/E60 -> 0 | M60: =L60/E60 -> 0 | O60: =N60/E60 -> 0 | Q60: =P60/E60 -> 0 | R60: 14225 | S60: =R60/E60 -> 1 | U60: =T60/E60 -> 0 | V60: =U60+S60+Q60+O60+M60+K60+I60+G60 -> 1 | Y60: 0 | AA60: 0 | AC60: 0 | AE60: 0 | AG60: 0 | AI60: 0 | AK60: 0 | AM60: 0 | AO60: 0 | AQ60: 0 | AS60: 0 | AU60: =D60-W60-Y60-AA60-AC60-AE60-AG60-AI60-AK60-AM60-AO60-AQ60-AS60 -> 14244.88
A61: MEURIOT (LGO BE HOME) | C61: 92777 | D61: =+C61 -> 92777 | G61: =F61/E61 -> #DIV/0! | I61: =H61/E61 -> #DIV/0! | K61: =J61/E61 -> #DIV/0! | M61: =L61/E61 -> #DIV/0! | O61: =N61/E61 -> #DIV/0! | Q61: =P61/E61 -> #DIV/0! | S61: =R61/E61 -> #DIV/0! | U61: =T61/E61 -> #DIV/0! | V61: =U61+S61+Q61+O61+M61+K61+I61+G61 -> #DIV/0! | Y61: 0 | AA61: 0 | AC61: 0 | AE61: 0 | AG61: 0 | AI61: 0 | AK61: 0 | AM61: 0 | AO61: 0 | AQ61: 0 | AS61: 0 | AU61: =D61-W61-Y61-AA61-AC61-AE61-AG61-AI61-AK61-AM61-AO61-AQ61-AS61 -> 92777
A62: GUIBERT (Geslin) | C62: =17461-2233-80 -> 15148 | D62: =C62 -> 15148 | E62: 17461 | G62: =F62/E62 -> 0 | I62: =H62/E62 -> 0 | K62: =J62/E62 -> 0 | M62: =L62/E62 -> 0 | O62: =N62/E62 -> 0 | Q62: =P62/E62 -> 0 | S62: =R62/E62 -> 0 | U62: =T62/E62 -> 0 | V62: =U62+S62+Q62+O62+M62+K62+I62+G62 -> 0 | Y62: 0 | AA62: 0 | AC62: 3579.71 | AD62: 3579.71 | AE62: 0 | AG62: 1922.31 | AH62: 1922.31 | AI62: 4050 | AJ62: 4050.16 | AK62: 4685 | AL62: 4684.54 | AM62: 911 | AN62: 911.42 | AO62: =D62-W62-Y62-AA62-AC62-AE62-AG62-AI62-AK62-AM62 -> -0.02 | AQ62: =D62-W62-Y62-AA62-AC62-AE62-AG62-AI62-AK62-AM62-AO62 -> 0 | AS62: =D62-W62-Y62-AA62-AC62-AE62-AG62-AI62-AK62-AM62-AO62-AQ62 -> 0 | AU62: =D62-W62-Y62-AA62-AC62-AE62-AG62-AI62-AK62-AM62-AO62-AQ62-AS62 -> 0
A63: SCI AMSD | C63: 22843 | D63: 22843 | E63: 22843 | G63: =F63/E63 -> 0 | H63: 22843 | I63: =H63/E63 -> 1 | K63: =J63/E63 -> 0 | M63: =L63/E63 -> 0 | O63: =N63/E63 -> 0 | Q63: =P63/E63 -> 0 | S63: =R63/E63 -> 0 | U63: =T63/E63 -> 0 | V63: =U63+S63+Q63+O63+M63+K63+I63+G63 -> 1 | Y63: 0 | AA63: 5982 | AB63: 5981.51 | AC63: 5170.4 | AD63: 5170.4 | AE63: 10056.18 | AF63: 10056.18 | AI63: 1634 | AJ63: 1634 | AK63: =D63-W63-Y63-AA63-AC63-AE63-AG63-AI63 -> 0.42 | AM63: =D63-W63-Y63-AA63-AC63-AE63-AG63-AI63-AK63 -> 0 | AO63: =D63-W63-Y63-AA63-AC63-AE63-AG63-AI63-AK63-AM63 -> 0 | AQ63: =D63-W63-Y63-AA63-AC63-AE63-AG63-AI63-AK63-AM63-AO63 -> 0 | AS63: =D63-W63-Y63-AA63-AC63-AE63-AG63-AI63-AK63-AM63-AO63-AQ63 -> 0 | AU63: =D63-W63-Y63-AA63-AC63-AE63-AG63-AI63-AK63-AM63-AO63-AQ63-AS63 -> 0
A64: SCI MICSTEPH | C64: 7139 | D64: 7139 | E64: 7139 | G64: =F64/E64 -> 0 | H64: 7139 | I64: =H64/E64 -> 1 | K64: =J64/E64 -> 0 | M64: =L64/E64 -> 0 | O64: =N64/E64 -> 0 | Q64: =P64/E64 -> 0 | S64: =R64/E64 -> 0 | U64: =T64/E64 -> 0 | V64: =U64+S64+Q64+O64+M64+K64+I64+G64 -> 1 | Y64: 0 | AA64: 0 | AC64: =D64-W64-Y64-AA64 -> 7139 | AD64: 7139.65 | AE64: =D64-W64-Y64-AA64-AC64 -> 0 | AG64: =D64-W64-Y64-AA64-AC64-AE64 -> 0 | AI64: =D64-W64-Y64-AA64-AC64-AE64-AG64 -> 0 | AK64: =D64-W64-Y64-AA64-AC64-AE64-AG64-AI64 -> 0 | AM64: =D64-W64-Y64-AA64-AC64-AE64-AG64-AI64-AK64 -> 0 | AO64: =D64-W64-Y64-AA64-AC64-AE64-AG64-AI64-AK64-AM64 -> 0 | AQ64: =D64-W64-Y64-AA64-AC64-AE64-AG64-AI64-AK64-AM64-AO64 -> 0 | AS64: =D64-W64-Y64-AA64-AC64-AE64-AG64-AI64-AK64-AM64-AO64-AQ64 -> 0 | AU64: =D64-W64-Y64-AA64-AC64-AE64-AG64-AI64-AK64-AM64-AO64-AQ64-AS64 -> 0
A65: BANSE BROTELANDE | C65: =2096.04+22767.26 -> 24863.3 | D65: =C65 -> 24863.3 | E65: =D65 -> 24863.3 | G65: =F65/E65 -> 0 | I65: =H65/E65 -> 0 | J65: 22767.26 | K65: =J65/E65 -> 0.91569743 | M65: =L65/E65 -> 0 | N65: 2096.04 | O65: =N65/E65 -> 0.084302566 | Q65: =P65/E65 -> 0 | S65: =R65/E65 -> 0 | U65: =T65/E65 -> 0 | V65: =U65+S65+Q65+O65+M65+K65+I65+G65 -> 1 | W65: 0 | Y65: 0 | AA65: =D65-W65-Y65 -> 24863.3 | AB65: 24863 | AC65: =D65-W65-Y65-AA65 -> 0 | AE65: =D65-W65-Y65-AA65-AC65 -> 0 | AG65: =D65-W65-Y65-AA65-AC65-AE65 -> 0 | AI65: =D65-W65-Y65-AA65-AC65-AE65-AG65 -> 0 | AK65: =D65-W65-Y65-AA65-AC65-AE65-AG65-AI65 -> 0 | AM65: =D65-W65-Y65-AA65-AC65-AE65-AG65-AI65-AK65 -> 0 | AO65: =D65-W65-Y65-AA65-AC65-AE65-AG65-AI65-AK65-AM65 -> 0 | AQ65: 314.11 | AR65: 314.11 | AU65: 0
A66: MARTINS | C66: ='2020-21'!AS16-976.86 -> 22456.67 | D66: =C66 -> 22456.67 | E66: 23434 | F66: =5274.01 -> 5274.01 | G66: =F66/E66 -> 0.22505804 | H66: 1870.13 | I66: =H66/E66 -> 0.079804131 | J66: 3332.67 | K66: =J66/E66 -> 0.14221516 | L66: 6800.94 | M66: =L66/E66 -> 0.29021678 | N66: 1406.23 | O66: =N66/E66 -> 0.060008108 | P66: 2475.19 | Q66: =P66/E66 -> 0.10562388 | R66: =976.86 -> 976.86 | S66: =R66/E66 -> 0.041685585 | T66: =397.5+900 -> 1297.5 | U66: =T66/E66 -> 0.055368268 | V66: =U66+S66+Q66+O66+M66+K66+I66+G66 -> 0.99997994 | W66: 0 | Y66: 4830 | Z66: 4829.9 | AA66: 5578 | AB66: 5578.39 | AC66: 2741.58 | AD66: 2742 | AE66: 8254.72 | AF66: 8254.72 | AG66: =D66-W66-Y66-AA66-AC66-AE66 -> 1052.37 | AH66: =-976.86+2028.94 -> 1052.08 | AI66: =D66-W66-Y66-AA66-AC66-AE66-AG66 -> 0 | AK66: =D66-W66-Y66-AA66-AC66-AE66-AG66-AI66 -> 0 | AM66: =D66-W66-Y66-AA66-AC66-AE66-AG66-AI66-AK66 -> 0 | AO66: =D66-W66-Y66-AA66-AC66-AE66-AG66-AI66-AK66-AM66 -> 0 | AQ66: =D66-W66-Y66-AA66-AC66-AE66-AG66-AI66-AK66-AM66-AO66 -> 0 | AS66: =D66-W66-Y66-AA66-AC66-AE66-AG66-AI66-AK66-AM66-AO66-AQ66 -> 0 | AU66: =D66-W66-Y66-AA66-AC66-AE66-AG66-AI66-AK66-AM66-AO66-AQ66-AS66 -> 0
A67: Mairie de MOULT | C67: ='2020-21'!AS17 -> 22357 | D67: =C67 -> 22357 | E67: 22356.5 | G67: =F67/E67 -> 0 | H67: =18576.5 -> 18576.5 | I67: =H67/E67 -> 0.83092166 | K67: =J67/E67 -> 0 | M67: =L67/E67 -> 0 | O67: =N67/E67 -> 0 | Q67: =P67/E67 -> 0 | R67: =1440+1440 -> 2880 | S67: =R67/E67 -> 0.1288216 | T67: 900 | U67: =T67/E67 -> 0.040256749 | V67: =U67+S67+Q67+O67+M67+K67+I67+G67 -> 1 | W67: 0 | Y67: 0 | AA67: 0 | AC67: 0 | AE67: 0 | AG67: =D67-W67-Y67-AA67-AC67-AE67 -> 22357 | AH67: 22357 | AI67: =D67-W67-Y67-AA67-AC67-AE67-AG67 -> 0 | AK67: =D67-W67-Y67-AA67-AC67-AE67-AG67-AI67 -> 0 | AM67: =D67-W67-Y67-AA67-AC67-AE67-AG67-AI67-AK67 -> 0 | AO67: =D67-W67-Y67-AA67-AC67-AE67-AG67-AI67-AK67-AM67 -> 0 | AQ67: =D67-W67-Y67-AA67-AC67-AE67-AG67-AI67-AK67-AM67-AO67 -> 0 | AS67: =D67-W67-Y67-AA67-AC67-AE67-AG67-AI67-AK67-AM67-AO67-AQ67 -> 0 | AU67: =D67-W67-Y67-AA67-AC67-AE67-AG67-AI67-AK67-AM67-AO67-AQ67-AS67 -> 0
A68: CROCHARD | C68: 8503 | D68: =C68 -> 8503 | E68: 8503 | G68: =F68/E68 -> 0 | H68: =4263.46+857.31+744 -> 5864.77 | I68: =H68/E68 -> 0.68972951 | J68: 2638.69 | K68: =J68/E68 -> 0.31032459 | M68: =L68/E68 -> 0 | O68: =N68/E68 -> 0 | Q68: =P68/E68 -> 0 | R68: 12602.14 | S68: =R68/E68 -> 1.4820816 | U68: =T68/E68 -> 0 | V68: =U68+S68+Q68+O68+M68+K68+I68+G68 -> 2.4821357 | W68: 0 | Y68: 1896 | Z68: 1895.84 | AA68: 0 | AC68: 0 | AE68: 5956.34 | AF68: 5956.35 | AG68: 0 | AH68: =-12098.68+12749.96 -> 651.28 | AI68: =D68-W68-Y68-AA68-AC68-AE68-AG68 -> 650.66 | AK68: =D68-W68-Y68-AA68-AC68-AE68-AG68-AI68 -> 0 | AM68: =D68-W68-Y68-AA68-AC68-AE68-AG68-AI68-AK68 -> 0 | AO68: =D68-W68-Y68-AA68-AC68-AE68-AG68-AI68-AK68-AM68 -> 0 | AQ68: =D68-W68-Y68-AA68-AC68-AE68-AG68-AI68-AK68-AM68-AO68 -> 0 | AS68: =D68-W68-Y68-AA68-AC68-AE68-AG68-AI68-AK68-AM68-AO68-AQ68 -> 0 | AU68: =D68-W68-Y68-AA68-AC68-AE68-AG68-AI68-AK68-AM68-AO68-AQ68-AS68 -> 0
A69: HERBLOT | C69: ='2020-21'!AS19+8371.22+1819.82 -> 71691.04 | D69: =C69 -> 71691.04 | E69: 61500.9 | F69: =900+9152.75 -> 10052.75 | G69: =F69/E69 -> 0.16345696 | H69: 10436.29 | I69: =H69/E69 -> 0.16969329 | J69: 8633.38 | K69: =J69/E69 -> 0.14037811 | L69: 11140.11 | M69: =L69/E69 -> 0.18113735 | N69: 3363.76 | O69: =N69/E69 -> 0.054694484 | P69: 14190.61 | Q69: =P69/E69 -> 0.23073825 | S69: =R69/E69 -> 0 | T69: 3685 | U69: =T69/E69 -> 0.059917822 | V69: =U69+S69+Q69+O69+M69+K69+I69+G69 -> 1.0000163 | W69: 0 | Y69: 10765 | Z69: 10765.17 | AC69: 16004.75 | AD69: 16004.75 | AE69: 12197.14 | AF69: 12197.14 | AG69: 16912.36 | AH69: 16912.36 | AI69: 12946 | AJ69: =6283.15+1472.69+5189.92 -> 12945.76 | AK69: 0 | AM69: 0 | AO69: 0 | AQ69: =D69-W69-Y69-AA69-AC69-AE69-AG69-AI69-AK69-AM69-AO69 -> 2865.79 | AR69: 2866 | AS69: =D69-W69-Y69-AA69-AC69-AE69-AG69-AI69-AK69-AM69-AO69-AQ69 -> 0 | AU69: =D69-W69-Y69-AA69-AC69-AE69-AG69-AI69-AK69-AM69-AO69-AQ69-AS69 -> 0
A70: VIVIER | C70: ='2020-21'!AS29+9455.68-9276 -> 9455.68 | D70: =C70 -> 9455.68 | E70: 9456 | G70: =F70/E70 -> 0 | I70: =H70/E70 -> 0 | K70: =J70/E70 -> 0 | L70: 9176 | M70: =L70/E70 -> 0.97038917 | O70: =N70/E70 -> 0 | Q70: =P70/E70 -> 0 | S70: =R70/E70 -> 0 | U70: =T70/E70 -> 0 | V70: =U70+S70+Q70+O70+M70+K70+I70+G70 -> 0.97038917 | AA70: 0 | AC70: 0 | AE70: 0 | AG70: 9456 | AH70: 9455.68 | AI70: =D70-W70-Y70-AA70-AC70-AE70-AG70 -> -0.32 | AK70: =D70-W70-Y70-AA70-AC70-AE70-AG70-AI70 -> 0 | AM70: =D70-W70-Y70-AA70-AC70-AE70-AG70-AI70-AK70 -> 0 | AO70: =D70-W70-Y70-AA70-AC70-AE70-AG70-AI70-AK70-AM70 -> 0 | AQ70: =D70-W70-Y70-AA70-AC70-AE70-AG70-AI70-AK70-AM70-AO70 -> 0 | AS70: =D70-W70-Y70-AA70-AC70-AE70-AG70-AI70-AK70-AM70-AO70-AQ70 -> 0 | AU70: =D70-W70-Y70-AA70-AC70-AE70-AG70-AI70-AK70-AM70-AO70-AQ70-AS70 -> 0
A71: MONTFOURNY SCI M.A.F.X | C71: 124584.16 | D71: =C71 -> 124584.16 | E71: 125299 | F71: =32632.97+672 -> 33304.97 | G71: =F71/E71 -> 0.26580396 | H71: 13276.2 | I71: =H71/E71 -> 0.10595615 | J71: 23415.25 | K71: =J71/E71 -> 0.186875 | L71: 25040.68 | M71: =L71/E71 -> 0.19984741 | N71: 7455.07 | O71: =N71/E71 -> 0.05949824 | P71: =20999.5+1812.52 -> 22812.02 | Q71: =P71/E71 -> 0.18206067 | S71: =R71/E71 -> 0 | U71: =T71/E71 -> 0 | V71: =U71+S71+Q71+O71+M71+K71+I71+G71 -> 1.0000414 | W71: 0 | Y71: 0 | AA71: 6107 | AB71: 6106.55 | AC71: 0 | AE71: 46840 | AF71: 46840.37 | AG71: 15425.31 | AH71: 15425.31 | AI71: 36139 | AJ71: 36139.12 | AK71: 17233.86 | AL71: 17233.86 | AM71: 2142 | AN71: 2141.52 | AO71: =D71-W71-Y71-AA71-AC71-AE71-AG71-AI71-AK71-AM71 -> 696.99 | AP71: 697 | AQ71: =D71-W71-Y71-AA71-AC71-AE71-AG71-AI71-AK71-AM71-AO71 -> 0 | AS71: =D71-W71-Y71-AA71-AC71-AE71-AG71-AI71-AK71-AM71-AO71-AQ71 -> 0 | AU71: =D71-W71-Y71-AA71-AC71-AE71-AG71-AI71-AK71-AM71-AO71-AQ71-AS71 -> 0
A72: ADB TREVIERS | C72: 149437 | D72: =C72 -> 149437 | G72: =F72/E72 -> #DIV/0! | I72: =H72/E72 -> #DIV/0! | K72: =J72/E72 -> #DIV/0! | M72: =L72/E72 -> #DIV/0! | O72: =N72/E72 -> #DIV/0! | Q72: =P72/E72 -> #DIV/0! | S72: =R72/E72 -> #DIV/0! | U72: =T72/E72 -> #DIV/0! | V72: =U72+S72+Q72+O72+M72+K72+I72+G72 -> #DIV/0! | W72: 0 | Y72: 0 | AA72: 0 | AC72: 0 | AE72: 0 | AG72: 0 | AI72: 0 | AK72: 0 | AM72: 0 | AO72: 0 | AQ72: 0 | AS72: 0 | AU72: =D72-W72-Y72-AA72-AC72-AE72-AG72-AI72-AK72-AM72-AO72-AQ72-AS72 -> 149437
A73: ADB VAL D'ARRY | C73: =125081+10460.23-583.33-450 -> 134507.9 | D73: =C73 -> 134507.9 | E73: =+D73 -> 134507.9 | F73: =900+28844 -> 29744 | G73: =F73/E73 -> 0.22113199 | H73: 34045 | I73: =H73/E73 -> 0.25310781 | J73: 25730 | K73: =J73/E73 -> 0.19128988 | L73: 28569 | M73: =L73/E73 -> 0.21239645 | N73: 5504 | O73: =N73/E73 -> 0.04091953 | Q73: =P73/E73 -> 0 | R73: 1489 | S73: =R73/E73 -> 0.011069982 | U73: =T73/E73 -> 0 | V73: =U73+S73+Q73+O73+M73+K73+I73+G73 -> 0.92991564 | W73: 0 | Y73: 0 | AA73: 0 | AC73: 20959.01 | AD73: 20959.01 | AE73: 0 | AG73: 56324.17 | AH73: 56324 | AI73: 0 | AK73: 37224 | AL73: 37224.01 | AM73: 19593 | AN73: =9716.38+9876.9 -> 19593.28 | AO73: =D73-W73-Y73-AA73-AC73-AE73-AG73-AI73-AK73-AM73 -> 407.72 | AP73: 408 | AQ73: =D73-W73-Y73-AA73-AC73-AE73-AG73-AI73-AK73-AM73-AO73 -> 0 | AS73: =D73-W73-Y73-AA73-AC73-AE73-AG73-AI73-AK73-AM73-AO73-AQ73 -> 0 | AU73: =D73-W73-Y73-AA73-AC73-AE73-AG73-AI73-AK73-AM73-AO73-AQ73-AS73 -> 0
A74: ZAGHBOUNI | C74: 117072 | D74: =C74 -> 117072 | G74: =F74/E74 -> #DIV/0! | I74: =H74/E74 -> #DIV/0! | K74: =J74/E74 -> #DIV/0! | M74: =L74/E74 -> #DIV/0! | O74: =N74/E74 -> #DIV/0! | Q74: =P74/E74 -> #DIV/0! | S74: =R74/E74 -> #DIV/0! | U74: =T74/E74 -> #DIV/0! | V74: =U74+S74+Q74+O74+M74+K74+I74+G74 -> #DIV/0! | W74: 0 | Y74: 0 | AA74: 0 | AC74: 0 | AE74: 0 | AG74: 0 | AI74: 0 | AK74: 0 | AM74: 0 | AO74: 0 | AQ74: 0 | AS74: 0 | AU74: =D74-W74-Y74-AA74-AC74-AE74-AG74-AI74-AK74-AM74-AO74-AQ74-AS74 -> 117072
A75: SCI PALLIERE | C75: 19250 | D75: =C75 -> 19250 | E75: 19250 | G75: =F75/E75 -> 0 | H75: 19250 | I75: =H75/E75 -> 1 | K75: =J75/E75 -> 0 | M75: =L75/E75 -> 0 | O75: =N75/E75 -> 0 | Q75: =P75/E75 -> 0 | S75: =R75/E75 -> 0 | U75: =T75/E75 -> 0 | V75: =U75+S75+Q75+O75+M75+K75+I75+G75 -> 1 | W75: 0 | Y75: 0 | AA75: 0 | AC75: =D75-W75-Y75-AA75 -> 19250 | AD75: 19250 | AE75: =D75-W75-Y75-AA75-AC75 -> 0 | AG75: =D75-W75-Y75-AA75-AC75-AE75 -> 0 | AI75: =D75-W75-Y75-AA75-AC75-AE75-AG75 -> 0 | AK75: =D75-W75-Y75-AA75-AC75-AE75-AG75-AI75 -> 0 | AM75: =D75-W75-Y75-AA75-AC75-AE75-AG75-AI75-AK75 -> 0 | AO75: =D75-W75-Y75-AA75-AC75-AE75-AG75-AI75-AK75-AM75 -> 0 | AQ75: =D75-W75-Y75-AA75-AC75-AE75-AG75-AI75-AK75-AM75-AO75 -> 0 | AS75: =D75-W75-Y75-AA75-AC75-AE75-AG75-AI75-AK75-AM75-AO75-AQ75 -> 0 | AU75: =D75-W75-Y75-AA75-AC75-AE75-AG75-AI75-AK75-AM75-AO75-AQ75-AS75 -> 0
A76: JARDIN | C76: =40438+30370+10568+1200+2132.33 -> 84708.33 | D76: =C76 -> 84708.33 | E76: =D76 -> 84708.33 | G76: =F76/E76 -> 0 | I76: =H76/E76 -> 0 | K76: =J76/E76 -> 0 | M76: =L76/E76 -> 0 | O76: =N76/E76 -> 0 | Q76: =P76/E76 -> 0 | S76: =R76/E76 -> 0 | T76: 1188 | U76: =T76/E76 -> 0.014024595 | V76: =U76+S76+Q76+O76+M76+K76+I76+G76 -> 0.014024595 | W76: 0 | Y76: 0 | AA76: 0 | AC76: 0 | AE76: 0 | AG76: 7497 | AH76: =626.02+2445.75+4425.21 -> 7496.98 | AI76: 0 | AK76: 38146 | AL76: =18227.74+15067.58+4851.05 -> 38146.37 | AM76: 14020 | AN76: =5823.47+6529.17+1667.42 -> 14020.06 | AO76: 8161 | AP76: =3796.92+1917.97+492+753.77+1200 -> 8160.66 | AQ76: 5423 | AR76: =735.47+2336.09+2351.76 -> 5423.32 | AS76: 11461 | AT76: =2057.82+595.93+7428.83+1378.56 -> 11461.14 | AU76: =D76-W76-Y76-AA76-AC76-AE76-AG76-AI76-AK76-AM76-AO76-AQ76-AS76 -> 0.33
D77: =C77 -> 0 | G77: =F77/E77 -> #DIV/0! | I77: =H77/E77 -> #DIV/0! | K77: =J77/E77 -> #DIV/0! | M77: =L77/E77 -> #DIV/0! | O77: =N77/E77 -> #DIV/0! | Q77: =P77/E77 -> #DIV/0! | S77: =R77/E77 -> #DIV/0! | U77: =T77/E77 -> #DIV/0! | V77: =U77+S77+Q77+O77+M77+K77+I77+G77 -> #DIV/0! | W77: 0 | Y77: =D77-W77 -> 0 | AA77: =D77-W77-Y77 -> 0 | AC77: =D77-W77-Y77-AA77 -> 0 | AE77: =D77-W77-Y77-AA77-AC77 -> 0 | AG77: =D77-W77-Y77-AA77-AC77-AE77 -> 0 | AI77: =D77-W77-Y77-AA77-AC77-AE77-AG77 -> 0 | AK77: =D77-W77-Y77-AA77-AC77-AE77-AG77-AI77 -> 0 | AM77: =D77-W77-Y77-AA77-AC77-AE77-AG77-AI77-AK77 -> 0 | AO77: =D77-W77-Y77-AA77-AC77-AE77-AG77-AI77-AK77-AM77 -> 0 | AQ77: =D77-W77-Y77-AA77-AC77-AE77-AG77-AI77-AK77-AM77-AO77 -> 0 | AS77: =D77-W77-Y77-AA77-AC77-AE77-AG77-AI77-AK77-AM77-AO77-AQ77 -> 0 | AU77: =D77-W77-Y77-AA77-AC77-AE77-AG77-AI77-AK77-AM77-AO77-AQ77-AS77 -> 0
D78: =C78 -> 0 | G78: =F78/E78 -> #DIV/0! | I78: =H78/E78 -> #DIV/0! | K78: =J78/E78 -> #DIV/0! | M78: =L78/E78 -> #DIV/0! | O78: =N78/E78 -> #DIV/0! | Q78: =P78/E78 -> #DIV/0! | S78: =R78/E78 -> #DIV/0! | U78: =T78/E78 -> #DIV/0! | V78: =U78+S78+Q78+O78+M78+K78+I78+G78 -> #DIV/0! | W78: 0 | Y78: =D78-W78 -> 0 | AA78: =D78-W78-Y78 -> 0 | AC78: =D78-W78-Y78-AA78 -> 0 | AE78: =D78-W78-Y78-AA78-AC78 -> 0 | AG78: =D78-W78-Y78-AA78-AC78-AE78 -> 0 | AI78: =D78-W78-Y78-AA78-AC78-AE78-AG78 -> 0 | AK78: =D78-W78-Y78-AA78-AC78-AE78-AG78-AI78 -> 0 | AM78: =D78-W78-Y78-AA78-AC78-AE78-AG78-AI78-AK78 -> 0 | AO78: =D78-W78-Y78-AA78-AC78-AE78-AG78-AI78-AK78-AM78 -> 0 | AQ78: =D78-W78-Y78-AA78-AC78-AE78-AG78-AI78-AK78-AM78-AO78 -> 0 | AS78: =D78-W78-Y78-AA78-AC78-AE78-AG78-AI78-AK78-AM78-AO78-AQ78 -> 0 | AU78: =D78-W78-Y78-AA78-AC78-AE78-AG78-AI78-AK78-AM78-AO78-AQ78-AS78 -> 0
D79: =C79 -> 0 | G79: =F79/E79 -> #DIV/0! | I79: =H79/E79 -> #DIV/0! | K79: =J79/E79 -> #DIV/0! | M79: =L79/E79 -> #DIV/0! | O79: =N79/E79 -> #DIV/0! | Q79: =P79/E79 -> #DIV/0! | S79: =R79/E79 -> #DIV/0! | U79: =T79/E79 -> #DIV/0! | V79: =U79+S79+Q79+O79+M79+K79+I79+G79 -> #DIV/0! | W79: 0 | Y79: 0 | AA79: =D79-W79-Y79 -> 0 | AC79: =D79-W79-Y79-AA79 -> 0 | AE79: =D79-W79-Y79-AA79-AC79 -> 0 | AG79: =D79-W79-Y79-AA79-AC79-AE79 -> 0 | AI79: =D79-W79-Y79-AA79-AC79-AE79-AG79 -> 0 | AK79: =D79-W79-Y79-AA79-AC79-AE79-AG79-AI79 -> 0 | AM79: =D79-W79-Y79-AA79-AC79-AE79-AG79-AI79-AK79 -> 0 | AO79: =D79-W79-Y79-AA79-AC79-AE79-AG79-AI79-AK79-AM79 -> 0 | AQ79: =D79-W79-Y79-AA79-AC79-AE79-AG79-AI79-AK79-AM79-AO79 -> 0 | AS79: =D79-W79-Y79-AA79-AC79-AE79-AG79-AI79-AK79-AM79-AO79-AQ79 -> 0 | AU79: =D79-W79-Y79-AA79-AC79-AE79-AG79-AI79-AK79-AM79-AO79-AQ79-AS79 -> 0
A80: LIGNE EXEMPLE GARDER | D80: =C80 -> 0 | G80: =F80/E80 -> #DIV/0! | I80: =H80/E80 -> #DIV/0! | K80: =J80/E80 -> #DIV/0! | M80: =L80/E80 -> #DIV/0! | O80: =N80/E80 -> #DIV/0! | Q80: =P80/E80 -> #DIV/0! | S80: =R80/E80 -> #DIV/0! | U80: =T80/E80 -> #DIV/0! | V80: =U80+S80+Q80+O80+M80+K80+I80+G80 -> #DIV/0! | W80: 0 | Y80: =D80-W80 -> 0 | AA80: =D80-W80-Y80 -> 0 | AC80: =D80-W80-Y80-AA80 -> 0 | AE80: =D80-W80-Y80-AA80-AC80 -> 0 | AG80: =D80-W80-Y80-AA80-AC80-AE80 -> 0 | AI80: =D80-W80-Y80-AA80-AC80-AE80-AG80 -> 0 | AK80: =D80-W80-Y80-AA80-AC80-AE80-AG80-AI80 -> 0 | AM80: =D80-W80-Y80-AA80-AC80-AE80-AG80-AI80-AK80 -> 0 | AO80: =D80-W80-Y80-AA80-AC80-AE80-AG80-AI80-AK80-AM80 -> 0 | AQ80: =D80-W80-Y80-AA80-AC80-AE80-AG80-AI80-AK80-AM80-AO80 -> 0 | AS80: =D80-W80-Y80-AA80-AC80-AE80-AG80-AI80-AK80-AM80-AO80-AQ80 -> 0 | AU80: =D80-W80-Y80-AA80-AC80-AE80-AG80-AI80-AK80-AM80-AO80-AQ80-AS80 -> 0
U81: =T81/E81 -> #DIV/0! | V81: =U81+S81+Q81+O81+M81+K81+I81+G81 -> #DIV/0!
A82: JAGER | C82: ='2020-21'!AS20 -> 67013.93 | D82: =C82 -> 67013.93 | E82: ='2020-21'!D20-'2020-21'!E20 -> 67013.78 | F82: =6950+17276.75-1450-11033.19 -> 11743.56 | G82: =F82/E82 -> 0.17524097 | H82: =6800.96-1804.96 -> 4996 | I82: =H82/E82 -> 0.074551831 | J82: 12139.26 | K82: =J82/E82 -> 0.18114573 | L82: 17237.07 | M82: =L82/E82 -> 0.2572168 | N82: 3360.83 | O82: =N82/E82 -> 0.050151327 | P82: 13445.76 | Q82: =P82/E82 -> 0.20064172 | R82: 4391.3 | S82: =R82/E82 -> 0.065528314 | U82: =T82/E82 -> 0 | V82: =U82+S82+Q82+O82+M82+K82+I82+G82 -> 1.0044767 | W82: 33546 | X82: 33546.46 | Y82: 13339 | Z82: 13338.81 | AA82: 12553.04 | AB82: 12553.04 | AC82: 3154.29 | AD82: 3154.29 | AG82: 0 | AI82: 0 | AK82: 0 | AM82: 0 | AO82: 0 | AQ82: 0 | AU82: =D82-W82-Y82-AA82-AC82-AE82-AG82-AI82-AK82-AM82-AO82-AQ82-AS82 -> 4421.6
A83: LEMOINE | C83: ='2020-21'!AS21 -> 0 | D83: =C83 -> 0 | G83: =F83/E83 -> #DIV/0! | I83: =H83/E83 -> #DIV/0! | K83: =J83/E83 -> #DIV/0! | M83: =L83/E83 -> #DIV/0! | O83: =N83/E83 -> #DIV/0! | Q83: =P83/E83 -> #DIV/0! | S83: =R83/E83 -> #DIV/0! | U83: =T83/E83 -> #DIV/0! | V83: =U83+S83+Q83+O83+M83+K83+I83+G83 -> #DIV/0! | W83: =D83 -> 0 | Y83: =D83-W83 -> 0 | AA83: =D83-W83-Y83 -> 0 | AC83: =D83-W83-Y83-AA83 -> 0 | AE83: =D83-W83-Y83-AA83-AC83 -> 0 | AG83: =D83-W83-Y83-AA83-AC83-AE83 -> 0 | AI83: =D83-W83-Y83-AA83-AC83-AE83-AG83 -> 0 | AK83: =D83-W83-Y83-AA83-AC83-AE83-AG83-AI83 -> 0 | AM83: =D83-W83-Y83-AA83-AC83-AE83-AG83-AI83-AK83 -> 0 | AO83: =D83-W83-Y83-AA83-AC83-AE83-AG83-AI83-AK83-AM83 -> 0 | AQ83: =D83-W83-Y83-AA83-AC83-AE83-AG83-AI83-AK83-AM83-AO83 -> 0 | AS83: =D83-W83-Y83-AA83-AC83-AE83-AG83-AI83-AK83-AM83-AO83-AQ83 -> 0 | AU83: =D83-W83-Y83-AA83-AC83-AE83-AG83-AI83-AK83-AM83-AO83-AQ83-AS83 -> 0
A84: FRANCOIS | C84: ='2020-21'!AS22 -> 39729 | D84: =C84 -> 39729 | E84: 39729 | F84: =14273+3025-900-4011.91 -> 12386.09 | G84: =F84/E84 -> 0.31176445 | H84: =3807.17-1141.89 -> 2665.28 | I84: =H84/E84 -> 0.067086511 | J84: =8973.49-2216.25 -> 6757.24 | K84: =J84/E84 -> 0.17008331 | L84: =18080.58-4084.8 -> 13995.78 | M84: =L84/E84 -> 0.35228121 | N84: 3924.83 | O84: =N84/E84 -> 0.098790053 | Q84: =P84/E84 -> 0 | S84: =R84/E84 -> 0 | U84: =T84/E84 -> 0 | V84: =U84+S84+Q84+O84+M84+K84+I84+G84 -> 1.0000055 | W84: 13251 | X84: 13250.89 | Y84: 10623 | Z84: 10622.69 | AA84: 0 | AC84: =D84-W84-Y84-AA84 -> 15855 | AD84: 15855.68 | AE84: =D84-W84-Y84-AA84-AC84 -> 0 | AG84: =D84-W84-Y84-AA84-AC84-AE84 -> 0 | AI84: =D84-W84-Y84-AA84-AC84-AE84-AG84 -> 0 | AK84: =D84-W84-Y84-AA84-AC84-AE84-AG84-AI84 -> 0 | AM84: =D84-W84-Y84-AA84-AC84-AE84-AG84-AI84-AK84 -> 0 | AO84: =D84-W84-Y84-AA84-AC84-AE84-AG84-AI84-AK84-AM84 -> 0 | AQ84: =D84-W84-Y84-AA84-AC84-AE84-AG84-AI84-AK84-AM84-AO84 -> 0 | AS84: =D84-W84-Y84-AA84-AC84-AE84-AG84-AI84-AK84-AM84-AO84-AQ84 -> 0 | AU84: =D84-W84-Y84-AA84-AC84-AE84-AG84-AI84-AK84-AM84-AO84-AQ84-AS84 -> 0
A85: CUVIGNY | C85: ='2020-21'!AS23 -> 0 | D85: =C85 -> 0 | G85: =F85/E85 -> #DIV/0! | I85: =H85/E85 -> #DIV/0! | K85: =J85/E85 -> #DIV/0! | M85: =L85/E85 -> #DIV/0! | O85: =N85/E85 -> #DIV/0! | Q85: =P85/E85 -> #DIV/0! | S85: =R85/E85 -> #DIV/0! | U85: =T85/E85 -> #DIV/0! | V85: =U85+S85+Q85+O85+M85+K85+I85+G85 -> #DIV/0! | W85: =D85 -> 0 | Y85: =D85-W85 -> 0 | AA85: =D85-W85-Y85 -> 0 | AC85: =D85-W85-Y85-AA85 -> 0 | AE85: =D85-W85-Y85-AA85-AC85 -> 0 | AG85: =D85-W85-Y85-AA85-AC85-AE85 -> 0 | AI85: =D85-W85-Y85-AA85-AC85-AE85-AG85 -> 0 | AK85: =D85-W85-Y85-AA85-AC85-AE85-AG85-AI85 -> 0 | AM85: =D85-W85-Y85-AA85-AC85-AE85-AG85-AI85-AK85 -> 0 | AO85: =D85-W85-Y85-AA85-AC85-AE85-AG85-AI85-AK85-AM85 -> 0 | AQ85: =D85-W85-Y85-AA85-AC85-AE85-AG85-AI85-AK85-AM85-AO85 -> 0 | AS85: =D85-W85-Y85-AA85-AC85-AE85-AG85-AI85-AK85-AM85-AO85-AQ85 -> 0 | AU85: =D85-W85-Y85-AA85-AC85-AE85-AG85-AI85-AK85-AM85-AO85-AQ85-AS85 -> 0
A86: BASSIERE | C86: ='2020-21'!AS24 -> 0 | D86: =C86 -> 0 | G86: =F86/E86 -> #DIV/0! | I86: =H86/E86 -> #DIV/0! | K86: 0 | M86: =L86/E86 -> #DIV/0! | O86: =N86/E86 -> #DIV/0! | Q86: =P86/E86 -> #DIV/0! | S86: =R86/E86 -> #DIV/0! | U86: =T86/E86 -> #DIV/0! | V86: =U86+S86+Q86+O86+M86+K86+I86+G86 -> #DIV/0! | W86: =D86 -> 0 | Y86: =D86-W86 -> 0 | AA86: =D86-W86-Y86 -> 0 | AC86: =D86-W86-Y86-AA86 -> 0 | AE86: =D86-W86-Y86-AA86-AC86 -> 0 | AG86: =D86-W86-Y86-AA86-AC86-AE86 -> 0 | AI86: =D86-W86-Y86-AA86-AC86-AE86-AG86 -> 0 | AK86: =D86-W86-Y86-AA86-AC86-AE86-AG86-AI86 -> 0 | AM86: =D86-W86-Y86-AA86-AC86-AE86-AG86-AI86-AK86 -> 0 | AO86: =D86-W86-Y86-AA86-AC86-AE86-AG86-AI86-AK86-AM86 -> 0 | AQ86: =D86-W86-Y86-AA86-AC86-AE86-AG86-AI86-AK86-AM86-AO86 -> 0 | AS86: =D86-W86-Y86-AA86-AC86-AE86-AG86-AI86-AK86-AM86-AO86-AQ86 -> 0 | AU86: =D86-W86-Y86-AA86-AC86-AE86-AG86-AI86-AK86-AM86-AO86-AQ86-AS86 -> 0
A87: EXAEQUO | C87: ='2020-21'!AS25 -> 0 | D87: =C87 -> 0 | G87: =F87/E87 -> #DIV/0! | I87: =H87/E87 -> #DIV/0! | K87: =J87/E87 -> #DIV/0! | M87: =L87/E87 -> #DIV/0! | O87: =N87/E87 -> #DIV/0! | Q87: =P87/E87 -> #DIV/0! | S87: =R87/E87 -> #DIV/0! | U87: =T87/E87 -> #DIV/0! | V87: =U87+S87+Q87+O87+M87+K87+I87+G87 -> #DIV/0! | W87: =D87 -> 0 | Y87: =D87-W87 -> 0 | AA87: =D87-W87-Y87 -> 0 | AC87: =D87-W87-Y87-AA87 -> 0 | AE87: =D87-W87-Y87-AA87-AC87 -> 0 | AG87: =D87-W87-Y87-AA87-AC87-AE87 -> 0 | AI87: =D87-W87-Y87-AA87-AC87-AE87-AG87 -> 0 | AK87: =D87-W87-Y87-AA87-AC87-AE87-AG87-AI87 -> 0 | AM87: =D87-W87-Y87-AA87-AC87-AE87-AG87-AI87-AK87 -> 0 | AO87: =D87-W87-Y87-AA87-AC87-AE87-AG87-AI87-AK87-AM87 -> 0 | AQ87: =D87-W87-Y87-AA87-AC87-AE87-AG87-AI87-AK87-AM87-AO87 -> 0 | AS87: =D87-W87-Y87-AA87-AC87-AE87-AG87-AI87-AK87-AM87-AO87-AQ87 -> 0 | AU87: =D87-W87-Y87-AA87-AC87-AE87-AG87-AI87-AK87-AM87-AO87-AQ87-AS87 -> 0
A88: PREVOST | C88: ='2020-21'!AS26 -> 0 | D88: =C88 -> 0 | G88: =F88/E88 -> #DIV/0! | I88: =H88/E88 -> #DIV/0! | K88: =J88/E88 -> #DIV/0! | M88: =L88/E88 -> #DIV/0! | O88: =N88/E88 -> #DIV/0! | Q88: =P88/E88 -> #DIV/0! | S88: =R88/E88 -> #DIV/0! | U88: =T88/E88 -> #DIV/0! | V88: =U88+S88+Q88+O88+M88+K88+I88+G88 -> #DIV/0! | W88: =D88 -> 0 | Y88: =D88-W88 -> 0 | AA88: =D88-W88-Y88 -> 0 | AC88: =D88-W88-Y88-AA88 -> 0 | AE88: =D88-W88-Y88-AA88-AC88 -> 0 | AG88: =D88-W88-Y88-AA88-AC88-AE88 -> 0 | AI88: =D88-W88-Y88-AA88-AC88-AE88-AG88 -> 0 | AK88: =D88-W88-Y88-AA88-AC88-AE88-AG88-AI88 -> 0 | AM88: =D88-W88-Y88-AA88-AC88-AE88-AG88-AI88-AK88 -> 0 | AO88: =D88-W88-Y88-AA88-AC88-AE88-AG88-AI88-AK88-AM88 -> 0 | AQ88: =D88-W88-Y88-AA88-AC88-AE88-AG88-AI88-AK88-AM88-AO88 -> 0 | AS88: =D88-W88-Y88-AA88-AC88-AE88-AG88-AI88-AK88-AM88-AO88-AQ88 -> 0 | AU88: =D88-W88-Y88-AA88-AC88-AE88-AG88-AI88-AK88-AM88-AO88-AQ88-AS88 -> 0
A89: DUCHENNE | C89: 21285 | D89: =C89 -> 21285 | E89: =D89 -> 21285 | F89: =4370.78+350-350-1311.23 -> 3059.55 | G89: =F89/E89 -> 0.14374207 | H89: =1822.44-546.73 -> 1275.71 | I89: =H89/E89 -> 0.059934696 | J89: =4242.27-1080.47 -> 3161.8 | K89: =J89/E89 -> 0.14854592 | L89: =5913.81-1261.73 -> 4652.08 | M89: =L89/E89 -> 0.21856143 | N89: 1428.19 | O89: =N89/E89 -> 0.067098426 | P89: 3077.16 | Q89: =P89/E89 -> 0.14456942 | S89: =R89/E89 -> 0 | U89: =T89/E89 -> 0 | V89: =U89+S89+Q89+O89+M89+K89+I89+G89 -> 0.78245196 | W89: 5449 | X89: 5448.85 | Y89: 8857 | Z89: 8857 | AA89: 3738 | AB89: =2348.75+1389.31 -> 3738.06 | AC89: =D89-W89-Y89-AA89 -> 3241 | AD89: 3241.72 | AE89: =D89-W89-Y89-AA89-AC89 -> 0 | AG89: =D89-W89-Y89-AA89-AC89-AE89 -> 0 | AI89: =D89-W89-Y89-AA89-AC89-AE89-AG89 -> 0 | AK89: =D89-W89-Y89-AA89-AC89-AE89-AG89-AI89 -> 0 | AM89: =D89-W89-Y89-AA89-AC89-AE89-AG89-AI89-AK89 -> 0 | AO89: =D89-W89-Y89-AA89-AC89-AE89-AG89-AI89-AK89-AM89 -> 0 | AQ89: =D89-W89-Y89-AA89-AC89-AE89-AG89-AI89-AK89-AM89-AO89 -> 0 | AS89: =D89-W89-Y89-AA89-AC89-AE89-AG89-AI89-AK89-AM89-AO89-AQ89 -> 0 | AU89: =D89-W89-Y89-AA89-AC89-AE89-AG89-AI89-AK89-AM89-AO89-AQ89-AS89 -> 0
A90: RAOULT | C90: ='2020-21'!AS28 -> 0 | D90: =C90 -> 0 | G90: =F90/E90 -> #DIV/0! | I90: =H90/E90 -> #DIV/0! | K90: =J90/E90 -> #DIV/0! | M90: =L90/E90 -> #DIV/0! | O90: =N90/E90 -> #DIV/0! | Q90: =P90/E90 -> #DIV/0! | S90: =R90/E90 -> #DIV/0! | U90: =T90/E90 -> #DIV/0! | V90: =U90+S90+Q90+O90+M90+K90+I90+G90 -> #DIV/0! | W90: =D90 -> 0 | Y90: =D90-W90 -> 0 | AA90: =D90-W90-Y90 -> 0 | AC90: =D90-W90-Y90-AA90 -> 0 | AE90: =D90-W90-Y90-AA90-AC90 -> 0 | AG90: =D90-W90-Y90-AA90-AC90-AE90 -> 0 | AI90: =D90-W90-Y90-AA90-AC90-AE90-AG90 -> 0 | AK90: =D90-W90-Y90-AA90-AC90-AE90-AG90-AI90 -> 0 | AM90: =D90-W90-Y90-AA90-AC90-AE90-AG90-AI90-AK90 -> 0 | AO90: =D90-W90-Y90-AA90-AC90-AE90-AG90-AI90-AK90-AM90 -> 0 | AQ90: =D90-W90-Y90-AA90-AC90-AE90-AG90-AI90-AK90-AM90-AO90 -> 0 | AS90: =D90-W90-Y90-AA90-AC90-AE90-AG90-AI90-AK90-AM90-AO90-AQ90 -> 0 | AU90: =D90-W90-Y90-AA90-AC90-AE90-AG90-AI90-AK90-AM90-AO90-AQ90-AS90 -> 0
A91: FOUQUES mam bassene | C91: ='2020-21'!AS30 -> 0 | D91: =C91 -> 0 | G91: =F91/E91 -> #DIV/0! | I91: =H91/E91 -> #DIV/0! | K91: =J91/E91 -> #DIV/0! | M91: =L91/E91 -> #DIV/0! | O91: =N91/E91 -> #DIV/0! | Q91: =P91/E91 -> #DIV/0! | S91: =R91/E91 -> #DIV/0! | U91: =T91/E91 -> #DIV/0! | V91: =U91+S91+Q91+O91+M91+K91+I91+G91 -> #DIV/0! | W91: =D91 -> 0 | Y91: =D91-W91 -> 0 | AA91: =D91-W91-Y91 -> 0 | AC91: =D91-W91-Y91-AA91 -> 0 | AE91: =D91-W91-Y91-AA91-AC91 -> 0 | AG91: =D91-W91-Y91-AA91-AC91-AE91 -> 0 | AI91: =D91-W91-Y91-AA91-AC91-AE91-AG91 -> 0 | AK91: =D91-W91-Y91-AA91-AC91-AE91-AG91-AI91 -> 0 | AM91: =D91-W91-Y91-AA91-AC91-AE91-AG91-AI91-AK91 -> 0 | AO91: =D91-W91-Y91-AA91-AC91-AE91-AG91-AI91-AK91-AM91 -> 0 | AQ91: =D91-W91-Y91-AA91-AC91-AE91-AG91-AI91-AK91-AM91-AO91 -> 0 | AS91: =D91-W91-Y91-AA91-AC91-AE91-AG91-AI91-AK91-AM91-AO91-AQ91 -> 0 | AU91: =D91-W91-Y91-AA91-AC91-AE91-AG91-AI91-AK91-AM91-AO91-AQ91-AS91 -> 0
A92: CHATELIN | C92: ='2020-21'!AS32 -> 23737 | D92: =C92 -> 23737 | E92: 23737 | F92: =2790-1953.41 -> 836.59 | G92: =F92/E92 -> 0.035244134 | H92: =3204.33-1837.35 -> 1366.98 | I92: =H92/E92 -> 0.057588575 | J92: =6143.12-1413.6 -> 4729.52 | K92: =J92/E92 -> 0.19924675 | L92: =6359.72-1860.32 -> 4499.4 | M92: =L92/E92 -> 0.18955218 | N92: =3884.41-251.49 -> 3632.92 | O92: =N92/E92 -> 0.15304883 | P92: 8670.84 | Q92: =P92/E92 -> 0.36528795 | S92: =R92/E92 -> 0 | U92: =T92/E92 -> 0 | V92: =U92+S92+Q92+O92+M92+K92+I92+G92 -> 0.9999684 | W92: 4416 | X92: 4416.36 | Y92: 9725 | Z92: 9724.53 | AA92: 7516.05 | AB92: 7516.05 | AC92: 1756 | AD92: 1756.49 | AE92: 0 | AG92: =D92-W92-Y92-AA92-AC92-AE92 -> 323.95 | AH92: 324 | AI92: =D92-W92-Y92-AA92-AC92-AE92-AG92 -> 0 | AK92: =D92-W92-Y92-AA92-AC92-AE92-AG92-AI92 -> 0 | AM92: =D92-W92-Y92-AA92-AC92-AE92-AG92-AI92-AK92 -> 0 | AO92: =D92-W92-Y92-AA92-AC92-AE92-AG92-AI92-AK92-AM92 -> 0 | AQ92: =D92-W92-Y92-AA92-AC92-AE92-AG92-AI92-AK92-AM92-AO92 -> 0 | AS92: =D92-W92-Y92-AA92-AC92-AE92-AG92-AI92-AK92-AM92-AO92-AQ92 -> 0 | AU92: =D92-W92-Y92-AA92-AC92-AE92-AG92-AI92-AK92-AM92-AO92-AQ92-AS92 -> 0
A93: BRETAGNE | C93: ='2020-21'!AS34 -> 0 | D93: =C93 -> 0 | G93: =F93/E93 -> #DIV/0! | I93: =H93/E93 -> #DIV/0! | K93: =J93/E93 -> #DIV/0! | M93: =L93/E93 -> #DIV/0! | O93: =N93/E93 -> #DIV/0! | Q93: =P93/E93 -> #DIV/0! | S93: =R93/E93 -> #DIV/0! | U93: =T93/E93 -> #DIV/0! | V93: =U93+S93+Q93+O93+M93+K93+I93+G93 -> #DIV/0! | W93: =D93 -> 0 | Y93: =D93-W93 -> 0 | AA93: =D93-W93-Y93 -> 0 | AC93: =D93-W93-Y93-AA93 -> 0 | AE93: =D93-W93-Y93-AA93-AC93 -> 0 | AG93: =D93-W93-Y93-AA93-AC93-AE93 -> 0 | AI93: =D93-W93-Y93-AA93-AC93-AE93-AG93 -> 0 | AK93: =D93-W93-Y93-AA93-AC93-AE93-AG93-AI93 -> 0 | AM93: =D93-W93-Y93-AA93-AC93-AE93-AG93-AI93-AK93 -> 0 | AO93: =D93-W93-Y93-AA93-AC93-AE93-AG93-AI93-AK93-AM93 -> 0 | AQ93: =D93-W93-Y93-AA93-AC93-AE93-AG93-AI93-AK93-AM93-AO93 -> 0 | AS93: =D93-W93-Y93-AA93-AC93-AE93-AG93-AI93-AK93-AM93-AO93-AQ93 -> 0 | AU93: =D93-W93-Y93-AA93-AC93-AE93-AG93-AI93-AK93-AM93-AO93-AQ93-AS93 -> 0
A94: GERBAULT - IBANESCU | C94: ='2020-21'!AS35-3119 -> 46081 | D94: =C94 -> 46081 | E94: =49200 -> 49200 | F94: =28840.11+900-'2020-21'!F35 -> 168 | G94: =F94/E94 -> 0.0034146341 | H94: =10398.73-'2020-21'!H35 -> 1533.07 | I94: =H94/E94 -> 0.031159959 | J94: =26345.86-'2020-21'!J35 -> 20303.58 | K94: =J94/E94 -> 0.41267439 | L94: =22701.72-'2020-21'!L35 -> 17347.99 | M94: =L94/E94 -> 0.35260142 | N94: =9152.39-'2020-21'!N35 -> 4192.35 | O94: =N94/E94 -> 0.085210366 | Q94: =P94/E94 -> 0 | R94: 5655.43 | S94: =R94/E94 -> 0.11494776 | U94: =T94/E94 -> 0 | V94: =U94+S94+Q94+O94+M94+K94+I94+G94 -> 1.0000085 | W94: 2295 | X94: 2295.19 | Y94: 38353 | Z94: 38352.74 | AA94: 2897.06 | AB94: 2897.06 | AC94: 0 | AG94: 0 | AI94: 0 | AK94: 0 | AM94: 0 | AO94: 0 | AQ94: 5655.43 | AR94: 5655 | AS94: -3119.83 | AT94: -3119.83 | AU94: =D94-W94-Y94-AA94-AC94-AE94-AG94-AI94-AK94-AM94-AO94-AQ94-AS94 -> 0.34
A95: flipo portail | C95: ='2020-21'!AS36 -> 0 | D95: =C95 -> 0 | G95: =F95/E95 -> #DIV/0! | I95: =H95/E95 -> #DIV/0! | K95: =J95/E95 -> #DIV/0! | M95: =L95/E95 -> #DIV/0! | O95: =N95/E95 -> #DIV/0! | Q95: =P95/E95 -> #DIV/0! | R95: 1156 | S95: =R95/E95 -> #DIV/0! | U95: =T95/E95 -> #DIV/0! | V95: =U95+S95+Q95+O95+M95+K95+I95+G95 -> #DIV/0! | W95: =D95 -> 0 | Y95: =D95-W95 -> 0 | AA95: =D95-W95-Y95 -> 0 | AC95: =D95-W95-Y95-AA95 -> 0 | AE95: =D95-W95-Y95-AA95-AC95 -> 0 | AG95: =D95-W95-Y95-AA95-AC95-AE95 -> 0 | AI95: =D95-W95-Y95-AA95-AC95-AE95-AG95 -> 0 | AK95: =D95-W95-Y95-AA95-AC95-AE95-AG95-AI95 -> 0 | AM95: =D95-W95-Y95-AA95-AC95-AE95-AG95-AI95-AK95 -> 0 | AO95: =D95-W95-Y95-AA95-AC95-AE95-AG95-AI95-AK95-AM95 -> 0 | AQ95: =D95-W95-Y95-AA95-AC95-AE95-AG95-AI95-AK95-AM95-AO95 -> 0 | AS95: =D95-W95-Y95-AA95-AC95-AE95-AG95-AI95-AK95-AM95-AO95-AQ95 -> 0 | AU95: =D95-W95-Y95-AA95-AC95-AE95-AG95-AI95-AK95-AM95-AO95-AQ95-AS95 -> 0
A96: LECLEIR | C96: ='2020-21'!AS37 -> 5962.67 | D96: =C96 -> 5962.67 | E96: =D96 -> 5962.67 | F96: 0 | G96: =F96/E96 -> 0 | H96: 0 | I96: =H96/E96 -> 0 | J96: 0 | K96: =J96/E96 -> 0 | L96: =7263.46-6401.03 -> 862.43 | M96: =L96/E96 -> 0.14463822 | N96: 0 | O96: =N96/E96 -> 0 | P96: 5099.61 | Q96: =P96/E96 -> 0.85525612 | S96: =R96/E96 -> 0 | U96: =T96/E96 -> 0 | V96: =U96+S96+Q96+O96+M96+K96+I96+G96 -> 0.99989434 | W96: =D96 -> 5962.67 | X96: 5962.04 | Y96: =D96-W96 -> 0 | AA96: =D96-W96-Y96 -> 0 | AC96: =D96-W96-Y96-AA96 -> 0 | AE96: =D96-W96-Y96-AA96-AC96 -> 0 | AG96: =D96-W96-Y96-AA96-AC96-AE96 -> 0 | AI96: =D96-W96-Y96-AA96-AC96-AE96-AG96 -> 0 | AK96: =D96-W96-Y96-AA96-AC96-AE96-AG96-AI96 -> 0 | AM96: =D96-W96-Y96-AA96-AC96-AE96-AG96-AI96-AK96 -> 0 | AO96: =D96-W96-Y96-AA96-AC96-AE96-AG96-AI96-AK96-AM96 -> 0 | AQ96: =D96-W96-Y96-AA96-AC96-AE96-AG96-AI96-AK96-AM96-AO96 -> 0 | AS96: =D96-W96-Y96-AA96-AC96-AE96-AG96-AI96-AK96-AM96-AO96-AQ96 -> 0 | AU96: =D96-W96-Y96-AA96-AC96-AE96-AG96-AI96-AK96-AM96-AO96-AQ96-AS96 -> 0
A97: PORET | C97: ='2020-21'!AS38 -> 0 | D97: =C97 -> 0 | G97: =F97/E97 -> #DIV/0! | I97: =H97/E97 -> #DIV/0! | K97: =J97/E97 -> #DIV/0! | M97: =L97/E97 -> #DIV/0! | O97: =N97/E97 -> #DIV/0! | Q97: =P97/E97 -> #DIV/0! | S97: =R97/E97 -> #DIV/0! | U97: =T97/E97 -> #DIV/0! | V97: =U97+S97+Q97+O97+M97+K97+I97+G97 -> #DIV/0! | W97: =D97 -> 0 | Y97: =D97-W97 -> 0 | AA97: =D97-W97-Y97 -> 0 | AC97: =D97-W97-Y97-AA97 -> 0 | AE97: =D97-W97-Y97-AA97-AC97 -> 0 | AG97: =D97-W97-Y97-AA97-AC97-AE97 -> 0 | AI97: =D97-W97-Y97-AA97-AC97-AE97-AG97 -> 0 | AK97: =D97-W97-Y97-AA97-AC97-AE97-AG97-AI97 -> 0 | AM97: =D97-W97-Y97-AA97-AC97-AE97-AG97-AI97-AK97 -> 0 | AO97: =D97-W97-Y97-AA97-AC97-AE97-AG97-AI97-AK97-AM97 -> 0 | AQ97: =D97-W97-Y97-AA97-AC97-AE97-AG97-AI97-AK97-AM97-AO97 -> 0 | AS97: =D97-W97-Y97-AA97-AC97-AE97-AG97-AI97-AK97-AM97-AO97-AQ97 -> 0 | AU97: =D97-W97-Y97-AA97-AC97-AE97-AG97-AI97-AK97-AM97-AO97-AQ97-AS97 -> 0
A98: CLET CARON | C98: ='2020-21'!AS39+300.39 -> 21247.69 | D98: =C98-11720.04 -> 9527.65 | E98: =D98 -> 9527.65 | F98: =1125+37272.35+3789.69-'2020-21'!F39 -> 0 | G98: =F98/E98 -> 0 | H98: =15386.94+3582.6+2246.22+8396-'2020-21'!H39 -> 10642.22 | I98: =H98/E98 -> 1.1169827 | J98: =23156.77+868-'2020-21'!J39 -> 0 | K98: =J98/E98 -> 0 | L98: =32120.31+3341.42-'2020-21'!L39 -> 3638.77 | M98: =L98/E98 -> 0.38191684 | N98: =14781.65-'2020-21'!N39 -> 2992.43 | O98: =N98/E98 -> 0.3140785 | P98: =27134.83+3536.67-'2020-21'!P39 -> 3674.25 | Q98: =P98/E98 -> 0.38564074 | S98: =R98/E98 -> 0 | U98: =T98/E98 -> 0 | V98: =U98+S98+Q98+O98+M98+K98+I98+G98 -> 2.1986188 | W98: 5353 | X98: 5353.04 | Y98: 0 | AA98: 0 | AC98: 4175 | AD98: =300.39+15594.63-11720.04 -> 4174.98 | AE98: =D98-W98-Y98-AA98-AC98 -> -0.35 | AG98: =D98-W98-Y98-AA98-AC98-AE98 -> 0 | AI98: =D98-W98-Y98-AA98-AC98-AE98-AG98 -> 0 | AK98: =D98-W98-Y98-AA98-AC98-AE98-AG98-AI98 -> 0 | AM98: =D98-W98-Y98-AA98-AC98-AE98-AG98-AI98-AK98 -> 0 | AO98: =D98-W98-Y98-AA98-AC98-AE98-AG98-AI98-AK98-AM98 -> 0 | AQ98: =D98-W98-Y98-AA98-AC98-AE98-AG98-AI98-AK98-AM98-AO98 -> 0 | AS98: =D98-W98-Y98-AA98-AC98-AE98-AG98-AI98-AK98-AM98-AO98-AQ98 -> 0 | AU98: =D98-W98-Y98-AA98-AC98-AE98-AG98-AI98-AK98-AM98-AO98-AQ98-AS98 -> 0
A99: BICART | C99: ='2020-21'!AS40 -> 0 | D99: =C99 -> 0 | G99: =F99/E99 -> #DIV/0! | I99: =H99/E99 -> #DIV/0! | K99: =J99/E99 -> #DIV/0! | M99: =L99/E99 -> #DIV/0! | O99: =N99/E99 -> #DIV/0! | Q99: =P99/E99 -> #DIV/0! | S99: =R99/E99 -> #DIV/0! | U99: =T99/E99 -> #DIV/0! | V99: =U99+S99+Q99+O99+M99+K99+I99+G99 -> #DIV/0! | W99: =D99 -> 0 | Y99: =D99-W99 -> 0 | AA99: =D99-W99-Y99 -> 0 | AC99: =D99-W99-Y99-AA99 -> 0 | AE99: =D99-W99-Y99-AA99-AC99 -> 0 | AG99: =D99-W99-Y99-AA99-AC99-AE99 -> 0 | AI99: =D99-W99-Y99-AA99-AC99-AE99-AG99 -> 0 | AK99: =D99-W99-Y99-AA99-AC99-AE99-AG99-AI99 -> 0 | AM99: =D99-W99-Y99-AA99-AC99-AE99-AG99-AI99-AK99 -> 0 | AO99: =D99-W99-Y99-AA99-AC99-AE99-AG99-AI99-AK99-AM99 -> 0 | AQ99: =D99-W99-Y99-AA99-AC99-AE99-AG99-AI99-AK99-AM99-AO99 -> 0 | AS99: =D99-W99-Y99-AA99-AC99-AE99-AG99-AI99-AK99-AM99-AO99-AQ99 -> 0 | AU99: =D99-W99-Y99-AA99-AC99-AE99-AG99-AI99-AK99-AM99-AO99-AQ99-AS99 -> 0
A100: MAIRIE EVRECY | C100: ='2020-21'!AS41 -> 0 | D100: =C100 -> 0 | G100: =F100/E100 -> #DIV/0! | I100: =H100/E100 -> #DIV/0! | K100: =J100/E100 -> #DIV/0! | M100: =L100/E100 -> #DIV/0! | O100: =N100/E100 -> #DIV/0! | Q100: =P100/E100 -> #DIV/0! | S100: =R100/E100 -> #DIV/0! | U100: =T100/E100 -> #DIV/0! | V100: =U100+S100+Q100+O100+M100+K100+I100+G100 -> #DIV/0! | W100: =D100 -> 0 | Y100: =D100-W100 -> 0 | AA100: =D100-W100-Y100 -> 0 | AC100: =D100-W100-Y100-AA100 -> 0 | AE100: =D100-W100-Y100-AA100-AC100 -> 0 | AG100: =D100-W100-Y100-AA100-AC100-AE100 -> 0 | AI100: =D100-W100-Y100-AA100-AC100-AE100-AG100 -> 0 | AK100: =D100-W100-Y100-AA100-AC100-AE100-AG100-AI100 -> 0 | AM100: =D100-W100-Y100-AA100-AC100-AE100-AG100-AI100-AK100 -> 0 | AO100: =D100-W100-Y100-AA100-AC100-AE100-AG100-AI100-AK100-AM100 -> 0 | AQ100: =D100-W100-Y100-AA100-AC100-AE100-AG100-AI100-AK100-AM100-AO100 -> 0 | AS100: =D100-W100-Y100-AA100-AC100-AE100-AG100-AI100-AK100-AM100-AO100-AQ100 -> 0 | AU100: =D100-W100-Y100-AA100-AC100-AE100-AG100-AI100-AK100-AM100-AO100-AQ100-AS100 -> 0
A101: HUARD | C101: ='2020-21'!AS42 -> 30889 | D101: =C101 -> 30889 | E101: 30889 | G101: =F101/E101 -> 0 | I101: =H101/E101 -> 0 | K101: =J101/E101 -> 0 | M101: =L101/E101 -> 0 | O101: =N101/E101 -> 0 | Q101: =P101/E101 -> 0 | S101: =R101/E101 -> 0 | U101: =T101/E101 -> 0 | V101: =U101+S101+Q101+O101+M101+K101+I101+G101 -> 0 | W101: 0 | Y101: 0 | AA101: 15168 | AB101: =1499.49+5861.11+7807.11 -> 15167.71 | AC101: 15057 | AD101: =8691+6365.74 -> 15056.74 | AE101: 664 | AF101: =553.07+111.69 -> 664.76 | AG101: =D101-W101-Y101-AA101-AC101-AE101 -> 0 | AI101: =D101-W101-Y101-AA101-AC101-AE101-AG101 -> 0 | AK101: =D101-W101-Y101-AA101-AC101-AE101-AG101-AI101 -> 0 | AM101: =D101-W101-Y101-AA101-AC101-AE101-AG101-AI101-AK101 -> 0 | AO101: =D101-W101-Y101-AA101-AC101-AE101-AG101-AI101-AK101-AM101 -> 0 | AQ101: =D101-W101-Y101-AA101-AC101-AE101-AG101-AI101-AK101-AM101-AO101 -> 0 | AS101: =D101-W101-Y101-AA101-AC101-AE101-AG101-AI101-AK101-AM101-AO101-AQ101 -> 0 | AU101: =D101-W101-Y101-AA101-AC101-AE101-AG101-AI101-AK101-AM101-AO101-AQ101-AS101 -> 0
A102: GUEDON | C102: 41376 | D102: 41376 | E102: 41376 | F102: =21526.05+900-'2020-21'!F43 -> 0 | G102: =F102/E102 -> 0 | H102: =13992.88-13992.88 -> 0 | I102: =H102/E102 -> 0 | J102: =20605-20605 -> 0 | K102: =J102/E102 -> 0 | L102: =26105.24-'2020-21'!L43 -> 15300.92 | M102: =L102/E102 -> 0.36980182 | N102: =7603.21-'2020-21'!N43 -> 3996.28 | O102: =N102/E102 -> 0.096584493 | P102: =22602.28+3997.46-'2020-21'!P43 -> 21986.85 | Q102: =P102/E102 -> 0.53139139 | R102: 7004.72 | S102: =R102/E102 -> 0.16929428 | U102: =T102/E102 -> 0 | V102: =U102+S102+Q102+O102+M102+K102+I102+G102 -> 1.167072 | W102: 19057 | X102: 19057.06 | Y102: 11812 | Z102: 11811.5 | AA102: 0 | AC102: 8630 | AD102: =8565.68 +64.55 -> 8630.23 | AE102: =1849.81+27.65 -> 1877.46 | AF102: 1877 | AG102: =D102-W102-Y102-AA102-AC102-AE102 -> -0.46 | AI102: =D102-W102-Y102-AA102-AC102-AE102-AG102 -> 0 | AK102: =D102-W102-Y102-AA102-AC102-AE102-AG102-AI102 -> 0 | AM102: =D102-W102-Y102-AA102-AC102-AE102-AG102-AI102-AK102 -> 0 | AO102: =D102-W102-Y102-AA102-AC102-AE102-AG102-AI102-AK102-AM102 -> 0 | AQ102: =D102-W102-Y102-AA102-AC102-AE102-AG102-AI102-AK102-AM102-AO102 -> 0 | AS102: =D102-W102-Y102-AA102-AC102-AE102-AG102-AI102-AK102-AM102-AO102-AQ102 -> 0 | AU102: =D102-W102-Y102-AA102-AC102-AE102-AG102-AI102-AK102-AM102-AO102-AQ102-AS102 -> 0
A103: GIRARD double Flux fourniture | C103: 4309.78 | D103: =C103 -> 4309.78 | E103: 4310 | G103: =F103/E103 -> 0 | I103: =H103/E103 -> 0 | K103: =J103/E103 -> 0 | M103: =L103/E103 -> 0 | O103: =N103/E103 -> 0 | Q103: =P103/E103 -> 0 | R103: 4310 | S103: =R103/E103 -> 1 | U103: =T103/E103 -> 0 | V103: =U103+S103+Q103+O103+M103+K103+I103+G103 -> 1 | W103: 0 | Y103: =D103-W103 -> 4309.78 | Z103: 4310 | AA103: =D103-W103-Y103 -> 0 | AC103: =D103-W103-Y103-AA103 -> 0 | AE103: =D103-W103-Y103-AA103-AC103 -> 0 | AG103: =D103-W103-Y103-AA103-AC103-AE103 -> 0 | AI103: =D103-W103-Y103-AA103-AC103-AE103-AG103 -> 0 | AK103: =D103-W103-Y103-AA103-AC103-AE103-AG103-AI103 -> 0 | AM103: =D103-W103-Y103-AA103-AC103-AE103-AG103-AI103-AK103 -> 0 | AO103: =D103-W103-Y103-AA103-AC103-AE103-AG103-AI103-AK103-AM103 -> 0 | AQ103: =D103-W103-Y103-AA103-AC103-AE103-AG103-AI103-AK103-AM103-AO103 -> 0 | AS103: =D103-W103-Y103-AA103-AC103-AE103-AG103-AI103-AK103-AM103-AO103-AQ103 -> 0 | AU103: =D103-W103-Y103-AA103-AC103-AE103-AG103-AI103-AK103-AM103-AO103-AQ103-AS103 -> 0
A104: BOUILLET | C104: ='2020-21'!AS45 -> 0 | D104: =C104 -> 0 | G104: =F104/E104 -> #DIV/0! | I104: =H104/E104 -> #DIV/0! | K104: =J104/E104 -> #DIV/0! | M104: =L104/E104 -> #DIV/0! | O104: =N104/E104 -> #DIV/0! | Q104: =P104/E104 -> #DIV/0! | S104: =R104/E104 -> #DIV/0! | U104: =T104/E104 -> #DIV/0! | V104: =U104+S104+Q104+O104+M104+K104+I104+G104 -> #DIV/0! | W104: =D104 -> 0 | Y104: =D104-W104 -> 0 | AA104: =D104-W104-Y104 -> 0 | AC104: =D104-W104-Y104-AA104 -> 0 | AE104: =D104-W104-Y104-AA104-AC104 -> 0 | AG104: =D104-W104-Y104-AA104-AC104-AE104 -> 0 | AI104: =D104-W104-Y104-AA104-AC104-AE104-AG104 -> 0 | AK104: =D104-W104-Y104-AA104-AC104-AE104-AG104-AI104 -> 0 | AM104: =D104-W104-Y104-AA104-AC104-AE104-AG104-AI104-AK104 -> 0 | AO104: =D104-W104-Y104-AA104-AC104-AE104-AG104-AI104-AK104-AM104 -> 0 | AQ104: =D104-W104-Y104-AA104-AC104-AE104-AG104-AI104-AK104-AM104-AO104 -> 0 | AS104: =D104-W104-Y104-AA104-AC104-AE104-AG104-AI104-AK104-AM104-AO104-AQ104 -> 0 | AU104: =D104-W104-Y104-AA104-AC104-AE104-AG104-AI104-AK104-AM104-AO104-AQ104-AS104 -> 0
...

Sheet 2022-23
F4: OSSATURE | G4: OB | H4: CHARPENTE | I4: CB | J4: MENUISERIE | K4: MX | L4: BARDAGE | M4: BA | N4: ISOLATION | O4: IEA | P4: PLATRERIE | Q4: PII | R4: DIVERS | S4: DIV | T4: ETUDE SUIVI | U4: DIV | V4: COUVERTURE | W4: DIV | Y4: OCTOBRE | AA4: NOVEMBRE | AC4: DECEMBRE | AE4: JANVIER | AG4: FEVRIER | AI4: MARS | AK4: AVRIL | AM4: MAI | AO4: JUIN | AQ4: JUILLET | AS4: AOUT | AU4: SEPTEMBRE
A5: NOM | C5: CA/prevision | D5: CA/contrat | F5: BOIS | G5: % | H5: BOIS | I5: % | J5: EXTERIEURE | K5: % | L5: EXT | M5: % | N5: ETANCHEITE | O5: % | P5: ISO INT MI | Q5: % | S5: % | U5: % | W5: % | Y5: prévu | Z5: réalisé | AA5: prévu | AB5: réalisé | AC5: prévu | AD5: réalisé | AE5: prévu | AF5: réalisé | AG5: prévu | AH5: réalisé | AI5: prévu | AJ5: réalisé | AK5: prévu | AL5: réalisé | AM5: prévu | AN5: réalisé | AO5: prévu | AP5: réalisé | AQ5: prévu | AR5: réalisé | AS5: prévu | AT5: réalisé | AU5: prévu | AV5: réalisé | AW5: 2023/2024
A7: Commission PASQUET
A8: Commission PASQUET
A9: Commission PASQUET | C9: ='2021-22'!AU7 -> 0
A10: Commission PASQUET | C10: ='2021-22'!AU8 -> 0
A11: Commission ST | C11: ='2021-22'!AU9 -> 0
A12: loret avoir | C12: ='2021-22'!AU10 -> 0
G14: =F14/E14 -> #DIV/0! | I14: =H14/E14 -> #DIV/0! | K14: =J14/E14 -> #DIV/0! | M14: =L14/E14 -> #DIV/0! | O14: =N14/E14 -> #DIV/0! | Q14: =P14/E14 -> #DIV/0! | S14: =R14/E14 -> #DIV/0! | U14: =T14/E14 -> #DIV/0! | W14: =V14/E14 -> #DIV/0! | X14: =W14+U14+S14+Q14+O14+M14+K14+I14+G14 -> #DIV/0! | Y14: 0 | AA14: 0 | AC14: 0 | AE14: 0 | AG14: 0 | AI14: 0 | AK14: 0 | AM14: 0 | AQ14: =D14-Y14-AA14-AC14-AE14-AG14-AI14-AK14-AM14-AO14 -> 0 | AS14: =D14-Y14-AA14-AC14-AE14-AG14-AI14-AK14-AM14-AO14-AQ14 -> 0 | AU14: =D14-Y14-AA14-AC14-AE14-AG14-AI14-AK14-AM14-AO14-AQ14-AS14 -> 0 | AW14: =D14-Y14-AA14-AC14-AE14-AG14-AI14-AK14-AM14-AO14-AQ14-AS14-AU14 -> 0
G15: =F15/E15 -> #DIV/0! | I15: =H15/E15 -> #DIV/0! | K15: =J15/E15 -> #DIV/0! | M15: =L15/E15 -> #DIV/0! | O15: =N15/E15 -> #DIV/0! | Q15: =P15/E15 -> #DIV/0! | S15: =R15/E15 -> #DIV/0! | U15: =T15/E15 -> #DIV/0! | W15: =V15/E15 -> #DIV/0! | X15: =W15+U15+S15+Q15+O15+M15+K15+I15+G15 -> #DIV/0! | Y15: 0 | AA15: =D15-Y15 -> 0 | AC15: =D15-Y15-AA15 -> 0 | AE15: =D15-Y15-AA15-AC15 -> 0 | AG15: =D15-Y15-AA15-AC15-AE15 -> 0 | AI15: =D15-Y15-AA15-AC15-AE15-AG15 -> 0 | AK15: =D15-Y15-AA15-AC15-AE15-AG15-AI15 -> 0 | AM15: =D15-Y15-AA15-AC15-AE15-AG15-AI15-AK15 -> 0 | AO15: =D15-Y15-AA15-AC15-AE15-AG15-AI15-AK15-AM15 -> 0 | AQ15: =D15-Y15-AA15-AC15-AE15-AG15-AI15-AK15-AM15-AO15 -> 0 | AS15: =D15-Y15-AA15-AC15-AE15-AG15-AI15-AK15-AM15-AO15-AQ15 -> 0 | AU15: =D15-Y15-AA15-AC15-AE15-AG15-AI15-AK15-AM15-AO15-AQ15-AS15 -> 0 | AW15: =D15-Y15-AA15-AC15-AE15-AG15-AI15-AK15-AM15-AO15-AQ15-AS15-AU15 -> 0
G16: =F16/E16 -> #DIV/0! | I16: =H16/E16 -> #DIV/0! | K16: =J16/E16 -> #DIV/0! | M16: =L16/E16 -> #DIV/0! | O16: =N16/E16 -> #DIV/0! | Q16: =P16/E16 -> #DIV/0! | S16: =R16/E16 -> #DIV/0! | U16: =T16/E16 -> #DIV/0! | W16: =V16/E16 -> #DIV/0! | X16: =W16+U16+S16+Q16+O16+M16+K16+I16+G16 -> #DIV/0! | Y16: 0 | AA16: =D16-Y16 -> 0 | AC16: =D16-Y16-AA16 -> 0 | AE16: =D16-Y16-AA16-AC16 -> 0 | AG16: =D16-Y16-AA16-AC16-AE16 -> 0 | AI16: =D16-Y16-AA16-AC16-AE16-AG16 -> 0 | AK16: =D16-Y16-AA16-AC16-AE16-AG16-AI16 -> 0 | AM16: =D16-Y16-AA16-AC16-AE16-AG16-AI16-AK16 -> 0 | AO16: =D16-Y16-AA16-AC16-AE16-AG16-AI16-AK16-AM16 -> 0 | AQ16: =D16-Y16-AA16-AC16-AE16-AG16-AI16-AK16-AM16-AO16 -> 0 | AS16: =D16-Y16-AA16-AC16-AE16-AG16-AI16-AK16-AM16-AO16-AQ16 -> 0 | AU16: =D16-Y16-AA16-AC16-AE16-AG16-AI16-AK16-AM16-AO16-AQ16-AS16 -> 0 | AW16: =D16-Y16-AA16-AC16-AE16-AG16-AI16-AK16-AM16-AO16-AQ16-AS16-AU16 -> 0
G17: =F17/E17 -> #DIV/0! | I17: =H17/E17 -> #DIV/0! | K17: =J17/E17 -> #DIV/0! | M17: =L17/E17 -> #DIV/0! | O17: =N17/E17 -> #DIV/0! | Q17: =P17/E17 -> #DIV/0! | S17: =R17/E17 -> #DIV/0! | U17: =T17/E17 -> #DIV/0! | W17: =V17/E17 -> #DIV/0! | X17: =W17+U17+S17+Q17+O17+M17+K17+I17+G17 -> #DIV/0! | Y17: 0 | AA17: =D17-Y17 -> 0 | AC17: =D17-Y17-AA17 -> 0 | AE17: =D17-Y17-AA17-AC17 -> 0 | AG17: =D17-Y17-AA17-AC17-AE17 -> 0 | AI17: =D17-Y17-AA17-AC17-AE17-AG17 -> 0 | AK17: =D17-Y17-AA17-AC17-AE17-AG17-AI17 -> 0 | AM17: =D17-Y17-AA17-AC17-AE17-AG17-AI17-AK17 -> 0 | AO17: =D17-Y17-AA17-AC17-AE17-AG17-AI17-AK17-AM17 -> 0 | AQ17: =D17-Y17-AA17-AC17-AE17-AG17-AI17-AK17-AM17-AO17 -> 0 | AS17: =D17-Y17-AA17-AC17-AE17-AG17-AI17-AK17-AM17-AO17-AQ17 -> 0 | AU17: =D17-Y17-AA17-AC17-AE17-AG17-AI17-AK17-AM17-AO17-AQ17-AS17 -> 0 | AW17: =D17-Y17-AA17-AC17-AE17-AG17-AI17-AK17-AM17-AO17-AQ17-AS17-AU17 -> 0
G18: =F18/E18 -> #DIV/0! | I18: =H18/E18 -> #DIV/0! | K18: =J18/E18 -> #DIV/0! | M18: =L18/E18 -> #DIV/0! | O18: =N18/E18 -> #DIV/0! | Q18: =P18/E18 -> #DIV/0! | S18: =R18/E18 -> #DIV/0! | U18: =T18/E18 -> #DIV/0! | W18: =V18/E18 -> #DIV/0! | X18: =W18+U18+S18+Q18+O18+M18+K18+I18+G18 -> #DIV/0! | Y18: 0 | AA18: =D18-Y18 -> 0 | AC18: =D18-Y18-AA18 -> 0 | AE18: =D18-Y18-AA18-AC18 -> 0 | AG18: =D18-Y18-AA18-AC18-AE18 -> 0 | AI18: =D18-Y18-AA18-AC18-AE18-AG18 -> 0 | AK18: =D18-Y18-AA18-AC18-AE18-AG18-AI18 -> 0 | AM18: =D18-Y18-AA18-AC18-AE18-AG18-AI18-AK18 -> 0 | AO18: =D18-Y18-AA18-AC18-AE18-AG18-AI18-AK18-AM18 -> 0 | AQ18: =D18-Y18-AA18-AC18-AE18-AG18-AI18-AK18-AM18-AO18 -> 0 | AS18: =D18-Y18-AA18-AC18-AE18-AG18-AI18-AK18-AM18-AO18-AQ18 -> 0 | AU18: =D18-Y18-AA18-AC18-AE18-AG18-AI18-AK18-AM18-AO18-AQ18-AS18 -> 0 | AW18: =D18-Y18-AA18-AC18-AE18-AG18-AI18-AK18-AM18-AO18-AQ18-AS18-AU18 -> 0
A19: CHATELET | C19: 85260 | D19: 85260 | G19: =F19/E19 -> #DIV/0! | I19: =H19/E19 -> #DIV/0! | K19: =J19/E19 -> #DIV/0! | M19: =L19/E19 -> #DIV/0! | O19: =N19/E19 -> #DIV/0! | Q19: =P19/E19 -> #DIV/0! | S19: =R19/E19 -> #DIV/0! | U19: =T19/E19 -> #DIV/0! | W19: =V19/E19 -> #DIV/0! | X19: =W19+U19+S19+Q19+O19+M19+K19+I19+G19 -> #DIV/0! | Y19: 0 | AA19: 0 | AC19: 0 | AE19: 0 | AG19: 0 | AI19: 0 | AK19: 0 | AM19: 0 | AO19: 0 | AQ19: 0 | AS19: 0 | AU19: 0 | AW19: =D19-Y19-AA19-AC19-AE19-AG19-AI19-AK19-AM19-AO19-AQ19-AS19-AU19 -> 85260
A20: BLOTTIERE LAMARRE | C20: 7252.87 | D20: =C20 -> 7252.87 | E20: =D20 -> 7252.87 | G20: =F20/E20 -> 0 | H20: =E20 -> 7252.87 | I20: =H20/E20 -> 1 | K20: =J20/E20 -> 0 | M20: =L20/E20 -> 0 | O20: =N20/E20 -> 0 | Q20: =P20/E20 -> 0 | S20: =R20/E20 -> 0 | U20: =T20/E20 -> 0 | W20: =V20/E20 -> 0 | X20: =W20+U20+S20+Q20+O20+M20+K20+I20+G20 -> 1 | Y20: 0 | AA20: 0 | AC20: 0 | AE20: 0 | AG20: 0 | AI20: 0 | AK20: 0 | AM20: 0 | AO20: 0 | AQ20: 0 | AS20: 0 | AU20: 0 | AW20: =D20-Y20-AA20-AC20-AE20-AG20-AI20-AK20-AM20-AO20-AQ20-AS20-AU20 -> 7252.87
A21: ARTU MAUBANC | C21: 3111.05 | D21: 3111.05 | E21: 3111 | G21: =F21/E21 -> 0 | I21: =H21/E21 -> 0 | K21: =J21/E21 -> 0 | M21: =L21/E21 -> 0 | N21: 3111 | O21: =N21/E21 -> 1 | Q21: =P21/E21 -> 0 | S21: =R21/E21 -> 0 | U21: =T21/E21 -> 0 | W21: =V21/E21 -> 0 | X21: =W21+U21+S21+Q21+O21+M21+K21+I21+G21 -> 1 | Y21: 0 | AA21: 0 | AC21: 0 | AE21: 0 | AG21: 0 | AI21: 0 | AK21: 0 | AM21: 0 | AO21: 0 | AQ21: 0 | AS21: 0 | AU21: 3111.05 | AV21: 3111 | AW21: =D21-Y21-AA21-AC21-AE21-AG21-AI21-AK21-AM21-AO21-AQ21-AS21-AU21 -> 0
A22: LE CUZIAT | C22: 20301.5 | D22: 20302 | E22: 20302 | G22: =F22/E22 -> 0 | I22: =H22/E22 -> 0 | K22: =J22/E22 -> 0 | M22: =L22/E22 -> 0 | O22: =N22/E22 -> 0 | Q22: =P22/E22 -> 0 | S22: =R22/E22 -> 0 | U22: =T22/E22 -> 0 | W22: =V22/E22 -> 0 | X22: =W22+U22+S22+Q22+O22+M22+K22+I22+G22 -> 0 | Y22: 0 | AA22: 0 | AC22: 0 | AE22: 0 | AG22: 0 | AI22: 0 | AK22: 0 | AM22: 0 | AO22: 0 | AQ22: 0 | AS22: 0 | AW22: =D22-Y22-AA22-AC22-AE22-AG22-AI22-AK22-AM22-AO22-AQ22-AS22-AU22 -> 20302
A23: GABARD | C23: 5311.94 | D23: 5312 | E23: 5312 | G23: =F23/E23 -> 0 | I23: =H23/E23 -> 0 | K23: =J23/E23 -> 0 | M23: =L23/E23 -> 0 | O23: =N23/E23 -> 0 | Q23: =P23/E23 -> 0 | S23: =R23/E23 -> 0 | U23: =T23/E23 -> 0 | W23: =V23/E23 -> 0 | X23: =W23+U23+S23+Q23+O23+M23+K23+I23+G23 -> 0 | Y23: 0 | AA23: 0 | AC23: 0 | AE23: 0 | AG23: 0 | AI23: 0 | AK23: 0 | AM23: 0 | AO23: 0 | AQ23: 0 | AS23: 0 | AU23: 0 | AW23: =D23-Y23-AA23-AC23-AE23-AG23-AI23-AK23-AM23-AO23-AQ23-AS23-AU23 -> 5312
A24: LOCKQUEST | C24: 15674 | D24: 15674 | E24: 15674 | F24: 0 | G24: =F24/E24 -> 0 | I24: =H24/E24 -> 0 | K24: =J24/E24 -> 0 | M24: =L24/E24 -> 0 | O24: =N24/E24 -> 0 | Q24: =P24/E24 -> 0 | S24: =R24/E24 -> 0 | T24: 0 | U24: =T24/E24 -> 0 | W24: =V24/E24 -> 0 | X24: =W24+U24+S24+Q24+O24+M24+K24+I24+G24 -> 0 | Y24: 0 | AA24: 0 | AC24: 0 | AE24: 0 | AG24: 0 | AI24: 0 | AK24: 0 | AM24: 0 | AO24: 0 | AQ24: 0 | AS24: 0 | AU24: 0 | AW24: =D24-Y24-AA24-AC24-AE24-AG24-AI24-AK24-AM24-AO24-AQ24-AS24-AU24 -> 15674
A25: KLEBANER | C25: 7249 | D25: 7249 | E25: 7249 | G25: =F25/E25 -> 0 | I25: =H25/E25 -> 0 | K25: =J25/E25 -> 0 | M25: =L25/E25 -> 0 | O25: =N25/E25 -> 0 | Q25: =P25/E25 -> 0 | R25: 0 | S25: =R25/E25 -> 0 | U25: =T25/E25 -> 0 | W25: =V25/E25 -> 0 | X25: =W25+U25+S25+Q25+O25+M25+K25+I25+G25 -> 0 | Y25: 0 | AA25: 0 | AC25: 0 | AE25: 0 | AG25: 0 | AI25: 0 | AK25: 0 | AM25: 0 | AO25: 0 | AQ25: 0 | AS25: 0 | AU25: 0 | AW25: =D25-Y25-AA25-AC25-AE25-AG25-AI25-AK25-AM25-AO25-AQ25-AS25-AU25 -> 7249
A26: ALLEMAGNE | C26: =10948+44134 -> 55082 | D26: 55082 | E26: 55082 | G26: =F26/E26 -> 0 | I26: =H26/E26 -> 0 | K26: =J26/E26 -> 0 | L26: 0 | M26: =L26/E26 -> 0 | O26: =N26/E26 -> 0 | P26: 10948 | Q26: =P26/E26 -> 0.19875822 | S26: =R26/E26 -> 0 | U26: =T26/E26 -> 0 | W26: =V26/E26 -> 0 | X26: =W26+U26+S26+Q26+O26+M26+K26+I26+G26 -> 0.19875822 | Y26: 0 | AA26: 0 | AC26: 0 | AE26: 0 | AG26: 0 | AI26: 0 | AK26: 0 | AM26: 0 | AO26: 0 | AQ26: 4897.36 | AR26: 4897.36 | AS26: 0 | AU26: 0 | AW26: =D26-Y26-AA26-AC26-AE26-AG26-AI26-AK26-AM26-AO26-AQ26-AS26-AU26 -> 50184.64
A27: VITAL SPORT IFS | C27: 5832 | D27: 5832 | E27: 5832 | G27: =F27/E27 -> 0 | I27: =H27/E27 -> 0 | K27: =J27/E27 -> 0 | M27: =L27/E27 -> 0 | O27: =N27/E27 -> 0 | Q27: =P27/E27 -> 0 | R27: 5832 | S27: =R27/E27 -> 1 | U27: =T27/E27 -> 0 | W27: =V27/E27 -> 0 | X27: =W27+U27+S27+Q27+O27+M27+K27+I27+G27 -> 1 | Y27: 0 | AA27: 0 | AC27: 0 | AE27: 0 | AG27: 0 | AI27: 0 | AK27: 0 | AM27: 0 | AO27: 0 | AQ27: 5831.78 | AR27: 5831.78 | AS27: =D27-Y27-AA27-AC27-AE27-AG27-AI27-AK27-AM27-AO27-AQ27 -> 0.22 | AU27: =D27-Y27-AA27-AC27-AE27-AG27-AI27-AK27-AM27-AO27-AQ27-AS27 -> 0 | AW27: =D27-Y27-AA27-AC27-AE27-AG27-AI27-AK27-AM27-AO27-AQ27-AS27-AU27 -> 0
A28: DELENTECOMMELCHAL | C28: 16680.13 | D28: =C28 -> 16680.13 | E28: =D28 -> 16680.13 | G28: =F28/E28 -> 0 | I28: =H28/E28 -> 0 | J28: 24354 | K28: =J28/E28 -> 1.4600606 | M28: =L28/E28 -> 0 | O28: =N28/E28 -> 0 | Q28: =P28/E28 -> 0 | S28: =R28/E28 -> 0 | U28: =T28/E28 -> 0 | W28: =V28/E28 -> 0 | X28: =W28+U28+S28+Q28+O28+M28+K28+I28+G28 -> 1.4600606 | Y28: 0 | AA28: 0 | AC28: 0 | AE28: 0 | AG28: 0 | AI28: 0 | AK28: 0 | AM28: 0 | AO28: 0 | AQ28: 0 | AS28: 11870 | AT28: 11869.69 | AU28: 0 | AW28: =D28-Y28-AA28-AC28-AE28-AG28-AI28-AK28-AM28-AO28-AQ28-AS28-AU28 -> 4810.13
A29: SCI NOMELANI | C29: 42678 | D29: 42678 | G29: =F29/E29 -> #DIV/0! | I29: =H29/E29 -> #DIV/0! | K29: =J29/E29 -> #DIV/0! | M29: =L29/E29 -> #DIV/0! | O29: =N29/E29 -> #DIV/0! | Q29: =P29/E29 -> #DIV/0! | S29: =R29/E29 -> #DIV/0! | U29: =T29/E29 -> #DIV/0! | W29: =V29/E29 -> #DIV/0! | X29: =W29+U29+S29+Q29+O29+M29+K29+I29+G29 -> #DIV/0! | Y29: 0 | AA29: 0 | AC29: 0 | AE29: 0 | AG29: 0 | AI29: 0 | AK29: 0 | AM29: 0 | AO29: 0 | AQ29: 0 | AS29: 0 | AU29: 0 | AW29: =D29-Y29-AA29-AC29-AE29-AG29-AI29-AK29-AM29-AO29-AQ29-AS29-AU29 -> 42678
A30: HARDOIN | C30: 37950 | D30: =4494.21+8009.66+25069.84 -> 37573.71 | E30: =D30 -> 37573.71 | G30: =F30/E30 -> 0 | I30: =H30/E30 -> 0 | J30: 4494 | K30: =J30/E30 -> 0.1196049 | M30: =L30/E30 -> 0 | N30: 25070 | O30: =N30/E30 -> 0.66722184 | P30: =8386+7585+11054+3863-25070 -> 5818 | Q30: =P30/E30 -> 0.15484231 | S30: =R30/E30 -> 0 | T30: 2568 | U30: =T30/E30 -> 0.06834566 | W30: =V30/E30 -> 0 | X30: =W30+U30+S30+Q30+O30+M30+K30+I30+G30 -> 1.0100147 | Y30: 0 | AA30: 0 | AC30: 0 | AE30: 0 | AG30: 0 | AI30: 0 | AK30: 0 | AM30: 0 | AO30: 0 | AQ30: 0 | AS30: 0 | AU30: 13397 | AV30: 13397.49 | AW30: =D30-Y30-AA30-AC30-AE30-AG30-AI30-AK30-AM30-AO30-AQ30-AS30-AU30 -> 24176.71
A31: FERRARO | C31: 909.09 | D31: 909 | E31: 909 | G31: =F31/E31 -> 0 | H31: 909 | I31: =H31/E31 -> 1 | K31: =J31/E31 -> 0 | M31: =L31/E31 -> 0 | O31: =N31/E31 -> 0 | Q31: =P31/E31 -> 0 | S31: =R31/E31 -> 0 | U31: =T31/E31 -> 0 | W31: =V31/E31 -> 0 | X31: =W31+U31+S31+Q31+O31+M31+K31+I31+G31 -> 1 | Y31: 0 | AA31: 0 | AC31: 0 | AE31: 0 | AG31: 0 | AI31: 0 | AK31: 0 | AM31: 0 | AO31: =D31-Y31-AA31-AC31-AE31-AG31-AI31-AK31-AM31 -> 909 | AP31: 909.09 | AQ31: =D31-Y31-AA31-AC31-AE31-AG31-AI31-AK31-AM31-AO31 -> 0 | AS31: =D31-Y31-AA31-AC31-AE31-AG31-AI31-AK31-AM31-AO31-AQ31 -> 0 | AU31: =D31-Y31-AA31-AC31-AE31-AG31-AI31-AK31-AM31-AO31-AQ31-AS31 -> 0 | AW31: =D31-Y31-AA31-AC31-AE31-AG31-AI31-AK31-AM31-AO31-AQ31-AS31-AU31 -> 0
A32: POCHAT | C32: 67172.28 | D32: 67172.28 | E32: 69467 | F32: 9467 | G32: =F32/E32 -> 0.13628054 | H32: 5575 | I32: =H32/E32 -> 0.080253934 | J32: 9903 | K32: =J32/E32 -> 0.1425569 | L32: 4915 | M32: =L32/E32 -> 0.070753019 | N32: 5807 | O32: =N32/E32 -> 0.083593649 | P32: =13064+1334 -> 14398 | Q32: =P32/E32 -> 0.20726388 | S32: =R32/E32 -> 0 | T32: 6998 | U32: =T32/E32 -> 0.10073848 | V32: 12403 | W32: =V32/E32 -> 0.17854521 | X32: =W32+U32+S32+Q32+O32+M32+K32+I32+G32 -> 0.9999856 | Y32: 0 | AA32: 0 | AC32: 0 | AE32: 0 | AG32: 0 | AI32: 0 | AK32: 0 | AM32: 0 | AO32: 0 | AQ32: 0 | AS32: 0 | AU32: 27064 | AV32: 27063.87 | AW32: =D32-Y32-AA32-AC32-AE32-AG32-AI32-AK32-AM32-AO32-AQ32-AS32-AU32 -> 40108.28
A33: DELORME | C33: 9758.56 | D33: 9759 | E33: 9759 | G33: =F33/E33 -> 0 | I33: =H33/E33 -> 0 | K33: =J33/E33 -> 0 | M33: =L33/E33 -> 0 | O33: =N33/E33 -> 0 | Q33: =P33/E33 -> 0 | R33: 9759 | S33: =R33/E33 -> 1 | U33: =T33/E33 -> 0 | W33: =V33/E33 -> 0 | X33: =W33+U33+S33+Q33+O33+M33+K33+I33+G33 -> 1 | Y33: 0 | AA33: 0 | AC33: 0 | AE33: 0 | AG33: 0 | AI33: 0 | AK33: 0 | AM33: 1683 | AN33: 1683.07 | AO33: 5489 | AP33: 5489.02 | AQ33: 0 | AS33: 0 | AU33: 0 | AW33: =D33-Y33-AA33-AC33-AE33-AG33-AI33-AK33-AM33-AO33-AQ33-AS33-AU33 -> 2587
A34: PERIOT | C34: 111277.97 | D34: 111278 | G34: =F34/E34 -> #DIV/0! | I34: =H34/E34 -> #DIV/0! | K34: =J34/E34 -> #DIV/0! | M34: =L34/E34 -> #DIV/0! | O34: =N34/E34 -> #DIV/0! | Q34: =P34/E34 -> #DIV/0! | S34: =R34/E34 -> #DIV/0! | U34: =T34/E34 -> #DIV/0! | W34: =V34/E34 -> #DIV/0! | X34: =W34+U34+S34+Q34+O34+M34+K34+I34+G34 -> #DIV/0! | Y34: 0 | AA34: 0 | AC34: 0 | AE34: 0 | AG34: 0 | AI34: 0 | AK34: 0 | AM34: 0 | AO34: 0 | AQ34: 0 | AS34: 0 | AU34: 0 | AW34: =D34-Y34-AA34-AC34-AE34-AG34-AI34-AK34-AM34-AO34-AQ34-AS34-AU34 -> 111278
A35: GAUGUIN | C35: 52511 | D35: 52511 | E35: 52511 | F35: =7033+634 -> 7667 | G35: =F35/E35 -> 0.1460075 | H35: 4643 | I35: =H35/E35 -> 0.088419569 | J35: 9085 | K35: =J35/E35 -> 0.17301137 | L35: =1632+10335 -> 11967 | M35: =L35/E35 -> 0.22789511 | N35: 3324 | O35: =N35/E35 -> 0.063301023 | P35: =5329+245 -> 5574 | Q35: =P35/E35 -> 0.10614919 | S35: =R35/E35 -> 0 | T35: 3128 | U35: =T35/E35 -> 0.059568471 | V35: 7122 | W35: =V35/E35 -> 0.13562873 | X35: =W35+U35+S35+Q35+O35+M35+K35+I35+G35 -> 0.99998096 | Y35: 0 | AA35: 0 | AC35: 0 | AE35: 0 | AG35: 0 | AI35: 0 | AK35: 0 | AM35: 0 | AO35: 0 | AQ35: 0 | AS35: 0 | AU35: 0 | AW35: =D35-Y35-AA35-AC35-AE35-AG35-AI35-AK35-AM35-AO35-AQ35-AS35-AU35 -> 52511
A36: DUFOUR | C36: 54245.46 | D36: 51622 | G36: =F36/E36 -> #DIV/0! | I36: =H36/E36 -> #DIV/0! | K36: =J36/E36 -> #DIV/0! | M36: =L36/E36 -> #DIV/0! | O36: =N36/E36 -> #DIV/0! | Q36: =P36/E36 -> #DIV/0! | S36: =R36/E36 -> #DIV/0! | U36: =T36/E36 -> #DIV/0! | W36: =V36/E36 -> #DIV/0! | X36: =W36+U36+S36+Q36+O36+M36+K36+I36+G36 -> #DIV/0! | Y36: 0 | AA36: 0 | AC36: 0 | AE36: 0 | AG36: 0 | AI36: 0 | AK36: 0 | AM36: 0 | AO36: 0 | AQ36: 0 | AS36: 0 | AU36: 0 | AW36: =D36-Y36-AA36-AC36-AE36-AG36-AI36-AK36-AM36-AO36-AQ36-AS36-AU36 -> 51622
A37: BILLOIN HEUGUEBART | C37: 106000 | D37: 106000 | G37: =F37/E37 -> #DIV/0! | I37: =H37/E37 -> #DIV/0! | K37: =J37/E37 -> #DIV/0! | M37: =L37/E37 -> #DIV/0! | O37: =N37/E37 -> #DIV/0! | Q37: =P37/E37 -> #DIV/0! | S37: =R37/E37 -> #DIV/0! | U37: =T37/E37 -> #DIV/0! | W37: =V37/E37 -> #DIV/0! | X37: =W37+U37+S37+Q37+O37+M37+K37+I37+G37 -> #DIV/0! | Y37: 0 | AA37: 0 | AC37: 0 | AE37: 0 | AG37: 0 | AI37: 0 | AK37: 0 | AM37: 0 | AO37: 0 | AQ37: 0 | AS37: 0 | AU37: 0 | AW37: =D37-Y37-AA37-AC37-AE37-AG37-AI37-AK37-AM37-AO37-AQ37-AS37-AU37 -> 106000
A38: SAVARY | C38: 59982 | D38: =E38 -> 66485.7 | E38: =59982+6503.7 -> 66485.7 | F38: 8738.26 | G38: =F38/E38 -> 0.13143067 | H38: 5649.72 | I38: =H38/E38 -> 0.084976469 | J38: 10859.36 | K38: =J38/E38 -> 0.16333377 | L38: 1667.48 | M38: =L38/E38 -> 0.02508028 | N38: 3178.61 | O38: =N38/E38 -> 0.047808927 | P38: 7312.4 | Q38: =P38/E38 -> 0.10998455 | S38: =R38/E38 -> 0 | T38: 1260 | U38: =T38/E38 -> 0.018951444 | V38: =13555.82+7760.89 -> 21316.71 | W38: =V38/E38 -> 0.32062098 | X38: =W38+U38+S38+Q38+O38+M38+K38+I38+G38 -> 0.90218709 | Y38: 0 | AA38: 0 | AC38: 0 | AE38: 0 | AG38: 0 | AI38: 0 | AK38: 0 | AM38: 0 | AO38: 0 | AQ38: 35130 | AR38: 35129.61 | AS38: 4176 | AT38: 4176 | AU38: =AV38 -> 23803.18 | AV38: =20676.97+3126.21 -> 23803.18 | AW38: =D38-Y38-AA38-AC38-AE38-AG38-AI38-AK38-AM38-AO38-AQ38-AS38-AU38 -> 3376.52
A39: lavoir 3 perrieres | C39: 10614 | D39: 10614 | E39: 10614 | G39: =F39/E39 -> 0 | H39: 5253 | I39: =H39/E39 -> 0.49491238 | K39: =J39/E39 -> 0 | M39: =L39/E39 -> 0 | O39: =N39/E39 -> 0 | Q39: =P39/E39 -> 0 | S39: =R39/E39 -> 0 | T39: 352 | U39: =T39/E39 -> 0.033163746 | V39: 5008 | W39: =V39/E39 -> 0.47182966 | X39: =W39+U39+S39+Q39+O39+M39+K39+I39+G39 -> 0.99990578 | Y39: 0 | AA39: 0 | AC39: 0 | AE39: 0 | AG39: 0 | AI39: 0 | AK39: 0 | AM39: 0 | AO39: 0 | AQ39: 0 | AS39: 0 | AU39: 0 | AW39: =D39-Y39-AA39-AC39-AE39-AG39-AI39-AK39-AM39-AO39-AQ39-AS39-AU39 -> 10614
